Workbook

Sheet Лист3
A4: 09,03,2022 | B4: MAMATOVA YULDUZ DAVLATOVNA | C4: 98529134 | F4: 99 212 73 78 Iqush og`a Beruniy | H4: 2 | J4: 4
A5: 20,02,2022 | B5: YUSUPOVA NAZOKAT OTAXONOVNA( Otabek ) | C5: 40509212 | H5: 1 | J5: 77 028 77 81
A6: 10,03,2022 | B6: Jo`shqin og`a | F6: madaniyat | G6: 20 mln Jo`shqin og`ani o`zi | H6: 20 | J6: 9
A7: 23,03,2022 | F7: Nurafshon | G7: Nurafshon 77 033 91 01 karuch zavod | H7: =18.8*2 -> 37.6 | K7: 2
A8: 25,03,2022 | B8: MAMIYEVA ALIYAJAN MUMINOVNA | C8: 26706601 | E8: 20 | F8: Tozabozor | G8: Tozabozor Egamov Baxtiyor
A9: 25,03,2022 | B9: JUMANIYAZOV MARKS XO‘JANIYOZOVICH | C9: 75591482 | E9: 23 | F9: Madaniyat | G9: Madaniyat
A10: 29,03,2022 | B10: ATABAYEV GANJABOY JUMANAZAROVICH | C10: 97198640 | E10: 23 | F10: Tozabozor | G10: 32 mln rulli Tozabozor sahrtnomaga qarab turibdi 97 600 14 65
A11: 30,03,2022 | B11: OLLASHOVA DILRABO QURAMBOYEVNA | C11: 69346425 | E11: 18 | F11: Yangiariq | G11: Yangiariq 97 753 7313 97 601 95 95
A12: 30,03,2022 | B12: MADAMINOVA GULRUX TO‘LQIN | C12: 29675034 | E12: 22 | F12: Г | G12: Manaviyat 99 752 34 30
A13: 30,03,2022 | B13: XUDAYBERGANOV JO‘RABEK BOBONAZAROVICH | C13: 41699722 | D13: navbatda | E13: 22 | F13: Nurli Hayot | G13: Nurli hayot 94 860 58 87 | L13: 23,05,2023
A14: 31,03,2022 | B14: BAKIYEV HAMDAMBEK TOJIBOYEVICH | C14: 11498321 | E14: 22.5 | F14: 22.5 | G14: Nurafshon klient 99 122 61 52 | L14: 30,05,2023
A15: 31,03,2022 | B15: JUMANAZAROV NIZOMJON OZOD O‘G‘LI | C15: 30183671 | F15: Qalajiqala | G15: Qalajiqala 99 175 55 15
A16: 31,03,2022 | B16: JUMANAZAROV SAPARBOY MATCHONOVICH | E16: 25 | F16: madaniyat | G16: Mirzoxid og`a | J16: 2
A17: 31,03,2022 | B17: JABBAROV ISLOMBEK ABDULLAYEVICH | C17: 91142276 | E17: 25 | F17: madaniyat | G17: Mirzoxid og`a | J17: 3
A18: 31,03,2022 | B18: ABDULLAYEV DIYORBEK | C18: 19605444 | D18: navbatda | F18: madaniyat | G18: Tozabozor 97 091 17 95 | J18: 4
A19: 31,03,2022 | B19: MATYAQUBOV QODAMBOY YULDASHOVICH | C19: 81026374 | F19: madaniyat | G19: Toyir og`a | J19: 5 6
A20: 01,04,2023 | B20: JUMABOYEV HASANBOY QAHRAMON O‘G‘LI | C20: 72673422 | F20: Nurafshon | G20: Nurafshon 94 312 50 69 | L20: 04,05,2023
A21: 01,04,2023 | B21: XO‘JANIYOZOV MARDON BAXTIYOROVICH | C21: 29829339 | F21: madaniyat | G21: Nurafshon 93 467 15 14 | J21: 7 | L21: 04,05,2023
A22: 01,04,2023 | B22: OTAJONOVA GULYOR HAYITBOY QIZ | C22: 67505033 | E22: 25 | F22: madaniyat | G22: Qalajiqala 94 112 77 66 | J22: 8
A23: 02,04,2023 | B23: TILLAYEV BOZORBOY RO‘ZIYEVICH | C23: 34772565 | F23: Oq tepa | G23: Oq tepa 99 176 86 86
A24: 02,04,2023 | B24: BABAJANOV OG‘ABEK RASHID O‘G‘LI | C24: 92554392 | E24: 33 | F24: Yangiqadam | G24: Yangiqadam 95 589 24 95
A25: 02,04,2023 | B25: MIRZAYEV RAXIMBERDI XUDASHUKUROVICH | C25: 40316239 | F25: Nurafshon | G25: Nurafshon | L25: 04,05,2023
A26: 02,04,2023 | B26: BEKMETOV SAPARBOY | C26: 27780518 | D26: navbatda | E26: 25 | F26: Qumbodoq | G26: Mirzoxid og`a
A27: 02,04,2023 | B27: MATYOQUBOV KOMILJON IBADULLAYEVICH | C27: 56211981 | E27: 23 | F27: Qalajiqala | G27: Qalajiqala
A28: 02,04,2023 | B28: QO‘ZIBAYEVA HAYOTXON SAFARBAYEVNA | C28: 15215403 | D28: benzin | E28: 33 | F28: Dexqonobod | G28: 88 857 00 29 33 mln matsakil Benzin Dexqonobod MFY
A29: 03,04,2023 | B29: BEKNAZAROV DAVRANBEK IBRAHIMOVICH | C29: 46213614 | E29: 25 | F29: Ashxobod | G29: Ashxobod
A30: 05,04,2023 | B30: MATCHANOV ODILBEK BOBOXONOVICH | C30: 38951800 | E30: 33 | F30: To`pchi | G30: Donyor oga to`pchi
A31: 05,04,2023 | B31: QURBONOVA FAROG‘AT TOHIROVNA | C31: 30306539 | E31: 25 | F31: Tozabozor | G31: Tozabozor 97 721 07 86
A32: 05,04,2023 | B32: OLLAMOVA GULBAXOR UMAROVNA | C32: 12539075 | D32: 28 ming soliq qarzi | E32: Mol mulki | F32: Oq tepa | G32: Oq tepa 93 744 40 90
A33: 06,04,2023 | B33: SAIDOVA GULNOZA SHONAZAROVNA | C33: 63804637 | E33: 20 | F33: Yangiqadam | G33: Yangiqadam
A34: 06,04,2023 | B34: QURBANBAYEV UKTAMBOY RAXIMBOYEVICH | C34: 95583528 | F34: Uzumzor | G34: Uzumzor 99 079 98 50
A35: 06,04,2023 | B35: AMINOV IXTIYOR | C35: 99087510 | F35: Tozabozor | G35: Tozabozor Qosim og`a 97 456 9002 | L35: 13,05,2023
A36: 06,04,2023 | B36: AMIROV NIZAMATDIN | F36: Qaraqalpoq | G36: Qaraqalpoq
A37: 07,04,2023 | B37: BOBOJONOV KAMOL | C37: 40665497 | E37: 24 | F37: madaniyat | G37: Xurriyat 31 53 236 93 287 84 36 | J37: 1 shapka
A38: 07,04,2023 | B38: MAVLONOV JABBORBERDI YULDOSHOVICH | C38: 57135624 | E38: 33 | F38: madaniyat | G38: 97 791 83 88 | J38: benzin
A39: 07,04,2023 | B39: YUSUPOVA GULNORA AXMEDOVNA | C39: 43037916 | F39: Ustalar | G39: 97 452 73 84 Ustalar Sarvar og`a | J39: 1,5 tonna
A40: 07,04,2023 | B40: ALLABERGANOVA GAVHAR KARIMBOYEVNA | C40: 57656509 | D40: 108 soliq qarz | F40: Xonqa | G40: Xonqa 93 854 64 27 99 184 08 39 | J40: 0,6 liq
A41: 07,04,2023 | B41: SADULLAYEVA ODINA QO‘ZIBAYEVNA | C41: 25491838 | E41: 33 | F41: madaniyat | G41: Soxibkor 99 333 74 13 | J41: rulli
A42: 07,04,2023 | B42: RAXIMOVA MARHAMAT NURULLAYEVNA | C42: 68347276 | D42: 16,05,2023 | E42: rasm | F42: Nurafshon | G42: Izzatni tanishlari 99 038 66 00 | L42: 30,05,2023
A43: 09,04,2023 | B43: JUMABOYEV SAN’ATBEK KUROMBOYEVICH | C43: 36748622 | D43: r | F43: Oq Oltin | G43: Oq Oltin 94 114 76 83 99 163 79 76 94 310 79 76
A44: 09,04,2023 | B44: MATNIYOZOV UTKIR KOMILOVICH | E44: 24 | F44: Yangiqadam | G44: Yangiqadam 991516211
A45: 09,04,2023 | B45: MAVLANOVA YULDUZ EGAMBERDIYEVNA | C45: 42332860 | F45: Kulonqorabog` | G45: Kulonqorabog` 941184628
A46: 10,04,2023 | B46: QLICHEV RASHIDBEK SADULLAYEVICH | C46: 90718005
A47: 11,04,2023 | B47: SADULLAYEVA SAPARGUL DURDIYEVNA | C47: 27931029 | F47: Bog`zor | G47: Bogzor tikish mashin
A48: 11,04,2023 | B48: JUMANIYAZOVA MANZURA KOMILJONOVNA | C48: 72456879 | F48: Bog`zor | G48: Bogzor tikish mashin
A49: 11,04,2023 | B49: SADULLAYEV XAMDAMBEK MAQSUD O‘G‘LI | C49: 41777269 | E49: 22 | F49: Bog`iston | G49: Bog`iston 94 151 3112 94 113 80 55
A50: 11,04,2023 | B50: SAPARBOYEV SIROJBEK MUHAMMAD O‘G‘LI | C50: 26421370 | F50: madaniyat | G50: Xurriyat 99 598 85 69 | J50: 32
A51: 12,04,2023 | B51: Mirzoxid og`a | E51: muammo | F51: Qumbodoq | G51: Mirzoxid og`a | H51: 1500 $
A52: 12,04,2023 | B52: ATOMUROTOVA NURJON JUMABAYEVNA | C52: 40578829 | E52: ch | F52: Oq Oltin | G52: Oq Oltin 94 234 10 91
A53: 12,04,2023 | B53: BOBOJONOVA KAROMAT BAXTIYEROVNA | C53: 65658348 | F53: Madaniyat | G53: Madaniyat 97 528 21 71
A54: 12,04,2023 | B54: RO‘ZMETOVA KUMUSH MADAMINOVNA | C54: 37816128 | E54: ch | F54: Madaniyat | G54: Madaniyat 97 528 21 71
A55: 12,04,2023 | B55: ABDULLAYEVA NASIBA ODAMBAYEVNA | C55: 25226906 | E55: rasm | F55: Bog`zor | G55: Tikish mashin Bog`zor qudrat og`a
A56: 13,04,2023 | B56: MAXMUDOV ZAFAR KOMILOVICH | C56: 21101008 | F56: Dexqonobod | G56: Dexqonobod 22,5
A57: 13,04,2023 | B57: ALLAKULIYEV XAKIMBAY DAVLETOVICH | C57: 41199038 | F57: Qumbodoq | G57: Mirzohid
A58: 13,04,2023 | B58: MASHARIPOV NE’MAT YO‘LDOSHEVICH | C58: 89285266 | F58: Ashxobod | G58: Ashxobod 99 969 07 66 | J58: 29.8
A59: 13,04,2023 | B59: MATCHANOVA ROXAT AZADOVNA | C59: 44166927 | F59: Saxovat | G59: Saxovat97 704 96 92
A60: 13,04,2023 | B60: JUMANIYAZOV ATABEK JUMANAZAROVICH | C60: 28545320 | F60: Oq tepa | G60: Otbek oqtepa 99120 72 79
A61: 14,04,2023 | B61: RAJABOV QUVONCHBEK XAITBOY O‘G‘LI | C61: 25970646 | F61: Ashxobod | G61: Ashxobod 97 511 59 60
A62: 14,04,2023 | B62: QO‘SHAQOV ABROR RO‘ZMATOVICH | C62: 43923254 | E62: rasm | F62: Nurafshon | G62: Nurafshon 94 117 20 21 | L62: 30,05,2023
A63: 14,04,2023 | B63: NURMATOV GANJA YUSUPOVICH | C63: 77939522 | D63: boshqa odam | E63: muammo | F63: Nurafshon | G63: Nurafshon 99 829 15 58 | I63: naqd berdi | K63: 2
A64: 14,04,2023 | B64: QURAMBOYEV SHIXNAZAR | C64: 89586855 | E64: rasm | F64: Navruz | G64: Navruz Rulli tel 932810484
A65: 15,04,2023 | B65: OLLANAZAROVA ZUBAYDA JUMABOYEVNA | C65: 65519116 | F65: Oq | G65: Oq Oltin 99 174 82 79
A66: 15,04,2023 | B66: IBODULLAYEVA GULBAHOR YUSUFOVNA | C66: 55755913 | E66: ch | F66: Yosh | G66: Yosh o`smir 88 859 88 33 93 063 25 77
A67: 15,04,2023 | B67: MATCHONOV OTAXON OLLANAZAROVICH | C67: 92694277 | D67: limit | E67: muammo | F67: Nurafshon | G67: Nurafshon 99 192 41 47 | H67: 23 | K67: 2
A68: 17,04,2023 | B68: ATAJONOVA MAMAGUL QABULOVNA | C68: 92856984 | F68: Xurriyat | G68: Xurriyat 99 552 44 69
A69: 17,04,2023 | B69: ACHILDIYEV ISROILJON MATKARIMOVICH | C69: 64184532 | E69: rasm | F69: Nurafshon | G69: Nurafshon 99 504 63 89 | L69: 30,05,2023
A70: 17,04,2023 | B70: JUMOBOYEV JASURBEK NAZARBOYEVICH | C70: 63877171 | F70: Gukshan | G70: Gukshan 99 282 52 10
A71: 17,04,2023 | B71: XAKIMOV XAYRULLA RUSTAMBAYEVICH | C71: 63638334 | F71: Manviyat | G71: Manviyat 99 716 07 51 | L71: 06,05,2023
A72: 18,04,2023 | B72: MASHARIPOV RASULJAN SABIROVICH | C72: 37191548 | F72: Xiva | G72: Xiva 88 201 07 69 919975633
A73: 19,04,2023 | B73: OTOMUROTOV YASHNARBEK TAVAKKALOVICH | C73: 31541163 | F73: Nurli | G73: Nurli maskan
A74: 19,04,2023 | B74: XO‘JAQOV ZIYODJON YULDASHOVICH | C74: 55979210 | E74: ch | F74: Bog`zor | G74: Bog`zor 94 658 28 91
A75: 19,04,2023 | B75: Akrom | E75: muammo | H75: =29.5-5 -> 24.5
A76: 19,04,2023 | B76: JALOLOV SHUHRAT SHARIPBAYEVICH | C76: 76400542 | F76: Ashxobod | G76: Ashxobod 99 312 29 80
A77: 20,04,2023 | B77: ALLASHEV FAXRIDDIN OZODOVICH | C77: 41041576 | E77: ch | F77: madaniyat | G77: Madaniyat 97 362 89 93 | J77: ko`k | K77: 1.5 | L77: berildi to`liq ikki marta xam bo`lishi mumkin
A78: 20,04,2023 | B78: RAXMONOV RUSLAN EGAMBERDIYEVICH | C78: 70020043 | E78: rasm | F78: Ashxobod | G78: Ashxobod 99 702 67 26
A79: 20,04,2023 | B79: JUMABAYEVA GULZIRA ARTIKOVNA | C79: 71495170 | E79: ch | F79: madaniyat | G79: Bog`iston 94 514 09 78 | J79: ko`k
A80: 20,04,2023 | B80: AVAZMETOV HAKIMBOY BEKCHONOVICH | C80: 29506023 | F80: madaniyat | G80: O`zbekiston 942381570 | J80: ko`k | K80: otmen
A81: 20,04,2023 | B81: JURAYEVA MAZGUL URALOVNA | C81: 28075206 | E81: ch | F81: madaniyat | G81: O`zbekiston 94 116 26 94 | J81: oq
A82: 21,04,2023 | B82: NURMETOVA SABOXAT | C82: 29201871 | D82: 16,05,2023 | E82: rasm | F82: madaniyat | G82: Qalajiqala kamandir 97 856 00 70 | J82: ko`k
A83: 22,04,2023 | B83: XUDOYBERGANOV SHUXRAT MADRAXIMOVICH | C83: 44716439 | D83: 16,05,2023 | E83: rasm yo`q | F83: Qorabog` | G83: Qorabog` 93 283 99 77 | J83: ko`k | M83: 27,05,2023
A84: 23,04,2023 | B84: SATIMOVA MUQADDAS JUMANAZAROVNA | C84: 77593076 | D84: boshqa odam | E84: muammo | F84: Navro`z | G84: Navruz Xasanni jo`rasi 97 459 67 07 | J84: ko`k | K84: 23
A85: 23,04,2023 | B85: ABDIRAXMANOVA YULDUZXON BAXTIYOROVNA | C85: 26610061 | F85: madaniyat | G85: Ashxobod | J85: ko`k
A86: 23,04,2023 | B86: XAMROYEVA NIGORA ZARIPBOYEVNA | C86: 40113265 | D86: 16,05,2023 | F86: ashxabod | G86: Ashxobod 97 600 26 57 | J86: ko`k
A87: 23,04,2023 | B87: BABAJANOV MAKSUDBEK YULDASHEVICH | F87: madaniyat | G87: Mirzoxid og`a | J87: ko`k | L87: 23,05,2023 2 mln berildi
A88: 24,04,2023 | B88: YUSUPOVA SHOHIDA OLLASHUKUROVNA | C88: 48264618 | F88: madaniyat | G88: Soxibkor 33 927 27 81 94 111 23 54 | J88: kabina
A89: 24,04,2023 | B89: SOBUROVA GULSARA AZAMAT QIZI | C89: 38173626 | D89: xokimni kutyapti | E89: muammo | F89: Tozabozor | G89: Tozabozor 94 312 96 62 94 942 00 54 | K89: 1 | M89: 12,06,2023
A90: 24,04,2023 | B90: QODIROV BOBURJON KOMIL O‘G‘L | C90: 76162609 | G90: Gulzoda apka 943137785 | K90: chiqmidi bekor qilish kerak
A91: 24,04,2023 | B91: ABDIRIMOVA MAFTUNA SAN’AT QIZI | C91: 72279341 | D91: 16,05,2023 | E91: rasm | F91: Manaviyat | G91: Manaviyat 33 427 00 81 99 774 54 14 | M91: 23,05,2023
A92: 25,04,2023 | B92: OCHILOVA GULSHODA MUXTORBEK QIZI | C92: 81115891 | E92: ch | F92: Soxibkor | G92: 93 745 49 79 Soxibkor
A93: 25,04,2023 | B93: JUMANIYOZOVA MANZURA RAJABBOYEVNA | C93: 82210723 | E93: rasm | F93: Qipchoq | G93: 94 110 78 61 Qipchoq
A94: 25,04,2023 | B94: TANGIRBERGANOV LOCHIN BABAJANOVICH | C94: 79361527 | E94: rasm | F94: Qorabog` | G94: Qorabog` 79361527 93 284 85 81 | M94: naqd oldi
A95: 25,04,2023 | B95: MASHARIPOV SANATBEK ODILBEKOVICH | C95: 30875959 | F95: Yangiariq | G95: Yangiariq 97 608 04 91
A96: 25,04,2023 | B96: ABDIKARIMOV IBRATJON AZAMATOVICH | C96: 81181734 | E96: ch | F96: Qipchoq | G96: Qipchoq moto 33 benzin
A97: 25,04,2023 | B97: Bekiyazova Sanobar | F97: Ko`nabirlashuv | G97: Ko`nabirlashuv 94 026 78 28 | L97: 14,05,2023
A98: 25,04,2023 | B98: RO‘ZMETOV AKMAL ASADULLAYEVICH | F98: Qumbodoq | G98: Mirzoxid og`a | L98: 23,05,2023
A99: 25,04,2023 | B99: QALANDAROV RAJABBOY QAXRAMON | C99: 44279882 | D99: 16,05,2023 | E99: rasm | F99: Nurafshon | G99: Nurafshon 99 193 50 30 | L99: 30,05,2023
A100: 25,04,2023 | B100: GAYIBOVA MARYAM MASHARIPOVNA | C100: 17602036 | F100: Nurli | G100: Nurli maskan 93 006 59 09 K | L100: 06,05,2023
A101: 25,04,2023 | B101: XUDAYBERGANOV MARDONBEK MUXTOR O‘G‘LI | C101: 51830800 | F101: Ashxobod | G101: Ashxobod 99 423 71 71 K
A102: 25,04,2023 | B102: OTANIYEZOVA DILOROM BAHROMOVNA | C102: 18498694 | E102: rasm | F102: Xurriyat | G102: Xurriyat 91 917 84 77
A103: 25,04,2023 | B103: O‘RINOVA ANAJON QILICHOVNA | C103: 37631834 | F103: Tikish | G103: Tikish mashin 91 914 45 66
...

Sheet Qoraqalpoq 
A2: 2022 yil | B2: XUDAYBERGENOV RAVSHANBEK DAVLATOVICH | E2: 30 млн матсакил Журабек ога | F2: 30 | H2: e | I2: 2.5
A3: 1 | B3: SHEROV SEVINDIK KURBANBAYEVICH | C3: 88888888 | F3: 31 | H3: e
A4: 2 | B4: ZARIPOVA DONOXON BEKNAZAR QIZI | F4: 26 | H4: e
A5: 3 | B5: BABAJANOVA SHAXNAZA BAZARBAYEVNA | F5: 33 | H5: b
A6: 4 | B6: SAPARBAYEVA KUNDUZ YERKABAYEVNA | F6: 33 | H6: b
A7: 5 | B7: YESHIMBETOV AKBAR YULDASHBAYEVICH | F7: 33 | H7: b
A8: 6 | B8: SAPARBAYEV ALISHER XUDAYBERGENOVICH | F8: 30 | H8: b
A9: 7 | B9: SABIROVA SANABAR DJUMABAYEVNA | F9: 30 | H9: b | J9: ariza berilmagan | O9: 20 mln berildi Bonus | P9: 27,,02,2023
A10: 8 | B10: RAMANBERGENOV ALLAMBERGAN RAVSHANBEK O‘G‘LI | F10: 31 | H10: e | O10: 10 mln 16,03,2023
A11: 9 | B11: MADAMINOVA ALMAGUL XAITBAYEVNA | F11: 30 | H11: b | O11: 10 mln 27,03,2023
A12: 10 | B12: JABBIYEV XAMID ALLAMBERGENOVICH | F12: 25 | H12: e | O12: 50 mln 05,04,2023
A13: 11 | B13: MOLDABAYEV ADIL ABDIMURATOVICH | F13: 30 | H13: b | O13: 10 mln 01,05,2023
A14: 12 | B14: BEKIMBETOV SEYTNAZAR FAYZULLAYEVICH | F14: 30 | H14: b | O14: 10mln 22,05,2023
A15: 13 | B15: MUMINOVA XOSIYAT KURBANBAYEVNA | F15: 31 | H15: e
A16: 14 | B16: XUDAYBERGENOVA MASTURA URAZBAYEVNA | F16: 33 | H16: b
A17: 15 | B17: ZARLIKOVA ROZA MURATBAYEVNA | F17: 30 | H17: b
A18: 16 | B18: KADIROVA GULSANAM YEGAMBERGANOVNA | F18: 30 | H18: b | J18: kredit shartnoma
A19: 17 | B19: KURBANBAYEV BAXRAM BERDIMURATOVICH | F19: 33 | H19: b | J19: kredit shartnoma
A20: 18 | B20: AKMANOV AZAMAT JUMABAYEVICH | F20: 33 | H20: b
A21: 19 | B21: DJABBARBERGENOV OYBEK NURKENOVICH | F21: 30 | H21: b
A22: 20 | B22: MATSAPAYEVA ZULFIYA KAMALADDINOVNA | F22: 31 | H22: e
A23: 21 | B23: ZaRLIQOV OBIDJON | F23: 25
A24: 22 | B24: BABANIYAZOV ERGASH XUSANOVICH | F24: 31
A25: 23 | B25: ABDREYMOV MAXAMMETJAN ABDREYMOVICH | F25: 31
A26: 24 | B26: MATNAZAROV FAXRATDIN ACHILOVICH | F26: 33
A27: 25 | B27: OSPANOVA BAYAN ROZUMBAYEVNA | F27: 33
A28: 26 | B28: ATADJANOV OBODJON FARXADOVICH | F28: 29
A29: 27 | B29: RAMETOV ILYAS ANVAROVICH | F29: 31
A30: 28 | B30: ISAKOVA ILMIRA RUSTAMOVNA | F30: 25
A31: 29 | B31: RADJAPBAYEV OTAMURAD YULDASHOVICH | F31: 29
A32: 30 | B32: YESHIMBETOVA OYDIN TURABAYEVNA | F32: 29
A33: 31 | B33: PRIMBETOVA TUXTA URAZBAYEVNA | C33: r | F33: 25
A34: 32 | B34: REYIMOV MATNAZAR TURABAYEVICH | F34: 33 | H34: 31
A35: 33 | B35: BABASHOV UMRBEK BALKIBAYEVICH | G35: 2 | H35: 31
A36: 34 | B36: YULDASHOV QAMAR SHERIPBAYEVICH | F36: 29
A37: 35 | B37: KOZIBAYEVA NAVBAXOR SABIROVNA
A38: 36 | B38: ATAJANOV AXMADJON RUSTAMOVICH | F38: 29
A39: 37 | B39: ABDULLAYEVA GUZAL ATAXANOVNA | F39: 29
A40: 38 | B40: RAXIMBAYEV YO‘LDOSH IBADULLAYEVICH | G40: 0 | H40: 25 | I40: Jonibek og` a
A41: 39 | B41: SABUROV KUDRAT JIYEMURATOVICH
A42: 40 | B42: KASIMOVA DILBAR TOXTABAYEVNA
A43: 41 | B43: SABIROVA UMIDA IBADULLAYEVNA | F43: 25
A44: 42 | B44: KUCHKAROV SUHROB YUNUS O‘G‘L
A45: 43 | B45: JUMASHEV TALGAT ASPANOVICH | F45: 29
A46: 44 | B46: XALILAYEVA GULIYOR ERGASH QIZI | F46: 29
A47: 45 | B47: DAUILBAYEV ABAY KENJEBAYEVICH | F47: 25
A48: 46 | B48: SAPARBAYEV ATABEK XUSINOVICH
A49: 47 | B49: DJUMAMURATOVA GULISTAN MAMATALIYEVNA | F49: 33
A50: 48 | B50: YULDASHEVA UMIDA BISANBOYEVNA | F50: 33
A51: 49 | B51: REYIMBAYEV YUSUPBAY AXMEDOVICH | F51: 33
A52: 50 | B52: DURDIBAYEV ABDULLA | F52: 33
A53: 51 | B53: DAVLETOVA ASALXON IKRAM QIZI | F53: 29
A54: 52 | B54: SAPARBAYEVA ROZA | F54: 29
A55: 53 | B55: MATYAKUPOV JAMSHID SAPARBAYEVICH | F55: 33 | H55: b | J55: 09,03,2022
A56: 54 | B56: ISMAILOV XOJAMURAT ATAXONOVICH | F56: 33 | H56: b
A57: 55 | B57: ALLAMOV SHUXRAT ALIMBAYEVICH | F57: 33 | H57: b
A58: 56 | B58: Sultonov Jaxongir | H58: b
A59: 57 | B59: REYMOV TURSUNBAY | F59: 33 | H59: b
A60: 58 | B60: ABDURAYIMOVA ROXATOY AZATJANOVNA | F60: 33 | H60: b
A61: 59 | B61: YO‘LDOSHEVA DILORAM | F61: 33 | H61: b
A62: =+A61+1 -> 60 | B62: Xo`jamboeva Gulshod | F62: 33 | H62: b
A63: =+A62+1 -> 61 | B63: TAYIROVA MUYASSAR RUZIMBAYEVNA | F63: 33 | H63: b | L63: 120
A64: =+A63+1 -> 62 | B64: MATYAKUBOVA XUMOR | F64: 33 | H64: b | I64: x` | L64: 130
A65: =+A64+1 -> 63 | B65: YUSUPOV ULUG‘BEK | F65: 33 | H65: b | L65: 90
A66: =+A65+1 -> 64 | B66: BAZARBAYEV SARDOR | F66: 33 | H66: b | L66: 105
A67: =+A66+1 -> 65 | B67: RADJAPBAYEV UMIRBEK | F67: 33 | H67: b
A68: =+A67+1 -> 66 | B68: Karimboyev Xamdam | F68: 33 | H68: b
A69: =+A68+1 -> 67 | B69: RUSTAMOV JAXONGIR KAMIL O‘G‘LI | F69: 33 | H69: b
A70: =+A69+1 -> 68 | B70: IBRAGIMOV ALIBEK | F70: 33 | G70: 0 | H70: b
A71: 69 | B71: RUZMETOV OYBEK DJUMABAYEVICH | F71: 24 | H71: e
A72: 70 | B72: MAMUTOV AMINBAY | F72: 33 | H72: b
A73: 71 | B73: KOSHANOV KAMALATDIN | F73: 33 | H73: b
A74: 72 | B74: KARIMOVA RAXATJAN | F74: 33 | H74: b
A75: 73 | B75: MAXSATOV SANJAR | F75: 33 | H75: b
A76: 74 | B76: QURYOZOV JALOLIDDIN | F76: 30 | G76: 3 | H76: b
A77: 75 | B77: BABADJANOV ESHCHANBAY | F77: 33 | H77: b
A78: 76 | B78: TOYLIYEVA GULALEK | F78: 33 | H78: b
A79: 77 | B79: DUISOVA SHIRINGUL NURLIBAYEVNA | G79: 33 | H79: b
A80: 78 | B80: Ismoilov Umrbek | F80: 33 | H80: b
A81: 79 | B81: Zavod | G81: 23 | H81: e
A82: 80 | B82: ATADJANOV AZAT FARXADOVICH | F82: 29 | H82: e
A83: 81 | B83: Seydanova Aziza | F83: 20 | H83: e
A84: 82 | B84: RUZMETOV RUSTAM BAXADIROVICH | F84: 20 | H84: e
A85: 84 | B85: AYTBAYEV FAZLIDDIN XADJIYEVICH | F85: 20 | H85: e
A86: 85 | B86: Po`latov Xabibullo | G86: 1 | H86: 34 | J86: 1
A87: 86 | B87: Ibodullayeva Farmon | G87: 1 | H87: 34 | J87: 1
B88: YULDASHEV UXTAM KENJABEKOVICH | H88: 33
B89: TO‘XTABOYEV SIROJ ZAFAR O‘G‘LI | H89: 33
B90: PERDEBAYEVA AYSULUV JAMALADDIN QIZI | H90: 33
B91: XUDAYBERGENOVA ZIYADA BALTABAYEVNA | H91: 33
B92: XALIMBETOVA AYNUR RADJAPBAYEVNA | H92: 33
B93: XODJABAYEVA DILFUZA REYMBAYEVNA | G93: 1 | H93: 33 | J93: 1
B94: ALIZAKOVA NISHANGUL KUANOVNA | H94: 33
B95: YERJANOVA KAMILA SULAYMANOVNA | G95: 0 | H95: 33
B96: YUSUPOV SHAVKAT YULDASHEVICH | G96: 1 | H96: 33
B97: SABUROVA NAZAKAT KURBANBAYEVNA | G97: 1 | H97: 33
B98: ATAJANOVA SHARAFAT PARXADOVNA | H98: 33
G99: 1 | H99: 33
B100: ABDULLAYEV NURADDIN REYIMBAYEVICH | G100: 0 | H100: 33
H101: 24
...

Sheet QAraqalpoq Jonibek og`a 
B3: KURBANALIYEVA MARAL | D3: b33
B4: Erkaboeva Mexribon | D4: b30
B5: RAXIMBAYEV YO‘LDOSH IBADULLAYEVICH | C5: 0 | D5: e | E5: 25
B6: SAPAROV XALMURAT GAIPNAZAROVICH | C6: =45+21-33 -> 33 | D6: 38594035
B7: Nurjonov Ilxom | D7: 33 | E7: Men tarafdan olingan
B8: Sabirova Adolat | D8: 24
B9: PRIMBETOVA GULSHAD AKNAZAROVNA | D9: 33 | E9: Jo`rabek tarafdan olingan
B10: KURBANBAYEV XASANBAY ULUG‘BEK O‘G‘LI | M10: 10
B11: SHUKURULLAYEVA ASALXON AXMAD QIZI
C12: 23
B13: O`razbayev Ibadulla 32 mln rulli | C13: 32 | M13: 4.7
D14: 1 | E14: 20lik | M14: 52.5
M15: 61.5
M16: 270.5
M17: 304.6
M18: 24
H19: 54 | M19: 60
H20: 87 | M20: 9.3
H21: 200 | M21: 0.9
M22: 1.74
M23: 2.8
M24: 15
M25: 4.5
M26: 4.5
M27: 4
M28: 6.3
M29: 25
M30: 25
M31: 20
M32: 20
M33: 287.5
... M46: 56

Sheet МХК
D3: Хоразм вилояти Богот тумани Ок Олтин МФЙ
A5: Уч ғилдиракли юк мотороллер | B5: 08711001001000000 08704001001000000 | C5: 21.23.25.30.31.32.33 | D5: Размер каретки:""2000*1300mmгрузовой транспорт"Задний мост:Мост CHANGAN с повышенной мощностьюПередняя шина: 5.00-12 Задняя шина: 5.00-12Двигатель: 200cc Расход топлива на 100 кмРазмер каретки:""2000*1300mmгрузовой транспорт"Задний мост:Мост CHANGAN с повышенной мощностьюПередняя шина: 5.00-12 Задняя шина: 5.00-12Двигатель: 200cc Расход топлива на 100 кмРазмер каретки:""2000*1300mmгрузовой транспорт"Задний мост:Мост CHANGAN с повышенной мощностьюПередняя шина: 5.00-12 Задняя шина: 5.00-12Двигатель: 200cc Расход топлива на 100 км
A6: Карчер | B6: 8.424002e+15 | C6: 10. 12.5 15 | D6: Мойка высокого давления RTRMAX RTM7015 Керамический поршень Шланг длиной 10 м, устойчивый к давлению и нагреванию Байпасная технология, предотвращающая перегрузку насоса и двигателя давлением Тепловая система, предотвращающая перегрев электродвигателя Бесшумная и плавная работа Области использования Напряжение сети 220 — 230 В Частота тока 50 Гц Мощность 3 кВт Скорость вращения 1400 об/мин Максимальное давление 150 бар Расход воды 480 л/час Вес 55 Кг Гарантия 6 месяцев Brand RTRMAX
A7: Музқаймок ишлаб чикариш ускунаси | B7: 08459001006000000 0841800101300 | C7: 25 - 33 mln | D7: Улгуржи(оптом) нархларда.Хитойнинг энг оригинал завод махсулотлари. Узбекистон буйича етказиб бериш хизматлари,1 йиллик сервиз хизматлари борУлгуржи(оптом) нархларда.Хитойнинг энг оригинал завод махсулотлари. Узбекистон буйича етказиб бериш хизматлари,1 йиллик сервиз хизматлари борУлгуржи(оптом) нархларда.Хитойнинг энг оригинал завод махсулотлари. Узбекистон буйича етказиб бериш хизматлари,1 йиллик сервиз хизматлари борУлгуржи(оптом) нархларда.Хитойнинг энг оригинал завод махсулотлари. Узбекистон буйича етказиб бериш хизматлари,1 йиллик сервиз хизматлари бор
A8: Тикиш машиналари | B8: 844700100600 | C8: 4,4 4,5 5 5,5 5,9 6 6,5 7 7,5 8,25 9 10 15 | D8: Швейная машинка JACK F4 "JK-F 4" Высокоскоростная прямострочная швейная машинка "JK-F 4" Одноигольная машина челночного стежка с плоской платформой, нижним транспортером и встроенным серводвигателем. Преимущества швейной машины: Автоматическая система смазки Подсветка рабочей зоны Встроенный в голову серводвигатель с блоком управления Применение швейной машины: Для стачивания легких и средних материалов
A9: Автомабил ювиш учун пуркагичли флакон | B9: 0841300200300 | C9: 3 4 5 | D9: Пеногенератор просто, эффективно и быстро преобразует моющее (химическое) вещество в пену, которая затем наносится на очищаемую поверхность. Используются пеногенераторы для очистки транспортных средств и различных сооружений, для работы в пищевой и перерабатывающей промышленности, для дезинфекции оборудования, производственных площадей.МАТЕРИАЛ БАКА крашенная сталь ОБЪЕМ БАКА 95 л. РАБОЧЕЕ ДАВЛЕНИЯ 6 бар МАКСИМАЛЬНОЕ ДАВЛЕНИЕ 8 бар ВЕРТИКАЛЬНОЕ ИСПОЛНЕНИЕ есть МАНОМЕТР есть ИНДИКАТОР УРОВНЯ есть ПРЕДОХРАНИТЕЛЬНЫЙ КЛАПАН есть БРЕНД
A10: Чангюткич | B10: 0850800100200 | C10: 3 4 5 8 10 | D10: Качественный и профессиональный пылесос для сухой и влажной уборки (пылеводосос) предназначен для сбора сухого или влажного мусора, воды и жидкой грязи. МОЩНОСТЬ 3600 Вт ОБЪЕМ БАКА 80 л. ПОТОК ВОЗДУХА 106 л/сек. НАПРЯЖЕНИЕ СЕТИ 220В ФУНКЦИИ УБОРКИ Влажная/сухая ДЛИНА КАБЕЛИ
A11: Компрессор | B11: 8.414002e+15 | C11: 2 3 4 4,5 5 8 10 15 | D11: Единица товара: Штука Вес, кг: 24,83 Длина, мм: 650 Ширина, мм: 275 Высота, мм: 620 Компрессор; Ресивер; Универсальное быстродействующее соединение; Обрезиненная рукоятка; Упаковка. Единица товара: Штука Вес, кг: 24,83 Длина, мм: 650 Ширина, мм: 275 Высота, мм: 620 Компрессор; Ресивер; Универсальное быстродействующее соединение; Обрезиненная рукоятка; Упаковка. Единица товара: Штука Вес, кг: 24,83 Длина, мм: 650 Ширина, мм: 275 Высота, мм: 620 Компрессор; Ресивер; Универсальное быстродействующее соединение; Обрезиненная рукоятка; Упаковка.
A12: Печка | B12: 8.417002e+15 | C12: 20 22 24 25 33 | D12: Печка Хитойники 380 В да ишлайди Гарантия 3 йил промой скаладдан таркатамиз Бизда хаммаси арзон ва янги Печка Хитойники 380 В да ишлайди Гарантия 3 йил промой скаладдан таркатамиз Бизда хаммаси арзон ва янгиПечка Хитойники 380 В да ишлайди Гарантия 3 йил промой скаладдан таркатамиз Бизда хаммаси арзон ва янги Печка Хитойники 380 В да ишлайди Гарантия 3 йил промой скаладдан таркатамиз Бизда хаммаси арзон ва янгиПечка Хитойники 380 В да ишлайди Гарантия 3 йил промой скаладдан таркатамиз Бизда хаммаси арзон ва янги Печка Хитойники 380 В да ишлайди Гарантия 3 йил промой скаладдан таркатамиз Бизда хаммаси арзон ва янги
A13: Жатки | B13: 8.432003e+15 | C13: 10 - 33 | D13: Мотоблоги билан бирга уриш ва ер хайдаш учун мулжалланган махсус спесжатка сифатли техникалар харит килишни хохлайсизми унда бизга мурожат килинг йитказиб бериш хизмати хам мавжут Ишлаб чикарилган давлат - Хитой Энг кам микдори - 1 та Яроклик муддати - 3 йил Қуввати -12 от кучи Техник параметрлари-Мотокултиватор 13 л,с. Бензин
A14: Мотоблок | B14: 843200300100 | C14: 10 -33 | D14: Ишлаб чикарилган давлат - Хитой Энг кам микдори - 1 та Яроклик муддати - 3 йил Қуввати -12 от кучи Техник параметрлари-Мотокултиватор 13 л,с. Бензин
A15: Cув тозалаш ускуна | B15: 08421002005000001 | C15: 27 - 33 | D15: Сув тозалаш тизими тўплами. Теплица. парник. иссиқхоналар: Мой сам. автомобилларни ювиш шахобчалари: Ахоли учун тоза ичимлик сувлари ишлаб чиқариш учун барча турдаги сув тозалаш тизимлари!!! Тескари осмос технологияси асосидаги 5 боскичли сув тозалаш системаси. Ишлаб чикариш куввати – 500 литр/соат. Боскичлари: 1. Механик фильтр, фильтрловчи элемент – кварц қуми 2. Сорбцион фильтр, фильтрловчи элемент – фаол кўмир 3. Сув юмшатиш фильтри, фильтрловчи элемент – катионит 4. Нозик тозалаш фильтри, фильтрловчи элемент – полипропилен картридж 5. Тескари осмос тизими, фильтрловчи элемент – мембрана Энергия истеъмоли – 1.9 кВт, 220V/50HZ. Ишчи харорат: +10С… +40С
A16: Кесувчи арра ускунаси | B16: 08461001005000000 2 | C16: 30 31 32 33 | D16: (РУС) Компания: (РУС) Модель: (РУС) Макс. длина распила: (РУС) Макс. ширина распила: (РУС) Радиус основной пилы: (РУС) Радиус второй пилы: (РУС) Скорость вращения основной пилы: (РУС) Скорость второй пилы: (РУС) Толщина распила: (РУС) В комплекте: (РУС) WoodTech Working Machinary (Китай) (РУС) MJ6132YT-MJ45 (РУС) 3000 мм (РУС) 1250 мм (РУС) 330/30 мм (РУС) 120/20 мм (РУС) 4000-6000 раз/мин (РУС) 7000-8000 раз/мин (РУС) 80 мм (РУС) пылесос , запасная пила
A17: Хомир коргич | B17: 843800200200 | C17: 8 10 12 | D17: юкори сифатга эга бўлган занга чидамли темирдан ясалган хамир қориш машинаси сотилади сифатига 100 фоиз кафолат берилади юкори сифатга эга бўлган занга чидамли темирдан ясалган хамир қориш машинаси сотилади сифатига 100 фоиз кафолат берилади юкори сифатга эга бўлган занга чидамли темирдан ясалган хамир қориш машинаси сотилади сифатига 100 фоиз кафолат берилади юкори сифатга эга бўлган занга чидамли темирдан ясалган хамир қориш машинаси сотилади сифатига 100 фоиз кафолат берилади
A18: Музлаткич | B18: 8.418001e+15 | C18: 7,5 8 10 12 | D18: • Телефон Кисела Хар хил маделларидан бор • Ишлаш тизими Но Фрост воздушный • Електор тежовчи А+ класс • Без табло с табло • Бойи 1.75см Ени 60см • 2 камерали • 3 Йил сервис гарантия + 10 йил маторига гарантия • Доставка Бепул Кун давомида йетказиб бериладиЮкори сифатили музкаймок ва шу каби сут махсулотларини саклаш учун 100 сифатга эга махсулот сифати кафолат берилади Юкори сифатили музкаймок ва шу каби сут махсулотларини саклаш учун 100 сифатга эга махсулот сифати кафолат берилади Юкори сифатили музкаймок ва шу каби сут махсулотларини саклаш учун 100 сифатга эга махсулот сифати кафолат берилади Юкори сифатили музкаймок ва шу каби сут махсулотларини саклаш учун 100 сифатга эга махсулот сифати кафолат берилади Юкори сифатили музкаймок ва шу каби сут махсулотларини саклаш учун 100 сифатга эга махсулот сифати кафолат берилади Юкори сифатили музкаймок ва шу каби сут махсулотларини саклаш учун 100 сифатга эга махсулот сифати кафолат берилади
A19: Авто кўтаргич | B19: 8.425001e+15 | C19: 24 25 26 | D19: 2-х стоечный подъемник Launch TDY-2D40M с моторчиком 220v и 380v. Имеется 3.5Т также 4Т.2-х стоечный подъемник Launch TDY-2D40M с моторчиком 220v и 380v. Имеется 3.5Т также 4Т.2-х стоечный подъемник Launch TDY-2D40M с моторчиком 220v и 380v. Имеется 3.5Т также 4Т.2-х стоечный подъемник Launch TDY-2D40M с моторчиком 220v и 380v. Имеется 3.5Т также 4Т.2-х стоечный подъемник Launch TDY-2D40M с моторчиком 220v и 380v. Имеется 3.5Т также 4Т.
A20: Электр перфоратор | B20: 0846700100200 | C20: 2 3 4 5 | D20: PowerMaxx BS Basic Set * Mobile Workshop (Аккумуляторная дрель-шуруповерт, мобильная мастерская) Напряжение аккумулятора:10.8 В Макс. мягкий крутящий момент:17 Нм Макс. жесткий крутящий момент:34 Нм Диаметр сверления в стали:10 мм д. сверления в мягкой древесине:18 ммPowerMaxx BS Basic Set * Mobile Workshop (Аккумуляторная дрель-шуруповерт, мобильная мастерская) Напряжение аккумулятора:10.8 В Макс. мягкий крутящий момент:17 Нм Макс. жесткий крутящий момент:34 Нм Диаметр сверления в стали:10 мм д. сверления в мягкой древесине:18 мм
A21: Товуқ | B21: 0015500100100 | C21: 50 ming | D21: Брама жожалари сотилади конни 100 % тоза ота онасиниям суратини куришингиз мумкин 1 хафталигдан бошлаб 1 йошгача бор Тоза қон 40 кунлик ПАЛИВИЙ жўжалар сотилади. Брама жожалари сотилади конни 100 % тоза ота онасиниям суратини куришингиз мумкин 1 хафталигдан бошлаб 1 йошгача бор Тоза қон 40 кунлик ПАЛИВИЙ жўжалар сотилади. Брама жожалари сотилади конни 100 % тоза ота онасиниям суратини куришингиз мумкин 1 хафталигдан бошлаб 1 йошгача бор Тоза қон 40 кунлик ПАЛИВИЙ жўжалар сотилади. Брама жожалари сотилади конни 100 % тоза ота онасиниям суратини куришингиз мумкин 1 хафталигдан бошлаб 1 йошгача бор Тоза қон 40 кунлик ПАЛИВИЙ жўжалар сотилади.
A22: Чувалчанг | B22: 199001007000000 | C22: 0,5 | D22: Биогомус таййорлаш ва даромад олиш учун кулай. Калифорния Кизил ёмгир чувалчанги. Табиий биогумос ишлаб чикаради. Бир квадрати 500000 сум. Калифорнийский черви. 1 шт 500000 сум.Биогомус таййорлаш ва даромад олиш учун кулай. Калифорния Кизил ёмгир чувалчанги. Табиий биогумос ишлаб чикаради. Бир квадрати 500000 сум. Калифорнийский черви. 1 шт 500000 сум.Биогомус таййорлаш ва даромад олиш учун кулай. Калифорния Кизил ёмгир чувалчанги. Табиий биогумос ишлаб чикаради. Бир квадрати 500000 сум. Калифорнийский черви. 1 шт 500000 сум.
A23: Контейнер | B23: 8.609001e+15 | D23: Контейнер под офис. Ест наличе. Ofis uchun tayyor konteynerlar Devori mdf dekor Eshigi ichi mdf tashqi tomoni temir Romi akfa plast 6000 trio Patalogi plastik Poli linolim Elektrikasi tayyo
A24: Кондитсинер | B24: 0841500100100 | D24: Мощность охлаждения - 9500 Btu Мощность обогрева - 11000Btu Расход электроэнергии - 0,55 кВт Обслуживаемая площадь - 30 м2 Обслуживаемая площадь - 90 м3 Колличество фриона - 675 гр. Фрион - R32 Расход воздуха - 620 Low Voltage 115V-265V Экономия до 60% электроэнергии Скрытый Led Display Компрессор GMCC Toshiba 10 лет гарантии на компрессор 3 года сервисного обслуживания
A25: Компютер | B25: 8.471001e+15 | D25: ntel Core i7-10700T 2.0 GHz (up to 4.3 GHz) 8C 35 W / 8GB (1x8GB) DDR4 2666 SODIMM / 1TB 7200RPM 2.5" HDD / 9.5mm DVD-Writer / 23.8" (54.6 cm) Full HD (1920 x 1080) / Intel UHD Graphics 630 / Intel 9560 ac 2x2 nvP +Bluetooth 5 WW / FreeDOS / One Years Warranty / Black / USB Keyboard and Mouse Несмотря на то, что моноблоки появились давно и потеряли свою актуальность из-за пришедших взамен ноутбуков, развитие информационных технологий позволило им снова возродиться. Моноблок представляет собой компьютер, который встроен в корпус монитора. Удобство моноблоков в том, что они занимают мало свободного пространства и являются миниатюрной частью интерьера. На этом устройстве полностью отсутствуют провода, кроме сетевого провода, что значительно облегчит вам задачу переносить его куда-либо.
A26: Принтер | B26: 844300100100 | D26: A4 Печать фотографий есть Количество цветов 6 Минимальный объем капли 1.5 пл Печать без полей есть Максимальное разрешение для цветной печати 5760x1440 dpi Скорость печати 37 стр/мин (ч/б А4), 38 стр/мин (цветн. А4) Время печати 10x15 см (цветн.) 12 с планшетный Тип датчика контактный (CIS) Максимальный формат оригинала A4 Максимальный размер сканирования 216x297 мм Глубина цвета 24 бит Разрешение сканера 1200x2400 dpi 64-300 г/м2 Печать на: карточках, пленках, этикетках, фотобумаге, CD/DVD, глянцевой бумаге, конвертах, матовой бумаге Ресурс цветного картриджа/тонера 1800 страниц Ресурс ч/б картриджа/тонера 1800 страниц Количество картриджей 6 Тип картриджа/тонера черный C13T67314A, голубой C13T67324A, пурпурный C13T67334A, желтый C13T67344A, светло-голубой C13T67354A, светло-пурпурный C13T67364A Система непрерывной подачи чернил есть
A27: Стол | B27: 940300300100 | D27: Стильный и эргономичный стол, станет важным элементом интерьера. Просторная поверхность стола позволяет удобно разместить как компьютерное оборудование, так и канцелярские принадлежности. Под столешницей расположены выдвижные ящики для хранения мелочей. Изделие выполнено из высококачественного и экологичного материала – МДФ. Все края обработаны ударопрочной кромкой ПВХ, которая значительно увеличивает срок эксплуатации изделия. Для сборки изделия используется фурнитура ведущих мировых производителей. Заказывайте по доступным ценам компьютерный стол от производителя
A28: Комплект стол стуллари билан | B28: 0940300301200 | D28: Представляем вашему вниманию стильные и современные офисные кресла от "FurniGlass". Офисные кресла выполнены из высококачественной кожи, которая имеет стойкость к истиранию и постарению. Благодаря современному и стильному дизайну, офисные кресла в интерьер любого помещения и с любой мебелью.
A29: Балансировка | B29: 8.542001e+15 | D29: Диаметр дисков 10”-26”Автоматический ввод двух параметров колеса – расстояние до колеса, диаметр. Размер ширины диска вводиться в ручную. Система Direct 3D – точное прямое измерение геометрии ALU – дисков. 22 “ LED монитор Модель класса БИЗНЕС с интеллектуальным приводом. Отличают удобство в эксплуатации, простота и надежность. Информативный LCD-монитор обеспечивает комфортную работу на станке. Легкость в освоении и обслуживании: наглядное представление информации при работе - экраны подсказок доступны в любой момент - текстовое меню настроек - пошаговые инструкции по калибровке - речевое сопровождение Дополнительные функции: Оптимизация положения "шина-диск". Для уменьшения массы устанавливаемых грузов возможно проведение оптимизации «шина-диск». При оптимизации тяжелые участки диска и шины перемещаются на противоположные стороны, что позволяет снизить суммарный дисбаланс колеса. - «Невидимый груз» – SPLIT. Для сохранения внешнего вида дорогого диска мы предлагаем решение – переместить груз за спицы. Функция SPLIT разделит груз на два так, что они окажутся за спицами. ПАРАМЕТРЫ Макс. масса колеса, кг 65 Макс. диаметр диска, дюйм 26 Макс. ширина диска, дюйм 20 Макс. диаметр колеса, мм 800 Точность, г 1 Диаметр вала, мм 40 Дисплей LCD 19 Напряжение в сети 220В Масса, кг 85 Габаритные размеры, мм 915 x 1290 x 1330 Цвет Синий / красный
A30: svarka aparat | B30: 8.515999e+15 | C30: 3.5 | D30: Сварочный полуавтомат ХУГОНГ "NB 251K" Профессиональный многофункциональный сварочный аппарат. Оптимально подходит для сварки углеродистых, низколегированных и нержавеющих сталей. Сварочные процессы MIG/MAG, FCAW, MMA. Работа от однофазной сети 220В, сварка проволокой 0.6 - 1.2 мм. ОСОБЕННОСТИ МОДЕЛИ • Сварочный аппарат для полуавтоматической сварки в среде защитного газа (MIG/MAG) и ручной дуговой сварки (ММА). • Инверторная технология на базе новейших IGBT транзисторов • Оптимально подходит для сварки углеродистых, низколегированных и нержавеющих сталей • Встроенный Горячий старт и Антизалипание электрода • Регулировка индуктивности • Режимы работы горелки 2Т/4Т • Дисплей сварочного тока • Дисплей сварочного напряжения • Встроенный 2-х роликовый подающий механизм • Скорость подачи проволоки 2.5-13 м/мин • Функция дожига провоолоки • Функция автоматической постпродувки, 3 секунды • Быстроразъемное соединение сварочных кабелей • Быстроразъемное подключение защитного газа • Легкая смена полярности на панели управления • Встроенная защита от скачков напряжения • Встроенная термальная защита • Индикатор перегрева • Охлаждение с помощью встроенного вентилятора • Встроенный подающий механизм • Установка катушки весом до 20 кг • Кнопка протяжки проволоки • Розетка 36В для подогрева газа • Запатентованная технология, высокая мощность и продолжительность работы • Современный дизайн, небольшой вес, ручка для переноски ОБЩИЕ ХАРАКТЕРИСТИКИ РЕЖИМЫ СВАРКИ MIG/MAG, MMA НАПРЯЖЕНИЕ СЕТИ 220В ± 15% ПОТРЕБЛЕНИЕ МАКСИМАЛЬНОЕ, КВА 10.6 НАПРЯЖЕНИЕ ХОЛОСТОГО ХОДА, В 56 РЕГУЛИРОВКА СВАРОЧНОГО НАПРЯЖЕНИЯ ДЛЯ MIG, В 16.5-26.5 СВАРОЧНЫЙ ТОК MIG, А 50-250 ДИАМЕТР ПРОВОЛОКИ, ММ 0.6-1.2 МАССА КАТУШКИ, КГ 15/20 СВАРОЧНЫЙ ТОК ММА, А 50-200 ДИАМЕТР ЭЛЕКТРОДА, ММ 1.6-4 ПВ, % 60% (20°С) / 35% (40°С) КЛАСС ИЗОЛЯЦИИ F СТЕПЕНЬ ЗАЩИТЫ IP21S МАССА, КГ 23.2 ГАБАРИТНЫЕ РАЗМЕРЫ (Д;Ш;В; ММ) 510x243x492 МАССА БРУТТО, КГ 29 ГАБАРИТНЫЕ РАЗМЕРЫ УПАКОВКИ (Д;Ш;В; ММ) 635х350х530 ГАРАНТИЯ, СРОК (МЕС) 12
A31: Электр болгарка | B31: 846700200200 | C31: 2 | D31: Электропила Makita GA9020, невероятно долговечная, стойкая к перегреву, имеет усиленные конические шестерни редуктора, надежный и пылезащитный мотор (2200 Вт) для работы с бетономЭлектропила Makita GA9020, невероятно долговечная, стойкая к перегреву, имеет усиленные конические шестерни редуктора, надежный и пылезащитный мотор (2200 Вт) для работы с бетономЭлектропила Makita GA9020, невероятно долговечная, стойкая к перегреву, имеет усиленные конические шестерни редуктора, надежный и пылезащитный мотор (2200 Вт) для работы с бетономЭлектропила Makita GA9020, невероятно долговечная, стойкая к перегреву, имеет усиленные конические шестерни редуктора, надежный и пылезащитный мотор (2200 Вт) для работы с бетоном
A32: Электр перфоратор | B32: 0846700100200 | C32: 3 | D32: PowerMaxx BS Basic Set * Mobile Workshop (Аккумуляторная дрель-шуруповерт, мобильная мастерская) Напряжение аккумулятора:10.8 В Макс. мягкий крутящий момент:17 Нм Макс. жесткий крутящий момент:34 Нм Диаметр сверления в стали:10 мм д. сверления в мягкой древесине:18 ммPowerMaxx BS Basic Set * Mobile Workshop (Аккумуляторная дрель-шуруповерт, мобильная мастерская) Напряжение аккумулятора:10.8 В Макс. мягкий крутящий момент:17 Нм Макс. жесткий крутящий момент:34 Нм Диаметр сверления в стали:10 мм д. сверления в мягкой древесине:18 мм
A33: Электр дрел | B33: 08467001001000000 | C33: 2 | D33: PowerMaxx BS Basic Set * Mobile Workshop (Аккумуляторная дрель-шуруповерт, мобильная мастерская) Напряжение аккумулятора:10.8 В Макс. мягкий крутящий момент:17 Нм Макс. жесткий крутящий момент:34 Нм Диаметр сверления в стали:10 мм д. сверления в мягкой древесине:18 ммPowerMaxx BS Basic Set * Mobile Workshop (Аккумуляторная дрель-шуруповерт, мобильная мастерская) Напряжение аккумулятора:10.8 В Макс. мягкий крутящий момент:17 Нм Макс. жесткий крутящий момент:34 Нм Диаметр сверления в стали:10 мм д. сверления в мягкой древесине:18 мм
A34: Електр арра | B34: 0846700100300 | C34: 4 | D34: Пила Аллигатор: Конструкция ручная; Мощность 1700; Выходная мощность 900 Вт; Количество скоростей 1; Длина полотна 430 мм; Производительность; Размер хода 40 мм; Число ходов в минуту 3000; Дополнительная информация Комплект поставки; пильное полотно, ключ; Габариты (ШхВ) 918x219 мм; Вес 5.5 кгПила Аллигатор: Конструкция ручная; Мощность 1700; Выходная мощность 900 Вт; Количество скоростей 1; Длина полотна 430 мм; Производительность; Размер хода 40 мм; Число ходов в минуту 3000; Дополнительная информация Комплект поставки; пильное полотно, ключ; Габариты (ШхВ) 918x219 мм; Вес 5.5 кг
A35: Калитлар тўплами | B35: 8.204001e+15 | C35: 2 | D35: Количество в наборе: 122 единиц. - Насадки 1/2″: от 12 до 24мм, длиной 38 мм; от 27 до 32мм, длиной 42 мм. - Насадки 1/4″: от 4 до 14мм, длиной 25 мм. - Насадки 1/2″ длиние: от 10 до 19мм, длиной 76 мм. - Насадки 1/4″ длиние: от 4 до 9мм, длиной 50 мм. - Насадки Torx 1/2″: E10, E12, E14, E16, E18, E20, E22, E24. - Удлинители: 1/2″: 254 мм, 1/4″: 152 мм. - Кардан: 1/4″, 1/2. - Свечные головки 1/2″: 16 мм, 21 мм. - Трещотки: 1/2″ 255 мм, 1/4″ 155 мм, на 72 зуба. - Головки 1/4″ плоские: от 3 до 6 мм, длиной 25 мм. - Головки 1/4″ Pozidrive: Pz0, Pz1, PZ2, длиной 25 мм. - Головки 1/4″ Philips: PH0, PH1, PH2, длиной 25 мм. - Биты 1/4″ плоске: 4 мм, 5,5 мм, 6,5 мм, длиной 37 мм. - Биты 1/4″ Philips: PH1, PH2, PH3, длиной 37 мм. - Биты 1/4″ Pozidrive: PZ2, PZ3, длиной 37 мм. - Биты 1/4″ HEX: 3 мм, 4 мм, 5 мм, 6 мм, длиной 37 мм. - Биты 1/4″ TORX: T8, T10, T15, T20, T25, длиной 37 мм. - Биты 1/4″ TORX с отвестием: T10, T15, T20, T25, T40, длиной 37 мм. - Ключи комбинированные: от 8 до 19 мм. - Отвёртки плоские: 4x100мм, 6x150мм. - Отвёртки Philips: Ph2х100, Ph3х150мм. - Плоскогубцы: 180 мм. - Бокорезы: 160 мм. - Длинногубцы: 160 мм. - Клещи: 250 мм. - Молоток: 300 грамм. - Набор ключей шестигранных: от 2 мм, до 10 мм. - Материал: CrV. - Вес: 11,5 кг
A36: асалари оиласи | B36: 00199001008000000 | D36: Chetdan porodali zottor asalari oylalari uyalari bilan sotiladi asalarilar sog'lom va sifatli mahsuldor asal yig'adi asalarini sifatiga kafolat asalari onalari oq kraska bilan yelkasini metka qilingan shuningdek asalari uyalarini ham yaseymizChetdan porodali zottor asalari oylalari uyalari bilan sotiladi asalarilar sog'lom va sifatli mahsuldor asal yig'adi asalarini sifatiga kafolat asalari onalari oq kraska bilan yelkasini metka qilingan shuningdek asalari uyalarini ham yaseymizChetdan porodali zottor asalari oylalari uyalari bilan sotiladi asalarilar sog'lom va sifatli mahsuldor asal yig'adi asalarini sifatiga kafolat asalari onalari oq kraska bilan yelkasini metka qilingan shuningdek asalari uyalarini ham yaseymiz
A37: Issiqxona | B37: 940600100500 | D37: juda sifatli profil maxsulotidan tayyorlangan issiqxonalar 1 sotixdan katta barcha turdagi issiqxonalarni talabga qarab turli xil o`lchamlarda yayyorlab beramiz 4 lik profildan kurilgan juda sifatli profil maxsulotidan tayyorlangan issiqxonalar 1 sotixdan katta barcha turdagi issiqxonalarni talabga qarab turli xil o`lchamlarda yayyorlab beramiz 4 lik profildan kurilgan juda sifatli profil maxsulotidan tayyorlangan issiqxonalar 1 sotixdan katta barcha turdagi issiqxonalarni talabga qarab turli xil o`lchamlarda yayyorlab beramiz 4 lik profildan kurilgan juda sifatli profil maxsulotidan tayyorlangan issiqxonalar 1 sotixdan katta barcha turdagi issiqxonalarni talabga qarab turli xil o`lchamlarda yayyorlab beramiz 4 lik profildan kurilgan
A38: Oq qand | B38: 08438001020000000
A39: Oshxona idishlar | B39: 03924001010034011
A40: Ускуналар барча турдаги | B40: 9.031001e+15
A41: Бошқа мебеллар (барча турлари) | B41: 9.4030011e+15
A42: Болалар учун ўйинчоқ тўплар | B42: 09503018043000000
A43: Бошқа совутгичлар ветринний | B43: 8.418001e+15
A44: Маиший музлатгичлардан | B44: 8.418002e+15
A45: Ўтириш учун мўлжалланган | B45: 9.401001e+15
A46: Совутгичлар, музлатгичлар ва совутиш ёки музлатиш ускуналарининг қисмлари | B46: 8.418003e+15
A47: Стол (барча турдаги) | B47: 9.4030011e+15
A48: Ётоқхона, меҳмонхона, офис, ошхона, дала ҳовли ва бошқа мебеллар тўплами (барча турдаги) | B48: 9.4030011e+15
A49: Моноблок компютер | B49: 8.47101e+15 | C49: 8.479001e+15
A50: Хамир аралаштиргич (барча турдаги) | B50: 8.438002e+15 | C50: 9.403005e+15
A51: Нон пишириш печлари, шу жумладан қандолат маҳсулотлари (электр бўлмаган) | B51: 8.417002e+15 | C51: 8.418001e+15
A52: Пайвандлаш учун ускуналар | B52: 8.515001e+15
A53: Домкратлар, транспор | B53: 8.425003e+15
A54: Металл айланмали станоклар | B54: 8.455003e+15
A55: Attriaktsion | B55: 9.508001e+15
A56: Компьютер | B56: 8.471001e+15
A57: Ишлов бериш ускуналари (барча турдаги) | B57: 8.457001e+15
A58: Нон учун ёғоч лоток | B58: 4.419001e+15
A59: Бошқа мебеллар (барча турлари) | B59: 9.4030011e+15
A60: Аристон | B60: 8.419009e+15
A61: кир ювиш машинаси | B61: 8.450001e+15
A62: Пресс, майдалагичлар | B62: 8.435001e+15
A63: Бетонлаш учун қолиплар | B63: 4.418001e+15
... A80: Торт колип | B80: 1.905007e+15

Sheet Списка фирма
B1: № | F1: Махалла | H1: Дата | I1: Фирма номлари | J1: Директор | K1: Cчет | L1: Мфо | N1: инн | O1: парол | P1: Солик тури | Q1: под | R1: яс | S1: фойда | T1: Ккс | U1: Сув | V1: мол мулк | W1: мол натижа | X1: Баланс | Y1: стат | Z1: Каттий солик отказ | AA1: инкасса | AB1: Рестир | AC1: ijara shartnoma | AE1: Камерал тушган | AF1: хат
B2: =ROW()-1 -> 1 | F2: G'alaba mahallasi | H2: 41095 | I2: Saidnazar Shaxzodbek | J2: Saidjanov Shoxzodbek Saidnazarovich | K2: 20208000204987861001 | L2: 1125 | N2: 302341341 | O2: 11111111 | P2: яс | Q2: 1 | R2: 1
B3: =ROW()-1 -> 2 | F3: Bog'ot shaharchasi | H3: 43182 | I3: Bogot tomorqa xizmat | J3: "SAIDNAZAR-SHAXZODBEK" XK | K3: 20208000900863059001 | L3: 1125 | N3: 305426920 | P3: яс | Q3: 1 | R3: 1
B4: =ROW()-1 -> 3 | C4: Бола пули | E4: 1 | F4: Bog'ot shaharchasi | H4: 43817 | I4: TRITON MEGA LUX | J4: ORTIQOV SHOKIRBOY O‘KTAMBOYEVICH | K4: 20208000605157236001 | L4: 1125 | N4: 306954264 | P4: яс
B5: =ROW()-1 -> 4 | C5: камерал | D5: 54082 | F5: Oq Oltin mahallasi, | H5: 44040 | I5: Oq Oltinli Qaxramon tomoqa xizmat | J5: SAIDJONOV QAHRAMON BEKTURDIYEVICH | K5: 20208000505258701001 | L5: 401 | N5: 307599285 | O5: тугатилди | P5: яс
B6: =ROW()-1 -> 5 | E6: 1 | F6: Bo'ka mahallasi, | G6: Тугатилган | H6: 44671 | I6: Yetakchi tomoqa xizmat | J6: ORTIQOV SHOKIRBOY O‘KTAMBOYEVICH | K6: 20208000305528834001 | L6: 401 | N6: 309484665 | O6: 44707213 | P6: яс
B7: =ROW()-1 -> 6 | F7: Xunarmand mahallasi | H7: 44858 | I7: "INNAVATSION YASHIL MAKON" MCHJ | J7: VAISOV FURQAT FARHADOVICH | K7: 20208000605581989001 | L7: 556 | N7: 309965873 | O7: клуч | P7: яс
B8: =ROW()-1 -> 7 | F8: Qulonqorabog' QFY | H8: 44858 | I8: Хоразм бюк чинори | J8: BALTAYEV OZAD KOMILOVICH | K8: 20208000905592951001 | L8: 401 | N8: 309966397 | O8: клуч | P8: яс
B9: =ROW()-1 -> 8 | E9: 1 | F9: Obod mahallasi | H9: 44880 | I9: "SHEXMUROD 2022" MCHJ | J9: shermetov Maxsud Achilovich | K9: 20208000105587264001 | L9: 579 | N9: 310017573 | O9: 7 | P9: яс | Q9: 1 | R9: 1
B10: =ROW()-1 -> 9 | F10: Obod mahallasi | H10: 44880 | I10: SHEXMUROD 0112 MCHJ | J10: Shermetov Maxsud Achilovich | K10: 20208000805587208001 | L10: 4 | N10: 310017637 | O10: 7 | P10: яс | Q10: 1 | R10: 1
B11: =ROW()-1 -> 10 | D11: Баланс мото | F11: Oq Oltin mahallasi, | H11: 44917 | I11: BOG'OT MOTO HOUSE 007 MCHJ | J11: Mavlonov Rahmatjon Ollayor o'g'li | K11: 20208000905598744001 | L11: 401 | N11: 310108634 | O11: 80540173 | P11: яс | Q11: 1 | R11: 1
B12: =ROW()-1 -> 11 | D12: Муаммо озод | F12: Oq Oltin mahallasi, | H12: 44943 | I12: BOG'OT TEXNIKA OLAMI 01 MCHJ | J12: BALTAYEV OZAD KOMILOVICH | K12: 20208000105606343001 | L12: 1183 | N12: 310152827 | O12: клуч | P12: яс
B13: =ROW()-1 -> 12 | D13: 59200 | F13: Oq Oltin mahallasi, | H13: 44983 | I13: FINANS MOTO TRADE MCHJ | J13: SAIDJONOV QAHRAMON BEKTURDIYEVICH | K13: 20208000305618798001 | L13: 579 | N13: 310266408 | O13: 11111111 | P13: яс | Q13: 1 | R13: 1
B14: =ROW()-1 -> 13 | C14: измен факт | D14: Баланс мотти | E14: 1 | F14: Oq Oltin mahallasi | H14: 45010 | I14: SUPER MOTO 100 | J14: SAIDJONOV QAHRAMON BEKTURDIYEVICH | K14: 20208000205628942001 | L14: 401 | N14: 310337674 | O14: 11111111 | P14: яс | Q14: 1 | R14: 1
B15: =ROW()-1 -> 14 | D15: Анвар Бекчанов | F15: Bozor mahallasi | H15: 45093 | I15: Bog`zor Armada motors | J15: RO`ZMATOV SHAHZODBEK ANVARBEK O`G`LI | K15: 20208000205672005001 | L15: 1037 | N15: 310572178 | P15: яс
A16: 45211 | B16: =ROW()-1 -> 15 | C16: тоза | D16: халкбанк | E16: куш | F16: Namuna mahallasi | H16: 45211 | I16: KORZINKA HAUSE 777 MCHJ | J16: MAVLANOV XUDOYSHUKUR OLLAYOR O‘G‘LI | K16: 20208000905705033001 | L16: 401 | N16: 310848125 | O16: клуч | P16: яс
A17: 45211 | B17: =ROW()-1 -> 16 | C17: тоза | E17: куш | F17: Bozor mahallasi | H17: 45211 | I17: GARDEN MOTORS MCHJ | J17: AMINOV KAMOLIDDIN BAXROMOVICH | K17: 20208000305705032001 | L17: 401 | N17: 310848140 | O17: 3Rz79VVo4w | P17: яс | Q17: 1 | R17: 1
A18: 45212 | B18: =ROW()-1 -> 17 | C18: тоза | E18: куш | F18: Bog'iston mahallasi | H18: 45212 | I18: GARDENS TRADE 101 MCHJ | J18: AMINOV KAMOLIDDIN BAXROMOVICH | K18: 20208000905705496001 | L18: 401 | N18: 310850780 | O18: v4r3v3CPM1 | P18: яс | Q18: 1 | R18: 1
A19: 45213 | B19: =ROW()-1 -> 18 | C19: тоза | E19: куш | F19: Bog'iston mahallasi | H19: 45213 | I19: "GARDENS TRADE OFFICE" MCHJ | J19: AMINOV KAMOLIDDIN BAXROMOVICH | K19: 20208000605705503001 | L19: 401 | N19: 310850844 | O19: AAaa123456 | P19: яс | Q19: 1 | R19: 1
A20: 17,10,2023 | B20: =ROW()-1 -> 19 | C20: тоза | D20: халкбанк | E20: там шарт | F20: To'pchi mahallasi | H20: 45216 | I20: GARDEN MARKET 111 | J20: MAVLANOV XUDOYSHUKUR OLLAYOR O`G`LI | K20: 20208000505706639001 | L20: 401 | N20: 310857691 | O20: 7 | P20: к | U20: 1 | V20: 1 | W20: 1 | X20: 1 | Z20: 1
A21: 20,10,2023 | B21: =ROW()-1 -> 20 | C21: тоза | E21: куш | F21: Oktepa mahallasi | G21: Тугатилган | H21: 45218 | I21: "OQ TEPA MOTORS" MCHJ | J21: MAVLANOV XUDOYSHUKUR OLLAYOR O`G`LI | K21: 20208000105707642001 | L21: 401 | N21: 310863400 | O21: 7 | P21: яс
B22: =ROW()-1 -> 21 | C22: тоза | E22: куш | F22: NURLI MASKAN | H22: 45243 | I22: "BEST MOTOTRANS" MCHJ | J22: MAVLONOV RAHMATJON OLLAYOR O`G`LI | K22: 20208000605716207001 | L22: 401 | N22: 310920986 | O22: 7 | P22: яс | Q22: клуч
B23: =ROW()-1 -> 22 | C23: тоза | E23: куш | F23: QALAJIQQALʻA | H23: 45244 | I23: "ARMADA EVRO MOTORS" MCHJ | J23: MAVLONOV RAHMATJON OLLAYOR O‘G‘LI | K23: 20208000205716767001 | L23: 401 | N23: 310924015 | O23: 7 | P23: яс | Q23: клуч
B24: =ROW()-1 -> 23 | C24: тоза | D24: 409 | E24: куш | F24: Obod mahallasi | H24: 45251 | I24: "TITANIUM MOTORS" MCHJ | J24: MAVLONOV RAHMATJON OLLAYOR O‘G‘LI | K24: 20208000905719578001 | L24: 401 | N24: 310940029 | P24: яс
B25: =ROW()-1 -> 24 | C25: Сотилди | D25: тугатилди | E25: куш | F25: АРБОБЛАР МФЙ | H25: 45271 | I25: "ARMADA CAMFORT MOTORS" MCHJ | J25: MAVLONOV RAHMATJON OLLAYOR O‘G‘LI | N25: 310974223 | P25: яс
B26: =ROW()-1 -> 25 | F26: Oq Oltin mahallasi | H26: 45376 | I26: ARMADA MOTORS 999 | J26: SAIDJANOV BEHZOD SAIDNAZAROVICH | N26: 311190978 | O26: 7 | P26: яс
B27: =ROW()-1 -> 26 | E27: сотилди | H27: 45666 | I27: PROFI NEX | J27: KARIMOV UMIRBEK | K27: 20208000207185396001 | L27: 491 | M27: Қорақалпоғистон | N27: 311820912 | O27: 11111111 | P27: к
B28: =ROW()-1 -> 27 | E28: сотилди | H28: 45677 | I28: BARAKA TEXNO DUNYO 777 | J28: MOVLANOV XUDASHUKUR | K28: 20208000107189367001 | L28: 491 | M28: Қорақалпоғистон | N28: 311846389 | O28: 20099666 | P28: к
B29: =ROW()-1 -> 28 | E29: шарт | H29: 45687 | I29: "ENERGIYA PANEL | J29: KARIMOV UMIRBEK | K29: 20208000107193587001 | L29: 1125 | N29: 311875306 | O29: 33391788 | P29: ккс | T29: 1
B30: =ROW()-1 -> 29 | E30: сотилди | H30: 45689 | I30: TEXHNO NEX | J30: SAIDJANOV BEHZOD SAIDNAZAROVICH | K30: 20208000107194156001 | L30: 450 | M30: Қорақалпоғистон | N30: 311881093 | P30: к
B31: =ROW()-1 -> 30 | E31: там шарт | H31: 45691 | I31: "TEXNO SPECIAL SERVIS | J31: SAIDJONOV QAHRAMON BEKTURDIYEVICH | K31: 20208000207194497001 | L31: 450 | M31: Қорақалпоғистон | N31: 311883827 | O31: 11111111 | P31: к | T31: 1 | Z31: 1
B32: =ROW()-1 -> 31 | E32: сотилди | H32: 45693 | I32: "OQ OLTIN BIZNES TADBIRKOR | J32: SAIDJOVOVA SABOXAT | K32: 20208000207195864001 | L32: 491 | M32: Қорақалпоғистон | N32: 311890834 | O32: 11111111 | P32: к
B33: =ROW()-1 -> 32 | C33: 80900 | D33: сотувда | E33: смарт | H33: 45695 | I33: SEVEN TEXNO MAX | J33: MOVLANOV XUDASHUKUR | K33: 20208000 | L33: 491 | M33: Қорақалпоғистон | N33: 311898482 | O33: 1111111 | P33: к
B34: =ROW()-1 -> 33 | E34: сотилди | H34: 45699 | I34: MEDIUM SALE | J34: SAIDJONOV QAHRAMON BEKTURDIYEVICH | K34: 20208000407199224001 | L34: 491 | M34: Қорақалпоғистон | N34: 311908509 | O34: 11111111 | P34: к
B35: =ROW()-1 -> 34 | E35: сотилди | H35: 45699 | I35: LIVESTOCK OF CATTLE | J35: MAVLANOV XUDOYSHUKUR OLLAYOR O‘G‘LI | K35: 20208000907199226001 | L35: 491 | M35: Қорақалпоғистон | N35: 311908548 | O35: 11111111 | P35: к
B36: =ROW()-1 -> 35 | E36: сотилди | H36: 45720 | I36: CONSTRUQTION CAPITAL TRADE | J36: SAIDJANOV BEHZOD SAIDNAZAROVICH | K36: 20208000007209411001 | L36: 491 | M36: Қорақалпоғистон | N36: 311960762 | O36: 11111111 | P36: к
B37: =ROW()-1 -> 36 | E37: сотилди | H37: 45727 | I37: TECHNICAL ACTIVE SERVICE | J37: SAIDJONOV QAHRAMON BEKTURDIYEVICH | K37: 20208000 | L37: 491 | M37: Қорақалпоғистон | N37: 311975158 | O37: 11111111 | P37: к
B38: =ROW()-1 -> 37 | D38: микрбанк | E38: сотилди | H38: 45731 | I38: CENTRAL CONSTRUCTION WORLD | J38: SAIDJOVOVA SABOXAT | K38: 20208000907214484001 | L38: 491 | M38: Қорақалпоғистон | N38: 311986974 | O38: 11111111 | P38: к
B39: =ROW()-1 -> 38 | C39: гитти | D39: сотувда | E39: там шарт | G39: M01851 | H39: 45736 | I39: STRATTON INVEST TEX | J39: MAVLANOV XUDOYSHUKUR OLLAYOR O`G`LI | K39: 20208000307217253001 | L39: 491 | M39: Қорақалпоғистон | N39: 312002021 | O39: 11111111 | P39: к
B40: =ROW()-1 -> 39 | C40: гитти | D40: сотувда | E40: там шарт | G40: MO1854 | H40: 45748 | I40: NEW BRIGHT CAPITAL | J40: SAIDJONOV QAHRAMON BEKTURDIYEVICH | K40: 20208000 | L40: 491 | M40: Қорақалпоғистон | N40: 312024445 | O40: 11111111 | P40: к
B41: =ROW()-1 -> 40 | D41: сотувда | E41: смарт | G41: M01853 | H41: 45748 | I41: NEW SEASON INVEST | J41: SAIDJANOV BEHZOD SAIDNAZAROVICH | K41: 20208000 | L41: 491 | M41: Қорақалпоғистон | N41: 312025239 | O41: 11111111 | P41: к
B42: =ROW()-1 -> 41 | D42: сотувда | E42: смарт | G42: MO1905 | H42: 45751 | I42: EXPENSIV BIZNES | J42: MAVLANOV XUDOYSHUKUR OLLAYOR O`G`LI | K42: 20208000 | L42: 491 | M42: Қорақалпоғистон | N42: 312035352 | O42: 11111111 | P42: к
B43: =ROW()-1 -> 42 | C43: гитти | D43: сотувда | E43: там шарт | H43: 45759 | I43: WHITE GOLD PANEL | J43: SAIDJANOV BEHZOD SAIDNAZAROVICH | K43: 20208000 | L43: 491 | M43: Қорақалпоғистон | N43: 312057412 | O43: 11111111 | P43: к
B44: =ROW()-1 -> 43 | C44: тайор | D44: ishu | E44: Халк банк там шарт | G44: M01928 | H44: 45769 | I44: YANGI TIJORAT | J44: KARIMOV UMIRBEK | K44: 20208000907231033001 | L44: 491 | M44: Қорақалпоғистон | N44: 312078354 | O44: 11111111 | P44: к
B45: 44 | H45: 45779 | I45: GREEN ECO PANEL | J45: SAIDJONOV QAHRAMON BEKTURDIYEVICH | K45: 20208000607236078001 | L45: 556 | N45: 312105312 | O45: 11111111 | P45: ккс | T45: 1
B46: 45 | D46: сотувда | E46: смарт | H46: 45782 | I46: BIO CHORVA | J46: KARIMOV UMIRBEK | K46: 20208000707236679001 | L46: 491 | M46: Қорақалпоғистон | N46: 312109084 | O46: 1111111 | P46: к | T46: 1 | U46: инкс
B47: 46 | C47: гитти | D47: сотувда | E47: там шарт | H47: 45783 | I47: EASTBRIDGE COMMERCE | J47: SAIDJANOV BEHZOD SAIDNAZAROVICH | K47: 202080000 | L47: 491 | M47: Қорақалпоғистон | N47: 312114697 | O47: 11111111 | P47: к
B48: 47 | D48: сотувда | E48: смарт | H48: 14,05,2025 | I48: SMART PANEL | J48: SAIDJONOV QAHRAMON BEKTURDIYEVICH | K48: 20208000 | L48: 1125 | M48: Қорақалпоғистон | N48: 312130568 | O48: 11111111 | P48: к
B49: 48 | D49: сотувда | E49: чорва | H49: 14,05,2025 | I49: INTERNATSIONAL TOMORQA | J49: SAIDJONOV QAHRAMON BEKTURDIYEVICH | K49: 20208000 | L49: 491 | M49: Қорақалпоғистон | N49: 312133721 | O49: 11111111 | P49: к
B50: 49 | C50: тайор | E50: там шарт | G50: M02024 | H50: 45796 | I50: EKO ZIYO PANEL | J50: SAIDJONOV QAHRAMON BEKTURDIYEVICH | K50: 20208000 | L50: 491 | M50: Қорақалпоғистон | N50: 312141428 | O50: 11111111 | P50: к
B51: 50 | C51: 11 | E51: чорва | G51: M02023 | H51: 45796 | I51: EKO AGRO FERMA MCHJ | J51: SAIDJOVOVA SABOXAT | K51: 20208000 | L51: 491 | M51: Қорақалпоғистон | N51: 312142892 | O51: 11111111 | P51: к
B52: =ROW()-1 -> 51 | C52: тайор 982 | E52: смарт | G52: M816Tijorat 600969 | H52: 45811 | I52: TIJORAT NEXT | J52: SAIDJANOV BEHZOD SAIDNAZAROVICH | K52: 20208000207251686001 | L52: 1125 | M52: Қорақалпоғистон | N52: 312183272 | O52: 11111111 | P52: к
B53: =ROW()-1 -> 52 | C53: Фауктура барилмаган 286 | D53: 200 | E53: там шарт | H53: 45818 | I53: FLEX SERVICES | J53: KARIMOV UMIRBEK | K53: 20208000 | L53: 1125 | M53: Қорақалпоғистон | N53: 312192167 | O53: 11111111 | P53: к
B54: 51 | H54: 45822 | I54: EXPENSIV CAPITAL | J54: SAIDJANOVA SABOXAT SAIDNAZAROVNA | K54: 20208000907256765001 | L54: 1125 | N54: 312206265 | O54: 70495765 | P54: ккс | T54: 1
B55: 52 | H55: 45824 | I55: OQTEPA SERVIC MCHJ | J55: SAIDJONOV QAHRAMON BEKTURDIYEVICH | L55: 1125 | M55: Қорақалпоғистон | N55: 312207944 | O55: 12345678 | P55: ккс | S55: 1 | T55: 1
B56: 53 | C56: 11 | D56: ishu | E56: там шарт | G56: XБ шокир ога | H56: 45828 | I56: INNOVATIONS STYL | J56: SAIDJONOV QAHRAMON BEKTURDIYEVICH | L56: 1125 | M56: Қорақалпоғистон | N56: 312220985 | O56: 11111111 | P56: к
B57: 54 | D57: ishu бардим | E57: смарт | H57: 45832 | I57: YANGIARIQ ECO CHORVA FARMIX | J57: SAIDJONOV QAHRAMON BEKTURDIYEVICH | K57: 312097695 | L57: 563 | M57: Қорақалпоғистон | N57: 312228088 | O57: 11111111 | P57: к
B58: 55 | D58: ishu | E58: смарт | G58: шокир ога | H58: 45832 | I58: SOLAX POWER HEAT | J58: SAIDJONOV QAHRAMON BEKTURDIYEVICH | L58: 556 | M58: Қорақалпоғистон | N58: 312240201 | O58: 11111111 | P58: к
B59: 56 | C59: отказ фактура бор | D59: ishu | E59: там шарт | H59: 45839 | I59: INNOVATSION TIJORAT | J59: Karimov Umrbek Shakirovich | L59: 556 | M59: Қорақалпоғистон | N59: 312244235 | O59: 11111111 | P59: к
B60: 57 | C60: 11 | E60: смарт | G60: M816TECH 600974 | H60: 45847 | I60: TECH NEST 777 | J60: MAVLANOV XUDOYSHUKUR OLLAYOR O`G`LI | L60: 1125 | M60: Қорақалпоғистон | N60: 312267959 | O60: 11111111 | P60: к
B61: 58 | C61: 615 тай | D61: ishu | E61: там шарт | G61: Mob 2222 | H61: 45850 | I61: ECO DEYE TRADE | J61: MAVLANOV XUDOYSHUKUR | L61: 556 | M61: Қорақалпоғистон | N61: 312274665 | O61: 11111111 | P61: к
B62: 59 | C62: 998 тай | D62: ishu | E62: там шарт | G62: M816Technical 600976 | H62: 45859 | I62: TECHNICAL GROUP LINE | J62: KARIMOV UMRBEK | L62: 1125 | M62: Қорақалпоғистон | N62: 312293974 | O62: 1111111 | P62: к
B63: 60 | C63: Х.Б | D63: ishu | E63: смарт | G63: Каха брат | H63: 45864 | I63: MCHJ EKOLOGIK MARKET | J63: SAIDJONOV QAHRAMON BEKTURDIYEVICH | L63: 1125 | M63: Қорақалпоғистон | N63: 312308605 | O63: 11111111 | P63: к | Q63: 1 | AA63: 1
B64: 61 | E64: чорва | G64: Каха брат | H64: 45868 | I64: YANGIARIQ RANCHO | J64: SAIDJONOV QAHRAMON BEKTURDIYEVICH | L64: 1125 | M64: Қорақалпоғистон | N64: 312319322 | O64: 11111111 | P64: к | Q64: 1 | T64: 1 | AA64: 1
B65: =+B64+1 -> 62 | C65: 1 | D65: 100 | E65: там шарт | H65: 45875 | I65: EXPENSIV ACTIVE SERVICE | J65: SAIDJONOV QAHRAMON BEKTURDIYEVICH | L65: 556 | M65: Қорақалпоғистон | N65: 312335969 | O65: 11111111 | P65: к | AA65: 1
B66: =+B65+1 -> 63 | D66: долди | E66: смарт | H66: 45882 | I66: EXPENSIV TEXNO MAX MCHJ | J66: SAIDJANOV BEHZOD SAIDNAZAROVICH | L66: 1125 | M66: Қорақалпоғистон | N66: 312355524 | O66: 11111111 | P66: к | AA66: 1
B67: =+B66+1 -> 64 | D67: долди | E67: там шарт | H67: 45903 | I67: TECHNICAL GROUP NEXT | J67: SAIDJONOV QAHRAMON BEKTURDIYEVICH | L67: 1125 | M67: Қорақалпоғистон | N67: 312400999 | O67: 11111111 | P67: к | AA67: 1
B68: =+B67+1 -> 65 | D68: бор | E68: смарт | H68: 45905 | I68: TEXNO CAPITAL GOLD | J68: SAIDJANOVA SABOXAT SAIDNAZAROVNA | L68: 491 | M68: Қорақалпоғистон | N68: 312407459 | O68: 11111111 | P68: к | Q68: 1 | T68: 1 | AA68: 1
B69: =+B68+1 -> 66 | C69: шартнома | D69: бор | E69: там шарт | G69: ижара | H69: 45906 | I69: PRO TECH MARKET | J69: Karimov Umrbek Shakirovich | L69: 491 | M69: Қорақалпоғистон | N69: 312410543 | O69: 11111111 | P69: к | Q69: 1 | T69: 1 | AA69: 1
B70: =+B69+1 -> 67 | C70: шартнома | D70: бор | E70: там шарт | G70: ижара | H70: 45917 | I70: EXPRESS TEXNO SMART | J70: Karimov Umrbek Shakirovich | L70: 491 | M70: Қорақалпоғистон | N70: 312440260 | O70: 11111111 | P70: к | Q70: 1 | T70: 1 | AA70: 1
B71: =+B70+1 -> 68 | C71: шартнома | D71: Сай | E71: там шарт | G71: ижара | H71: 45925 | I71: EXPRESS TEXNO 777 | J71: SAIDJANOVA SABOXAT SAIDNAZAROVNA | L71: 491 | M71: Қорақалпоғистон | N71: 312462297 | O71: 11111111 | P71: к | Q71: 1 | T71: 1 | AA71: 1
B72: =+B71+1 -> 69 | H72: 45936 | I72: GREEN WORLD CENTER | J72: MUNISA SULTANOVA | K72: 20208000407326498001 | L72: 491 | N72: 312484981 | O72: 1111111 | P72: ккс | T72: 1
B73: =+B72+1 -> 70 | D73: долди | E73: смарт | G73: ижара | H73: 45937 | I73: SMART TEX CAPITAL | J73: SAIDJONOV QAHRAMON BEKTURDIYEVICH | L73: 491 | M73: Қорақалпоғистон | N73: 312487424 | O73: 11111111 | P73: к | Q73: 1 | T73: 1
B74: =+B73+1 -> 71 | D74: 20496 | E74: чорва | G74: ижара | H74: 45938 | I74: HAZORASP ECO CHORVA | J74: Karimov Umrbek Shakirovich | K74: 20208000207326497001 | L74: 491 | N74: 312489168 | O74: 7 | P74: к | Q74: 1 | R74: 1
B75: 72 | C75: шартнома | E75: там шарт | H75: 45946 | I75: INVEST HAUSE 777 | J75: SAIDJONOV QAHRAMON BEKTURDIYEVICH | L75: 491 | M75: Қорақалпоғистон | N75: 312507904 | O75: NY6sv49bS2 | P75: к | Q75: 1 | T75: 1
B76: =+B75+1 -> 73 | D76: долди | E76: смарт | G76: ижара | H76: 45946 | I76: NERO MAX | J76: SAIDJANOV BEHZOD SAIDNAZAROVICH | L76: 491 | M76: Қорақалпоғистон | N76: 312508499 | O76: 7 | P76: к | Q76: 1 | R76: 1
B77: =+B76+1 -> 74 | C77: шартнома | D77: 97446 | E77: там шарт | G77: Каха моб банк | H77: 45950 | I77: SIFAT TEXNO HAUSE | J77: Karimov Umrbek Shakirovich | L77: 491 | M77: Қорақалпоғистон | N77: 312515775 | O77: 6Ay090ZnQm | P77: к | Q77: 1 | R77: 1
B78: =+B77+1 -> 75 | D78: 97000 | E78: там шарт | G78: Каха моб банк | H78: 45950 | I78: TEXNO MAX 222 | J78: SAIDJONOV QAHRAMON BEKTURDIYEVICH | K78: 20208000707333547001 | L78: 556 | M78: Қорақалпоғистон | N78: 312517187 | P78: к | Q78: 1 | R78: 1
B79: =+B78+1 -> 76 | E79: Кредит | H79: 45958 | I79: EXPENSIV TEX | J79: Karimov Umrbek Shakirovich | K79: 20208000807337242001 | L79: 1125 | N79: 312535355 | O79: aaAA123456789 | P79: яс
B80: =+B79+1 -> 77 | E80: там шарт | G80: Каха моб банк | H80: 45967 | I80: MIR HAUSE | J80: SAIDJANOV BEHZOD SAIDNAZAROVICH | K80: 20208000007343017001 | L80: 579 | M80: Қорақалпоғистон | N80: 312558818 | O80: 7 | P80: к | Q80: 1 | R80: 1
B81: =+B80+1 -> 78 | E81: смарт | H81: 45968 | I81: FINANS MARKET | J81: SAIDJANOV BEHZOD SAIDNAZAROVICH | L81: 556 | M81: Қорақалпоғистон | N81: 312560294 | O81: uQ8W60dPz6 | P81: к | Q81: 1 | R81: 1
B82: =+B81+1 -> 79 | E82: там шарт | H82: 45972 | I82: TEXNO SERVICES 777 | J82: SAIDJONOV QAHRAMON BEKTURDIYEVICH | K82: 20208000807345234001 | L82: 556 | M82: Қорақалпоғистон | N82: 312567094 | O82: aaAA123456789 | P82: к | Q82: 1 | R82: 1
B83: =+B82+1 -> 80 | E83: там шарт | H83: 45973 | I83: CENTRAL SMART MARKET | J83: SAIDJONOV QAHRAMON BEKTURDIYEVICH | K83: 20208000307347781001 | L83: 556 | M83: Қорақалпоғистон | N83: 312575457 | O83: 7 | P83: к | Q83: 1 | R83: 1
B84: 81 | E84: там шарт | H84: 45979 | I84: SEVEN HOUSE LINE | J84: SAIDJANOV BEHZOD SAIDNAZAROVICH | K84: 20208000307350098001 | L84: 556 | N84: 312586815 | O84: 5ba0tIU8J2 | P84: к | Q84: 1 | R84: 1
B85: =+B84+1 -> 82 | H85: 45986 | I85: EURO MAX SERVICES | J85: JUMABOYEV XUMOYUN | K85: 2.0208e+19 | L85: 816 | N85: 312599102 | O85: AEae2066592 | P85: ккс | Q85: 1 | T85: 1
B86: =+B85+1 -> 83 | H86: 46028 | I86: HAUSE RS TRADE | J86: SAIDJONOV QAHRAMON BEKTURDIYEVICH | L86: 556 | N86: 312696393 | O86: 7 | P86: яс
M94: 0kDY1i34Sh

Sheet Лист6

Sheet с
A1: № | B1: январ | D1: феврвл | E1: март | F1: апрел | G1: май | H1: июн | I1: июл | J1: август | K1: сентябр | L1: октябр | M1: ноябр | N1: декабр | O1: жами
A2: 1 | B2: 5000000 | D2: 6500000 | E2: 6000000 | F2: =2000000+3000000+120000+100000+100000+680000 -> 6000000 | G2: 10000000 | H2: 9000000 | J2: =1000000+500000+1000000+100000+1000000+2400000 -> 6000000 | K2: =4000000+6500000 -> 10500000 | L2: =1500000+500000 -> 2000000 | M2: =1000000+1064000+900000+3000000 -> 5964000 | N2: =3500000+500000-800000 -> 3200000 | O2: =B2+D2+E2+F2+G2+H2+I2+J2+K2+L2+M2+N2-M2-N2 -> 61000000
A3: 2 | O3: =B3+D3+E3+F3+G3+H3+I3+J3+K3+L3+M3+N3 -> 0
A4: 3 | O4: =B4+D4+E4+F4+G4+H4+I4+J4+K4+L4+M4+N4 -> 0
A5: 4 | O5: =B5+D5+E5+F5+G5+H5+I5+J5+K5+L5+M5+N5 -> 0
A6: 5 | O6: =B6+D6+E6+F6+G6+H6+I6+J6+K6+L6+M6+N6 -> 0
A7: 6 | O7: =B7+D7+E7+F7+G7+H7+I7+J7+K7+L7+M7+N7 -> 0
D9: Расход
A10: сана | B10: Расход | G10: № | H10: прихот
A11: 46015 | B11: авария | C11: =265*12000+480000+420000 -> 4080000 | D11: Декабр ойлик | G11: 1 | H11: иш хакки подохот | I11: 460000 | J11: Гулом ога микра
G12: 2 | H12: иш хакки подохот | I12: 300000 | J12: Гулом ога микра
G13: 3 | H13: Ахмед ога бух | I13: 500000 | J13: Бух
G14: 4
G15: 5 | H15: иш хакки подохот | I15: 600000 | J15: Гулом ога мкб
G16: 6 | H16: иш хакки подохот | I16: 1000000 | J16: Бехзод ога Миллий банк
G17: 7
H18: Той | I18: 500000 | J18: Нозима апкам
K20: 45899 | N20: 28705000
N21: 9900000
C22: =SUM(C11:C21) -> 4080000
B24: Банк карздорлик
B25: Микро кредит банк | C25: =(16*350000)*0.24-900000 -> 444000 | D25: Эшон бува
B26: Халк Банк | C26: =(30*350000)*0.24+9442000+1512000-C27 -> 10174000
B27: Халк Банк | C27: 3300000
I45: =I44-I43 -> 0

Sheet сомпютер 
C2: Kompyuter
B3: Жуманазаов Тохир | C3: 7.5 | D3: Ғайрат дарча
B4: Садуллаева Гуламбой | C4: 7.5
B5: Худайберганов Ғанижон | C5: 7.5
B6: Жуманазаров Зафар | C6: 7.5
B7: Исмоилова Ойша | C7: 7.5 | D7: каримбой Сабез
B8: Аллаберганова Гулой | C8: 7.5 | D8: Темур машин
B9: Aminova Zeboxon | C9: 6.5
B10: Тоиров Сухроб | D10: Ренат ога шокир огани платигина 11.75 млн ташлаш керар
B11: Тоирова Матлуба
B12: Davletov Донёр | C12: 7.5 | D12: Азамат
B13: Кодирова Саида | C13: 7.5
B14: Рўзметова Рўзажон | C14: 7.5 | D14: Азамат
B15: Собиров Одамбой | C15: 7.5
B16: Жуманазарова Ўғилжон | C16: 7.5 | D16: Анвар ога
B17: Самандаров Жамшид | C17: 7.5 | D17: Анвар ога
B18: Худайназарова Момогул | C18: 7.5 | D18: Анвар ога
B19: Жуманиёзова Хилола | C19: 7.5 | D19: Анвар ога
B20: Алимбоев Камоладдин | C20: 7.5 | D20: 3.5 млн астака колди
B21: Алимбоева Рухсора | C21: 7.5
B22: Садуллаев Бобуржон | C22: 7.5 | D22: Farid oga
B23: Сапаев нурбек | C23: 7.5 | D23: azamat
B24: Садуллаев Содикжон | C24: 7.5 | D24: gulom mikra
B25: Тажиев Музаффар | C25: 7.5 | D25: Азамат
B26: Умаров Шодлик | C26: 7.5 | D26: Азамат
B27: Сабирова Назокат | C27: 7.5 | D27: Азамат
B28: Курaнбоева Мадина | C28: 5.8 | D28: Азамат
B29: Сотимбоева Нилуфар | C29: 7.5 | D29: Asad Xalq banki
B30: Султонова Махлиё | C30: 7.5 | D30: Азамат
B31: Сапаев Ойбек | C31: 7.5 | D31: Азамат
B32: Babajonova Soxiba | C32: 7.5 | D32: Азамат
B33: Мирзаева Матлуба | C33: 7.5 | D33: Даврон Доктор
... B35: Кушаев Расулбек | C35: 7.5 | D35: Rustam og`a usta mikra
B36: Кушаева Дилафруз | C36: 7.5
B37: Кушаева Гулшода | C37: 7.5
B38: Саидмуротова Зумрад | C38: 7.5 | D38: Ковунчи тошкент колхоз
B39: Турдиева Наргизахон | C39: 7.5 | D39: Сапаев Достон Боходирни укаси
B40: Бахрамова Дилфуза | C40: 6.7 | D40: урганчли апка
B41: Ахмадова Мохидил | C41: 7.5 | D41: Maqsad jura
B42: Бекчанова Анамой | C42: 7.5
B43: Yusupova Saodat | C43: 7 | D43: Baxodir mikra
B44: Egamberdiyev Xayrulla | C44: 7.5 | D44: Ренат ога
B45: Ражабов Жавохир | C45: 7.5 | D45: Maqsad jura
B46: Бекчанов Максадбек | C46: 7.5
B47: Юсупова Мохичехра | C47: 7.5 | D47: Дилшод жура
B48: Юсупов Еркабой | C48: 7.5
B49: Авазов Сулаймон | C49: 6.3 | D49: каримбой Сабез
B50: Исмаилова Фотима | C50: 7.5
B51: Саидниёзов Камолбой | C51: 7.5 | D51: камол ога
B52: Киличев Дилмурод | C52: 7.5 | D52: Дилмурод ога Беруний МФЙ
B53: Худайберганов Отабек | C53: 7.5 | D53: Азамат
B54: Бабахонов Раматилло | C54: 7.5 | D54: Азамат
B55: Худайберганов Полвон | C55: 7.5 | D55: Азамат
B56: Саидова Гуландон | C56: 7.5 | D56: Дилшод жура
B57: Мадаминов Огабек | C57: 7.5 | D57: Азамат
B58: Каримбоев Сирож | C58: 7.5 | D58: узи
B59: Пулатов Сурат | C59: 7.5 | D59: Отабек хоким ёрдамчи
B60: Абдуллаев Санжар | C60: 7.5 | D60: Хасанбой
B61: Абдуллаева Гулжон | C61: 7.5
B62: Ибрагимова Исмигул | C62: 7.5 | D62: Сирож поспон
B63: Сафарбоев Донёрбек | C63: 7.5 | D63: опаси келди
B64: Садуллаева Зайнаб | C64: 7.5 | D64: Хасанбой
B65: Курбонбоев Ўлмас | C65: 7.5
B66: Жуманиёзов Улугбек | C66: 7.5 | D66: Микра юрист
B67: Ахмедов Атхамжон | C67: 7.5
B68: Самандарова Олтиной | C68: 7.5 | D68: Маданият Котиб
B69: Маткурбонова Дилфуза | C69: 7.5 | D69: Жасур халк банк олди
B70: Ахмедов Аброржон | C70: 7.5 | D70: Микра юрист
B71: Сапарбоева Гулёр | C71: 7.5 | D71: ўзи келди
B72: Сапаев Елмурод | C72: 7.5 | D72: Маданият Котиб
B73: Самандаров Нодирбек | C73: 7.5 | D73: Маданият Котиб
B74: Шоназарова Дилноза | C74: 7.5 | D74: Акаси Косим
B75: Курбондурдиев Достон | C75: 7.5 | D75: Зафарбек Ога олиб кетди
B76: Мадаминова Мохира | C76: 7.5
B77: Атаниёзов Умрбек | C77: 7.5
B78: Курбондурдиев Максуд | C78: 7.5
B79: Шариббоева Икбол | C79: 7.5
B80: Садуллаева Гуласал | C80: 7.5
B81: Шомуротов Асад | C81: 7.5
B82: Гаипова Зарнигор | C82: 7.5 | D82: Домла узи
B83: Худайназарова Нилуфар | C83: 7.5 | D83: Жасур халк банк олди
B84: Алимов Анварбек | C84: 7.5 | D84: Улугбек ога уста Халк банки
B85: Ахмадова Комила | C85: 7.5 | D85: Максад охран
B86: Шоназаров Акмалбек | C86: 7.5 | E86: даргумон
B87: Фарходов Акмал | C87: 7.5 | D87: Донёр халк банки
B88: Жабборов Жамшид | C88: 7.5 | D88: Донёр халк банки
B89: Оллаберганов Фаррух | C89: 7.5 | D89: Алибек Ога Паспорт стол
B90: Сафарбоев Қувондик | C90: 7.5
B91: Садуллаева Мохинисо | C91: 7.5 | D91: Улуғ кўзи
B92: Курбонбоева дилдора | C92: 7.5 | D92: Хамид Халк Банки
B93: Жуманиёзов Хамдам | C93: 7.5 | D93: Домла узи
B94: Авезова Мадина | C94: 7.5 | D94: Одилбек ога экология
B95: Хужамуротова Гулхаё | C95: 7.5 | D95: Уз келди
B96: Мадаминова Кумуш | C96: 7.5 | D96: Азамат
B97: Ахмадова Нафиса | C97: 7.5 | D97: Максад охран | E97: 1
B98: Бектурдиев Хаким | C98: 7.5 | D98: Бахриддин ога
B99: Хаитбоев Санжар | C99: 7.5 | D99: Усмон узи олиб кетди
B100: Маткурбонов Усмонжон | C100: 7.5
B101: Олимова Азиза | C101: 7.5 | D101: узи
B102: Машарипова Райхона | C102: 7.5 | D102: Домла узи
...

Sheet Лист1
B4: firma nomi | C4: login | D4: parol | E4: pulniki
A5: 1 | B5: Oq oltin moto | C5: Oqoltinmoto | D5: 310215446 | E5: 500676 | CG5: 25
A6: 2 | B6: Kelajak | C6: 310203 | D6: 310203571 | E6: 521114 | CG6: 33
A7: 3 | B7: Future Moto line | C7: 310267 | D7: 310266415 | E7: 325679 | CG7: 24
A8: 4 | B8: Oq oltin moto trade | C8: 310266 | D8: 310266423 | E8: 513395 | CG8: 30
A9: 5 | B9: Shexmurod 1509 | C9: 310062915 | D9: 310062915 | E9: 477339 | CG9: 22
A10: 6 | B10: Shexmurod 0112 | C10: 310017637 | D10: 310017637 | E10: 142424 | CG10: 33
A11: 7 | B11: Chichila | C11: 7659 | D11: 77777777 | E11: 374351 | F11: 0 | H11: 0 | L11: 0 | N11: 0 | O11: 0 | R11: 0 | T11: 0 | V11: 0 | X11: 0 | Z11: 0 | AT11: 0 | AX11: 0 | BJ11: 0 | BN11: 0 | BP11: 0 | BR11: 0 | BT11: 0 | BV11: 0 | BX11: 0 | BY11: 53.6 | BZ11: 53.6 | CA11: 20.6 | CB11: 8.6 | CG11: 33
A12: 8 | B12: Super moto | C12: 7674 | D12: 310337674 | E12: 365788 | F12: 44 | H12: 44 | I12: =-42.3+22+22 -> 1.7 | J12: 42.3 | K12: 22 | L12: 20.3 | N12: 0 | O12: 0 | R12: 0 | T12: 0 | V12: 0 | X12: 0 | Z12: 0 | AL12: 0 | AM12: 0 | AT12: 0 | AX12: 0 | BB12: 0 | BH12: 0 | BJ12: 0 | BL12: 0 | BN12: 0 | BP12: 0 | BR12: 0 | BT12: 0 | BV12: 0 | BX12: 0 | BY12: 19.8 | BZ12: 19.8 | CA12: 19.8 | CB12: 19.8 | CG12: 33
A13: 9 | B13: Bog`ot kelajak moto | C13: 310401800 | D13: 310401800 | E13: 199050 | F13: 3 | H13: 3 | J13: 3 | L13: 3 | N13: 3 | O13: 0 | P13: 3 | R13: 3 | T13: 0 | V13: 0 | X13: 0 | Z13: 0 | AL13: 0 | AM13: 0 | AT13: 0 | AX13: 0 | BB13: 0 | BH13: 0 | BJ13: 0 | BL13: 0 | BN13: 0 | BP13: 0 | BR13: 0 | BT13: 0 | BV13: 0 | BX13: 0 | BZ13: 0 | CA13: 0 | CB13: 0 | CG13: 32 | CH13: 14 | CI13: 11 | CJ13: =324.8+8.8 -> 333.6 | CK13: 325 | CL13: 407 | CM13: 29.5 | CN13: 340 | CO13: 271.5 | CP13: 321.5 | CQ13: 5.5 | CR13: 5.5 | CS13: 5.5 | CT13: 5.5 | CU13: 5.5 | CV13: 364.5 | CW13: 23.4 | CX13: 173.4 | CY13: 163 | CZ13: 49.7 | DA13: 86.5 | DB13: 73.5 | DC13: 108.8 | DD13: 87.2 | DE13: 85.2 | DF13: 78 | DG13: 18 | DH13: 296 | DI13: 323.7 | DJ13: 620.6 | DK13: 7.3 | DL13: 8.1 | DM13: 34.3 | DN13: 241 | DO13: 100.4 | DP13: 132 | DQ13: 79.5 | DR13: 77.5 | DS13: 37.7 | DT13: 210 | DU13: 222.3 | DV13: 221.6 | DW13: 25.5 | DX13: 50.6 | DY13: 68.6 | DZ13: 142.7 | EA13: 224.4 | EB13: 11.8 | EC13: 9.2 | ED13: 41.6 | EE13: 49 | EF13: 20.1 | EG13: =155.7+5.7+276.4 -> 437.8 | EH13: =4.2+5.1+276.4 -> 285.7 | EI13: 289.4 | EK13: =+EH13-EI13 -> -3.7 | EM13: 5.5 | EN13: 5.5 | EO13: 5.5 | EP13: 5.5 | EQ13: 5.5 | ER13: 5.5 | ES13: 5.5 | ET13: 5.5 | EU13: 5.5 | EV13: 5.5 | EW13: 5.5 | EX13: 5.5 | EY13: 5.5 | EZ13: 5.5 | FA13: 5.5 | FB13: 5.5 | FC13: 5.5 | FD13: 5.5 | FE13: 5.5 | FF13: 5.5 | FG13: 5.5 | FH13: 5.5 | FI13: 5.5 | FJ13: 5.5 | FK13: 5.5 | FL13: 5.5 | FM13: 5.5 | FN13: 5.5 | FO13: 5.5 | FP13: 5.5 | FQ13: 5.5 | FR13: 5.5 | FS13: 5.5 | FT13: 5.5 | FU13: 5.2 | FV13: 5.5 | FW13: 5.5 | FX13: 5.5 | FY13: 5.5
A14: 10 | B14: Bog`ot lochin Armada moto MCHJ | C14: 310401792 | D14: 310401792 | E14: 569470 | F14: 0 | H14: 0 | I14: -6.3 | J14: 6.3 | L14: 0 | N14: 0 | O14: -4.7 | P14: 4.7 | R14: 4.7 | S14: =2.1+2.7 -> 4.8 | T14: 22 | V14: 22 | X14: 22 | Y14: 22 | Z14: 0 | AF14: 0 | AG14: =22-41 -> -19 | AH14: 19 | AL14: 0 | AM14: 0 | AT14: 22 | AX14: 0 | BB14: 0 | BF14: 0 | BH14: 0 | BJ14: 0 | BL14: 0 | BN14: 0 | BP14: 0 | BR14: 23 | BT14: 23 | BV14: 23 | BX14: 0 | BY14: 24 | BZ14: 24 | CA14: 24 | CB14: 24 | CG14: 32.9 | CH14: 3.1 | CI14: 2.1 | CJ14: 8.6 | CK14: 8.6 | CL14: 20.6 | CM14: 53.6 | CQ14: 7.2 | CR14: 7.2 | CS14: 7.2 | CT14: 7.2 | CU14: 7.2 | CY14: 6.2 | CZ14: 6.2 | DA14: 6.2 | DB14: 6.2 | DC14: 6.2 | DD14: 6.2 | DE14: 6.2 | DF14: 6.2 | DG14: 6.2 | DH14: 6.2 | DI14: 6.2 | DJ14: 6.2 | DK14: 6.2 | DL14: 6.2 | DM14: 6.2 | DN14: 6.2 | DO14: 6.2 | DP14: 6.2 | DQ14: 6.2 | DR14: 6.2 | DS14: 6.2 | DT14: 6.2 | DU14: 6.2 | DV14: 6.2 | DW14: 6.2 | DX14: 6.2 | DY14: 6.2 | DZ14: 6.2 | EA14: 6.2 | EB14: 6.2 | EC14: 6.2 | ED14: 6.2 | EE14: 6.2 | EF14: 6.2 | EG14: 6 | EH14: 6 | EI14: 6 | EK14: =+EH14-EI14 -> 0 | EM14: 7.2 | EN14: 7.2 | EO14: 7.2 | EP14: 7.2 | EQ14: 7.2 | ER14: 7.2 | ES14: 7.2 | ET14: 7.2 | EU14: 7.2 | EV14: 7.2 | EW14: 7.2 | EX14: 7.2 | EY14: 7.2 | EZ14: 7.2 | FA14: 7.2 | FB14: 7.2 | FC14: 7.2 | FD14: 7.2 | FE14: 7.2 | FF14: 7.2 | FG14: 7.2 | FH14: 7.2 | FI14: 7.2 | FJ14: 7.2 | FK14: 7.2 | FL14: 7.2 | FM14: 7.2 | FN14: 7.2 | FO14: 7.2 | FP14: 7.2 | FQ14: 7.2 | FR14: 7.2 | FS14: 7.2 | FT14: 7.2 | FU14: 7.2 | FV14: 7.2 | FW14: 7.2 | FX14: 7.2 | FY14: 7.2
A15: 11 | B15: ASHXABOD MOTOROLLER | C15: 310423741 | D15: 310423741 | E15: 194459 | F15: 0 | H15: 0 | J15: 0 | L15: 0 | N15: 0 | O15: -3.8 | P15: 3.85 | R15: 3.85 | T15: 0 | V15: 0 | X15: 0 | Z15: 0 | AA15: =20.4+5-25.2 -> 0.2 | AF15: 0 | AH15: 0 | AL15: 0 | AM15: 0 | AT15: 0 | AX15: 0 | BB15: 0 | BF15: 0 | BH15: 0 | BJ15: 0 | BL15: 0 | BN15: 0 | BP15: 0 | BR15: 24 | BS15: 24 | BT15: 0 | BV15: 0 | BX15: 0 | BY15: 66.4 | BZ15: 66.4 | CA15: 66.4 | CB15: 44.4 | CH15: 0.6 | CI15: 20.6 | CJ15: 19.8 | CK15: 19.8 | CL15: 19.8 | CM15: 19.8 | CO15: 23 | CP15: 23 | CQ15: 0.2 | CR15: 0.2 | CS15: 0.2 | CT15: 0.2 | CU15: 0.2 | CV15: 23 | CW15: 23 | CX15: 22 | CY15: 22 | DA15: 66 | DB15: 8.5 | DC15: 15.9 | DF15: 24.78 | DG15: 24.78 | DH15: 22 | DI15: 23 | DJ15: 24 | DK15: 24 | DL15: 6.8 | DM15: 22.5 | DN15: 15.75 | DO15: 8.25 | DP15: 38.25 | DQ15: 38.25 | DR15: 38.25 | DS15: 20.6 | DZ15: 22 | EA15: 22 | EB15: 3 | EC15: 3 | ED15: 2 | EE15: 20.3 | EF15: 42.3 | EG15: 44 | EH15: 44 | EI15: 44 | EK15: =+EH15-EI15 -> 0 | EM15: 0.2 | EN15: 0.2 | EO15: 0.2 | EP15: 0.2 | EQ15: 0.2 | ER15: 0.2 | ES15: 0.2 | ET15: 0.2 | EU15: 0.2 | EV15: 0.2 | EW15: 0.2 | EX15: 0.2 | EY15: 0.2 | EZ15: 0.2 | FA15: 0.2 | FB15: 0.2 | FC15: 0.2 | FD15: 0.2 | FE15: 0.2 | FF15: 0.2 | FG15: 0.2 | FH15: 0.2 | FI15: 0.2 | FJ15: 0.2 | FK15: 0.2 | FL15: 0.2 | FM15: 0.2 | FN15: 0.2 | FO15: 0.2 | FP15: 0.2 | FQ15: 0.2 | FR15: 0.2 | FS15: 0.2 | FT15: 0.2 | FU15: 0.2 | FV15: 0.2 | FW15: 0.2 | FX15: 0.2 | FY15: 0.2
A16: 12 | B16: Bog`ot Motoroller | C16: 310423575 | D16: 310423575 | E16: 643178 | F16: 2 | H16: 2 | J16: 2 | L16: 2 | N16: 2 | P16: 2 | R16: 2 | T16: 0 | V16: 0 | X16: 0 | Y16: -21.9 | Z16: 21.9 | AF16: 0 | AH16: 0 | AJ16: 0 | AL16: 0 | AN16: 0 | AT16: 0 | AV16: 0 | AX16: 0 | AZ16: 0 | BB16: 0 | BD16: 0 | BF16: 0 | BH16: 0 | BJ16: 0 | BL16: 0 | BM16: -22 | BN16: 22 | BP16: 22 | BR16: 0 | BS16: =24-33.9 -> -9.9 | BT16: 10 | BV16: 10 | BX16: 5.7 | BZ16: 5.7 | CA16: 5.7 | CB16: 55.7 | CH16: 24 | CI16: 24 | CJ16: 24 | CK16: 24 | CL16: 24 | CM16: 24 | CQ16: 4.5 | CR16: 4.5 | CS16: 4.5 | CT16: 4.5 | CU16: 4.5 | DA16: 50 | DC16: 23 | DD16: 19 | DE16: 19 | DF16: 32.2 | DG16: 20 | DH16: 16.7 | DI16: 97.5 | DJ16: 66.25 | DK16: 66.25 | DL16: 10 | DM16: 33 | DN16: 22 | DO16: 33.3 | DP16: 32 | DQ16: 32 | DR16: 32 | DX16: 21.9 | DY16: 22 | DZ16: 15 | EA16: 48 | EB16: 4.7 | EC16: 4.7 | ED16: 3 | EE16: 3 | EF16: 3 | EG16: 3 | EH16: 3 | EI16: 3 | EK16: =+EH16-EI16 -> 0 | EM16: 4.5 | EN16: 4.5 | EO16: 4.5 | EP16: 4.5 | EQ16: 4.5 | ER16: 4.5 | ES16: 4.5 | ET16: 4.5 | EU16: 4.5 | EV16: 4.5 | EW16: 4.5 | EX16: 4.5 | EY16: 4.5 | EZ16: 4.5 | FA16: 4.5 | FB16: 4.5 | FC16: 4.5 | FD16: 4.5 | FE16: 4.5 | FF16: 4.5 | FG16: 4.5 | FH16: 4.5 | FI16: 4.5 | FJ16: 4.5 | FK16: 4.5 | FL16: 4.5 | FM16: 4.5 | FN16: 4.5 | FO16: 4.5 | FP16: 4.5 | FQ16: 4.5 | FR16: 4.5 | FS16: 4.5 | FT16: 4.5 | FU16: 4.5 | FV16: 4.5 | FW16: 4.5 | FX16: 4.5 | FY16: 4.5
A17: 13 | B17: Bagat gold drakon | F17: 8.25 | H17: 0 | I17: -8.25 | J17: 8.25 | L17: 8.25 | N17: 8.3 | P17: 7.5 | R17: 0 | T17: 0 | V17: 0 | X17: =+Y17+Z17 -> 0 | Y17: -16.5 | Z17: 16.5 | AA17: =8.25+8.25 -> 16.5 | AB17: 0 | AD17: 0 | AF17: 38.25 | AG17: =8.25-16.5+8.25+15+15 -> 30 | AH17: 8.25 | AI17: =8.25+45-30-30-9+8.25 -> -7.5 | AJ17: =8.25+7.5 -> 15.75 | AL17: 22.5 | AM17: =7.5+8.25 -> 15.75 | AN17: 6.8 | AP17: 0.25 | AQ17: =8.25*5-41 -> 0.25 | AR17: 0 | AS17: =8.25+8.25+8.25+8.25+8.25+8.25+8.25-30-30-14.5 -> -16.75 | AT17: 16.7 | AU17: =8.25+8.25-30-11+8.25+8.25 -> -8 | AV17: 24.78 | AX17: 24.78 | AZ17: 0 | BB17: 15.9 | BC17: =8.25+8.25+8.25+8.25-11.3-10-20+8.25+7.5 -> 7.45 | BD17: 8.5 | BE17: =-66+8.25+8.25-8 -> -57.5 | BF17: 66 | BG17: 41.25 | BH17: 24.75 | BJ17: 0 | BL17: 0 | BN17: 40.53 | BP17: 24.75 | BR17: 0 | BT17: 0 | BV17: 0 | BX17: 16.5 | BZ17: 16.5 | CA17: 8.3 | CB17: 92 | CH17: 2.5 | CI17: 44 | CJ17: 44.4 | CK17: 44.4 | CL17: 66.4 | CM17: 66.4 | CQ17: 62.1 | CR17: 62.1 | CS17: 62.1 | CT17: 62.1 | CU17: 62.1 | DA17: 24 | DB17: 23 | DC17: 23.8 | DF17: 32.2 | DH17: 33 | DI17: 22.4 | DJ17: 100.3 | DK17: 100.3 | DL17: 70 | DM17: 27.3 | DO17: 65.5 | DP17: 21.2 | DQ17: 21.2 | DR17: 21.2 | DX17: 16.5 | DY17: 38.6 | DZ17: 9 | EA17: 33 | EB17: 3.85 | EC17: 3.85 | ED17: 8.3 | EE17: 2 | EF17: 6.3 | EG17: 2 | EH17: 2 | EI17: 2 | EK17: =+EH17-EI17 -> 0 | EM17: 62.1 | EN17: 62.1 | EO17: 62.1 | EP17: 62.1 | EQ17: 62.1 | ER17: 62.1 | ES17: 62.1 | ET17: 62.1 | EU17: 62.1 | EV17: 62.1 | EW17: 62.1 | EX17: 62.1 | EY17: 62.1 | EZ17: 62.1 | FA17: 62.1 | FB17: 62.1 | FC17: 62.1 | FD17: 62.1 | FE17: 62.1 | FF17: 62.1 | FG17: 62.1 | FH17: 62.1 | FI17: 62.1 | FJ17: 62.1 | FK17: 62.1 | FL17: 62.1 | FM17: 62.1 | FN17: 62.1 | FO17: 62.1 | FP17: 62.1 | FQ17: 62.1 | FR17: 62.1 | FS17: 62.1 | FT17: 62.1 | FU17: 62.1 | FV17: 62.1 | FW17: 62.1 | FX17: 62.1 | FY17: 62.1
A18: =+A17+1 -> 14 | B18: Soxibkor motoroller | C18: 310453508 | D18: 310453508 | E18: 168969 | F18: 0 | G18: 0 | H18: 0 | I18: -22 | J18: 22 | K18: 22 | L18: 22 | M18: 22 | N18: 21 | O18: =-28.1+21 -> -7.1 | P18: 28.1 | Q18: 24 | R18: 4.1 | S18: 4.1 | T18: 0 | V18: 0 | X18: =+Y18+Z18 -> 0 | Y18: =-15-5 -> -20 | Z18: 20 | AA18: 20 | AB18: 0 | AC18: 0 | AD18: 0 | AF18: 0 | AH18: 0 | AJ18: 0 | AL18: 33 | AM18: 33 | AN18: 0 | AO18: 0 | AP18: 0 | AR18: 0 | AT18: 0 | AV18: 0 | AW18: -32.2 | AX18: 32.2 | AY18: 31.71 | AZ18: 0.5 | BB18: 0.5 | BD18: 0.5 | BF18: 0.5 | BH18: 0.5 | BJ18: 0.5 | BL18: 0.5 | BM18: 0 | BN18: 0.5 | BP18: 0.5 | BQ18: -52 | BR18: 52.5 | BS18: =23-74+24+30-1.66 -> 1.34 | BT18: 51.2 | BU18: 33 | BV18: 18.2 | BX18: 0.2 | BY18: 69 | BZ18: =+CA18-CD18 -> 69.2 | CA18: 159.2 | CB18: 135.2 | CD18: 90 | CH18: 93.7 | CI18: 33.7 | CJ18: 55.7 | CK18: 55.7 | CL18: 5.7 | CM18: 5.7 | CN18: 5.7 | CO18: 10 | CP18: 10 | CQ18: 1 | CR18: 1 | CS18: 1 | CT18: 1 | CV18: 10 | CW18: 24 | CX18: 24.75 | CY18: 40.53 | DA18: 120.4 | DB18: 23.8 | DC18: 21.5 | DF18: 16.5 | DH18: 77 | DI18: 34.8 | DM18: 49.5 | DO18: 108.8 | DP18: 22.5 | DQ18: 22.5 | DR18: 22.5 | DX18: 20 | DZ18: 39.5 | EA18: 153.5 | EB18: 2 | EC18: 2 | ED18: 21 | EE18: 8.25 | EF18: 8.3 | EG18: 5 | EH18: 5 | EI18: 8.25 | EK18: =+EH18-EI18 -> -3.25
A19: =+A18+1 -> 15 | B19: shabnam | C19: 310453174 | D19: 310453174 | E19: 337796 | F19: 0 | G19: 0 | H19: 0 | I19: -11 | J19: 11 | K19: 11 | L19: 0 | N19: 0 | O19: -3.2 | P19: 3.2 | R19: 3.2 | S19: 3.2 | T19: 0 | V19: 0 | X19: 0 | Z19: 0 | AA19: 0 | AB19: 0 | AC19: 0 | AD19: 0 | AF19: 0 | AH19: 0 | AJ19: 0 | AL19: 0 | AM19: 0 | AN19: 0 | AO19: 0 | AP19: 24 | AQ19: 24 | AR19: 0 | AT19: 0 | AV19: 0 | AW19: -32.2 | AX19: 32.2 | AY19: 32.2 | AZ19: 0 | BB19: 0 | BD19: 0 | BF19: 50 | BH19: 0 | BI19: -50 | BJ19: 50 | BK19: 50 | BL19: 0 | BM19: 0 | BN19: 0 | BP19: 0 | BQ19: -32 | BR19: 32.04 | BS19: =25-1.66 -> 23.34 | BT19: 8.7 | BU19: -200 | BV19: 209 | BW19: 100 | BX19: =24+BZ19 -> 190 | BZ19: =+CA19+CC19-CD19 -> 166 | CA19: 211 | CB19: 111.9 | CC19: =21+24 -> 45 | CD19: 90 | CH19: 116 | CI19: 92 | CJ19: 92 | CK19: 92 | CL19: 8.3 | CM19: 16.5 | CN19: 16.5 | CO19: 18.2 | CP19: 51.2 | CQ19: 25 | CR19: 25 | CS19: 25 | CT19: 25 | CU19: 25 | CV19: 51.2 | CW19: 52.5 | CX19: 0.5 | CY19: 0.5 | DA19: 30.2 | DB19: 21.5 | DC19: 97.3 | DD19: 52.3 | DE19: 52.3 | DF19: 21.5 | DO19: 19 | DP19: 83.7 | DQ19: 83.7 | DR19: 83.7 | DX19: 76 | DZ19: 76.5 | EB19: 4.1 | EC19: 7.5 | ED19: 29.9 | EE19: 22 | EF19: 2 | EI19: 4.5 | EK19: =+EH19-EI19 -> -4.5 | EM19: 25 | EN19: 25 | EO19: 25 | EP19: 25 | EQ19: 25
A20: =+A19+1 -> 16 | B20: largo | C20: 310455544 | D20: 310455544 | E20: 845517 | F20: 0 | G20: 0 | H20: 0 | I20: 0 | J20: 0 | L20: 0 | N20: 0 | O20: 0 | P20: 0 | R20: 0 | S20: 0 | T20: 0 | V20: 0 | X20: 0 | Z20: 0 | AA20: 0 | AB20: 0 | AC20: 0 | AD20: 0 | AF20: 0 | AH20: 0 | AJ20: 0 | AL20: 0 | AM20: 0 | AN20: 0 | AO20: 0 | AP20: 0 | AR20: 0 | AT20: 0 | AV20: 0 | AW20: -16.5 | AX20: 16.5 | AY20: -2.5 | AZ20: 19 | BB20: 23 | BD20: 23 | BE20: =-24+23 -> -1 | BF20: 24 | BG20: 24 | BH20: 0 | BJ20: 0 | BL20: 0 | BM20: -25.9 | BN20: 25.9 | BP20: 25.9 | BQ20: 26 | BR20: 0 | BS20: -105.5 | BT20: 105.5 | BU20: =-100-100 -> -200 | BV20: 305.7 | BW20: 100 | BX20: =+BZ20-BY20 -> 250.5 | BY20: 10 | BZ20: =+CA20+CC20-CD20 -> 260.5 | CA20: 313.5 | CB20: 338.5 | CC20: =24+22+18+33 -> 97 | CD20: =100+50 -> 150 | CH20: 153.9 | CI20: 116 | CJ20: 135.2 | CK20: 135.2 | CL20: 159.2 | CM20: 69.2 | CN20: 0.2 | CO20: 209 | CP20: 8.7 | CQ20: 2.2 | CR20: 2.2 | CS20: 2.2 | CT20: 2.2 | CU20: 2.2 | CV20: 8.7 | CW20: 32.04 | CX20: 25.9 | CY20: 25.9 | DA20: 128 | DF20: 41.7 | EB20: 3.2 | EC20: 28.1 | ED20: 100 | EE20: 22 | EF20: 22 | EI20: 19.6 | EK20: =+EH20-EI20 -> -19.6 | EM20: 2.2 | EN20: 2.2 | EO20: 2.2 | EP20: 2.2 | EQ20: =2.2+17.5 -> 19.7 | ER20: 19.7 | ES20: 19.5 | ET20: =2.2+17.5 -> 19.7 | EU20: 19.7 | EV20: 19.7 | EW20: 19.7 | EX20: 19.7 | EY20: 19.7 | EZ20: 19.7 | FA20: 19.7 | FB20: 19.7 | FC20: 19.7 | FD20: 19.7 | FE20: 14.7 | FF20: 14.7 | FG20: 14.7 | FH20: 14.7 | FI20: 14.7 | FJ20: 14.7 | FK20: 14.7 | FL20: 14.7 | FM20: 14.7 | FN20: 14.7 | FO20: 14.7 | FP20: 14.7 | FQ20: 14.7 | FR20: 14.7 | FS20: 14.7 | FT20: 14.7 | FU20: 14.7 | FV20: 14.7 | FW20: 14.7 | FX20: 14.7 | FY20: 14.7
A21: =+A20+1 -> 17 | B21: oltinqum | C21: 310455536 | D21: 310455536 | E21: 317083 | F21: 0 | G21: 0 | H21: 0 | I21: 0 | J21: 0 | L21: 0 | N21: 0 | O21: -1.92 | P21: 1.92 | R21: 1.92 | S21: 1.959 | T21: 0 | V21: 0 | X21: 0 | Z21: 0 | AA21: 0 | AB21: 0 | AC21: 0 | AD21: 0 | AF21: 0 | AH21: 0 | AJ21: 0 | AL21: 0 | AM21: 0 | AN21: 0 | AO21: 0 | AP21: 0 | AQ21: 0 | AR21: 0 | AT21: 0 | AV21: 0 | AW21: -21.5 | AX21: 21.5 | AY21: =24-2.5 -> 21.5 | AZ21: 0 | BB21: 23.8 | BD21: 23.8 | BE21: =-59.8-59.8+23 -> -96.6 | BF21: 120.4 | BH21: 120.4 | BI21: =10+33 -> 43 | BJ21: 77.4 | BK21: 21 | BL21: 56.4 | BM21: =-59.8-59.8-26+28+28 -> -89.6 | BN21: 146 | BO21: =33+17+19.2 -> 69.2 | BP21: 76.8 | BQ21: =-22+24+22+6.5+24 -> 54.5 | BR21: =+BS21+BT21 -> 22.34 | BS21: =-60-1.66+24 -> -37.66 | BT21: 60 | BU21: =22+30-100 -> -48 | BV21: 108 | BW21: 100 | BX21: =+BZ21-BY21 -> 53 | BY21: =90+100 -> 190 | BZ21: 243 | CA21: 432.3 | CB21: 265.4 | CC21: =25+27+24 -> 76 | CD21: =250+15 -> 265 | CH21: 161 | CI21: 208 | CJ21: 111.9 | CK21: 111.9 | CL21: 211 | CM21: 166 | CN21: 190 | CO21: 305.7 | CP21: 105.5 | CQ21: 35 | CR21: 35 | CS21: 35 | CT21: 35 | CU21: 35 | CV21: 105.5 | CW21: 22.34 | CX21: 76.8 | CY21: 146 | CZ21: 56.4 | DA21: 155.3 | DF21: 22 | DG21: 87 | EB21: 2 | EC21: 3.2 | EF21: 11 | EK21: =+EH21-EI21 -> 0 | EM21: 35 | EN21: 35 | EO21: 35 | EP21: 35 | EQ21: 35 | ER21: 35 | ES21: 35 | ET21: 35 | EU21: 35 | EV21: 35 | EW21: 35 | EX21: 35 | EY21: 35 | EZ21: 35 | FA21: 35 | FB21: 35 | FC21: 35 | FD21: 36 | FE21: 36 | FF21: 36 | FG21: 36 | FH21: 36 | FI21: 36 | FJ21: 0
A22: =+A21+1 -> 18 | B22: Qalajiqala | C22: 310495320 | D22: 310495320 | E22: 170580 | F22: 0 | G22: 0 | H22: 0 | I22: 0 | J22: 0 | L22: 0 | N22: 0 | O22: -25.1 | P22: 25.15 | R22: 25.15 | S22: =22+3.15 -> 25.15 | T22: 0 | V22: 0 | X22: 0 | Z22: 0 | AA22: 0 | AB22: 0 | AC22: 0 | AD22: 0 | AF22: 0 | AH22: 0 | AJ22: 0 | AL22: 0 | AM22: 0 | AN22: 0 | AO22: 0 | AP22: 0 | AQ22: -23 | AR22: 23 | AS22: 23 | AT22: 0 | AU22: -20 | AV22: 20 | AW22: =-41.7+20 -> -21.7 | AX22: 41.7 | AY22: =21+23-2.5 -> 41.5 | AZ22: 0 | BB22: 0 | BD22: 0 | BE22: -30 | BF22: 30.2 | BH22: 30.2 | BI22: =11.5+23-100 -> -65.5 | BJ22: 95.7 | BK22: =-100-90+21+22 -> -147 | BL22: 242.7 | BM22: =-400-1+28+23+32+20+22 -> -276 | BN22: 518.7 | BO22: =22+20+28+24 -> 94 | BP22: =+BQ22+BR22 -> 424.69 | BQ22: 30 | BR22: =+BS22+BT22 -> 394.69 | BS22: =22+23+23-1.66-1.1-0.25+33+23+23 -> 143.99 | BT22: 250.7 | BU22: =22+22+22+33+2+32+33-100+22 -> 88 | BV22: 163 | BW22: 100 | CO22: 108 | CP22: 60 | CV22: 60 | CW22: 394.7 | CX22: 424.7 | CY22: 518.7 | CZ22: 242.7 | DF22: 150.8 | DG22: 190.8 | EB22: 25.1 | EC22: 2 | EF22: 22 | EK22: =+EH22-EI22 -> 0
A23: =+A22+1 -> 19 | B23: Obod | C23: 310495337 | D23: 310495337 | E23: 396479 | F23: 0 | G23: 0 | H23: 0 | I23: 0 | J23: 0 | L23: 0 | N23: 0 | O23: 0 | P23: 0 | R23: 0 | S23: 0 | T23: 0 | V23: 0 | X23: 0 | Z23: 0 | AA23: 0 | AB23: 0 | AC23: 0 | AD23: 0 | AE23: -32 | AF23: 32 | AH23: 0 | AJ23: 0 | AL23: 0 | AM23: -10 | AN23: 10 | AO23: 10 | AP23: 0 | AQ23: =-97+33-33.5 -> -97.5 | AR23: 97.5 | AS23: =-33+26+22+22+27.5 -> 64.5 | AT23: 33 | AU23: =-87+33 -> -54 | AV23: 87 | AW23: =-22+32+22+33 -> 65 | AX23: 22 | AY23: 22 | AZ23: 0 | BB23: 21.5 | BD23: 21.5 | BE23: =-28-100+21.5 -> -106.5 | BF23: 128 | BG23: =-10+24+23+33 -> 70 | BH23: 58 | BI23: =22+22.7+23+33-100+33+24 -> 57.7 | BJ23: 0 | BK23: =22+24+24-100-46 -> -76 | BL23: 76.3 | BM23: =-200-0.5 -> -200.5 | BN23: 276.84 | BO23: =12+22 -> 34 | BP23: =+BQ23+BR23 -> 242.84 | BQ23: =24+33+33+33 -> 123 | BR23: =+BS23+BT23 -> 119.84 | BS23: =33-1.66 -> 31.34 | BT23: 88.5 | BU23: 58.5 | BV23: 30 | CO23: 163 | CP23: 250.7 | CV23: 250.7 | CW23: 119.84 | CX23: 242.84 | CY23: 276.84 | CZ23: 76.3 | EB23: 2.1 | EC23: 25.15 | EF23: 2.65 | EK23: =+EH23-EI23 -> 0
A24: =+A23+1 -> 20 | B24: Bog`zor | C24: 310483842 | D24: 310483842 | E24: 716581 | F24: 0 | G24: 0 | H24: 0 | I24: -22 | J24: 22 | K24: 22 | L24: 22 | M24: 22 | N24: 0 | O24: -2 | P24: 2.1 | Q24: 0 | R24: 2.1 | S24: =-48+2.1 -> -45.9 | T24: 48 | U24: 33 | V24: 15 | X24: 0 | Z24: 0 | AA24: 0 | AB24: 0 | AC24: =33-33 -> 0 | AD24: 0 | AE24: =-21+11.7+22-33.9 -> -21.2 | AF24: 21.2 | AH24: 33.3 | AJ24: 0.3 | AK24: 0 | AL24: 27.3 | AM24: 27 | AN24: 0.3 | AO24: -66 | AP24: 66.25 | AQ24: =24+22-68+33+32.85 -> 43.85 | AR24: 22.4 | AS24: 22 | AT24: 0.4 | AU24: =-97-93 -> -190 | AV24: 190.8 | AW24: =-150+20+24+28+21.5+22+22+26+26.5 -> 40 | AX24: 150.8 | AY24: =22+23-2.5+33+23 -> 98.5 | AZ24: 52.3 | BA24: =-97+22+22+8 -> -45 | BB24: 97.3 | BC24: =22+27+26.5+22 -> 97.5 | BD24: 0 | BE24: =33-188 -> -155 | BF24: 155.3 | BG24: 155.325 | EB24: 1 | EC24: 2.1 | EF24: 3.8 | EK24: =+EH24-EI24 -> 0
A25: =+A24+1 -> 21 | B25: G`alaba Qaxramon | C25: 310488749 | D25: 310488749 | E25: 214100 | F25: 0 | G25: 0 | H25: 0 | I25: -2.64 | J25: 2.65 | K25: 2.65 | L25: 0 | N25: 0 | O25: -5 | P25: 5 | Q25: 5 | R25: 0 | S25: 0 | T25: 33 | U25: 24 | V25: 9 | X25: 0 | Z25: 0 | AA25: 0 | AB25: 0 | AC25: =22-22.4 -> -0.4 | AD25: 0.4 | AE25: =15+7-44 -> -22 | AF25: 22.5 | AG25: =-65+22 -> -43 | AH25: 65.5 | AI25: =21.5+22 -> 43.5 | AJ25: 22 | AK25: =-49.5+22+33+22-77+22 -> -27.5 | AL25: 49.5 | AM25: =-15-55+23+26.5 -> -20.5 | AN25: 70 | AO25: =-100+22+24+24 -> -30 | AP25: 100.3 | AQ25: =22+22+22+21.5+21+24+33-100 -> 65.5 | AR25: 34.8 | AS25: =-76+12+22 -> -42 | AT25: 77 | AU25: =22+22+33 -> 77 | EB25: 41.6 | EC25: 5 | EF25: 130.5 | EK25: =+EH25-EI25 -> 0
A26: =+A25+1 -> 22 | B26: Gulzor Behzod | C26: 310510278 | D26: 310510278 | E26: 729470 | F26: 4.5 | G26: -0.5 | H26: 5 | I26: =-1.66+32-34.1+5 -> 1.24 | J26: 3.8 | K26: =4.7-1 -> 3.7 | L26: 0 | M26: -29.9 | N26: 29.9 | O26: =-80+18+11.9 -> -50.1 | P26: 80 | Q26: =33+22+25 -> 80 | R26: 0 | S26: 0 | T26: 0 | U26: 24 | V26: 39.5 | W26: =32.9-71.5+23+16.5 -> 0.9 | X26: 38.6 | Y26: =-76+22+16.5 -> -37.5 | Z26: 76 | AA26: =9+21+22+24 -> 76 | AB26: 0 | AC26: =26-10+31+28-95+33-3-30+33+22+22+22-99 -> -20 | AD26: 20.2 | AE26: =-15+21.5+22.5-100+28.5-41+20 -> -63.5 | AF26: =50.8+32.975 -> 83.775 | AG26: =-100+22+22+33+32+33-100 -> -58 | AH26: =22+31.8+22+33 -> 108.8 | EC26: 80 | EF26: 49.6 | EK26: =+EH26-EI26 -> 0
A27: =+A26+1 -> 23 | B27: Madaniyat Izzat | C27: 996767914 | D27: 996767914 | E27: 603038 | F27: 0 | G27: 0 | H27: 0 | I27: =-1.6-100-28.8-98+28+24+24+22 -> -130.4 | J27: 130.5 | K27: =24+18+33+22.5+33 -> 130.5 | L27: 0 | M27: -99.8 | N27: 100 | O27: =22+22+22+33 -> 99 | P27: 1 | R27: 1 | S27: =33+33-18-200 -> -152 | T27: 153.5 | U27: =22+22+33 -> 77 | V27: =27.5+27+22 -> 76.5 | X27: 0 | Z27: 0 | EC27: 1 | EK27: =+EH27-EI27 -> 0
A28: 24 | B28: Yusup Izzat Abdulla Izzat | C28: 309561982 | D28: 309561982 | E28: 872313 | F28: 0 | G28: =20-19.6 -> 0.4 | H28: 0 | I28: -49.6 | J28: 49.6 | K28: 49.5 | L28: 0 | M28: 0 | N28: 0 | O28: -41.6 | P28: 41.6 | R28: 41.6 | S28: =45-3.4 -> 41.6 | T28: 0 | U28: 0 | V28: 0 | X28: 0 | Z28: 0 | EC28: 41.6 | EK28: =+EH28-EI28 -> 0
A29: 25q | B29: Bog`zor Armada motors Izzat | C29: 310572178 | D29: 310572178 | EK29: =+EH29-EI29 -> 0
A30: 26q | B30: Obod Armada Motors MCHJ | C30: 310573334 | D30: 310573334 | E30: 893304 | F30: 19.6 | G30: 19.6 | EK30: =+EH30-EI30 -> 0
A31: 27q | B31: Oq Oltin Armada motors MCHJ | C31: 310572408 | D31: 310572408 | EK31: =+EH31-EI31 -> 0
A32: 28q | B32: Navbaxor Armada motors | C32: 310572312 | D32: 310572312 | EK32: =+EH32-EI32 -> 0
A33: 29 | B33: OQ OLTIN XUGO MOTORS | C33: 310616929 | D33: 310616929 | EK33: =+EH33-EI33 -> 0
A34: 30 | B34: BOG'OT ARMADA MOTORS | C34: 310626773 | D34: 310626773 | EK34: =+EH34-EI34 -> 0
EK35: =+EH35-EI35 -> 0
BZ36: 0 | CA36: 72.5 | CB36: 75 | CD36: 79.7 | CH36: 75 | CI36: 467.5 | CJ36: 338.5 | CK36: 338.5 | CL36: 313.5 | CM36: 260.5 | CN36: 250.5 | CO36: 30 | CP36: 88.5 | CQ36: 1.66 | CR36: 1.66 | CS36: 1.66 | CT36: 1.66 | CU36: 1.66 | CV36: 88.5 | EK36: =+EH36-EI36 -> 0 | EM36: 1.66 | EN36: 1.66 | EO36: 1.66 | EP36: 1.66 | EQ36: 1.66 | ER36: 1.66 | ES36: 1.66 | ET36: 1.66 | EU36: 1.66 | EV36: 1.66 | EW36: 1.66 | EX36: 1.66 | EY36: 1.66 | EZ36: 1.66 | FA36: 1.66 | FB36: 1.66 | FC36: 1.66 | FD36: 1.66 | FE36: 1.66 | FF36: 1.66 | FG36: 1.66 | FH36: 1.66 | FI36: 1.66 | FJ36: 1.66 | FK36: 1.66 | FL36: 1.66 | FM36: 1.66 | FN36: 1.66 | FO36: 1.66 | FP36: 1.66 | FQ36: 1.66 | FR36: 1.66 | FS36: 1.66 | FT36: 1.66 | FU36: 1.66 | FV36: 1.66 | FW36: 1.66 | FX36: 1.66 | FY36: 1.66
CH37: 0.9 | CI37: 75 | CJ37: 265.4 | CK37: 265.4 | CL37: 432.5 | CM37: 243 | CN37: 53 | CQ37: 7.5 | CR37: 7.5 | CS37: 7.5 | CT37: 7.5 | CU37: 7.5 | EK37: =+EH37-EI37 -> 0 | EM37: 7.5 | EN37: 7.5 | EO37: 7.5 | EP37: 7.5 | EQ37: 7.5 | ER37: 7.5 | ES37: 7.5 | ET37: 7.5 | EU37: 7.5 | EV37: 7.5 | EW37: 7.5 | EX37: 7.5 | EY37: 7.5 | EZ37: 7.5 | FA37: 7.5 | FB37: 7.5 | FC37: 7.5 | FD37: 7.5 | FE37: 7.5 | FF37: 7.5 | FG37: 7.5 | FH37: 7.5 | FI37: 7.5 | FJ37: 7.5 | FK37: 7.5 | FL37: 7.5 | FM37: 7.5 | FN37: 7.5 | FO37: 7.5 | FP37: 7.5 | FQ37: 7.5 | FR37: 7.5 | FS37: 7.5 | FT37: 7.5 | FU37: 7.5 | FV37: 7.5 | FW37: 7.5 | FX37: 7.5 | FY37: 7.5
CH38: 1.74 | CI38: 0.9 | CJ38: 75 | CK38: 75 | CL38: 72.5 | CM38: 0 | CN38: 0 | CQ38: 4.5 | CR38: 4.5 | CS38: 4.5 | CT38: 4.5 | CU38: 4.5 | CZ38: 0.9 | DA38: 0.9 | DB38: 0.9 | DC38: 0.9 | DD38: 0.9 | DE38: 0.9 | DF38: 0.9 | DG38: 0.9 | DH38: 0.9 | DI38: 0.9 | DJ38: 0.9 | DK38: 0.9 | DL38: 0.9 | DM38: 0.9 | DN38: 0.9 | DO38: 0.9 | DP38: 0.9 | DQ38: 0.9 | DR38: 0.9 | DS38: 0.9 | DT38: 0.9 | DU38: 0.9 | DV38: 0.9 | DW38: 0.9 | DX38: 0.9 | DY38: 0.9 | DZ38: 0.9 | EA38: 0.9 | EB38: 0.9 | EC38: 0.9 | ED38: 0.9 | EE38: 0.9 | EF38: 0.9 | EG38: 0.9 | EH38: 0.9 | EI38: 0.9 | EK38: =+EH38-EI38 -> 0 | EM38: 4.5 | EN38: 4.5 | EO38: 4.5 | EP38: 4.5 | EQ38: 4.5 | ER38: 4.5 | ES38: 4.5 | ET38: 4.5 | EU38: 4.5 | EV38: 4.5 | EW38: 4.5 | EX38: 4.5 | EY38: 4.5 | EZ38: 4.5 | FA38: 4.5 | FB38: 4.5 | FC38: 4.5 | FD38: 4.5 | FE38: 4.5 | FF38: 4.5 | FG38: 4.5 | FH38: 4.5 | FI38: 4.5 | FJ38: 4.5 | FK38: 4.5 | FL38: 4.5 | FM38: 4.5 | FN38: 4.5 | FO38: 4.5 | FP38: 4.5 | FQ38: 4.5 | FR38: 4.5 | FS38: 4.5 | FT38: 4.5 | FU38: 4.5 | FV38: 4.5 | FW38: 4.5 | FX38: 4.5 | FY38: 4.5
CH39: 2.8 | CI39: 1.74 | CJ39: 0.9 | CK39: 0.9 | CL39: 0.9 | CM39: 0.9 | CN39: 0.9 | CO39: 0.9 | CP39: 0.9 | CQ39: 5 | CR39: 5 | CS39: 5 | CT39: 5 | CU39: 5 | CV39: 0.9 | CW39: 0.9 | CX39: 0.9 | CY39: 0.9 | CZ39: 1.74 | DA39: 1.74 | DB39: 1.74 | DC39: 1.74 | DD39: 1.74 | DE39: 1.74 | DF39: 1.74 | DG39: 1.74 | DH39: 1.74 | DI39: 1.74 | DJ39: 1.74 | DK39: 1.74 | DL39: 1.74 | DM39: 1.74 | DN39: 1.74 | DO39: 1.74 | DP39: 1.74 | DQ39: 1.74 | DR39: 1.74 | DS39: 1.74 | DT39: 1.74 | DU39: 1.74 | DV39: 1.74 | DW39: 1.74 | DX39: 1.74 | DY39: 1.74 | DZ39: 1.74 | EA39: 1.74 | EB39: 1.74 | EC39: 1.74 | ED39: 1.74 | EE39: 1.74 | EF39: 1.74 | EG39: 1.74 | EH39: 1.74 | EI39: 1.74 | EK39: =+EH39-EI39 -> 0 | EM39: 5 | EN39: 5 | EO39: 5 | EP39: 5 | EQ39: 5 | ER39: 5 | ES39: 5 | ET39: 5 | EU39: 5 | EV39: 5 | EW39: 5 | EX39: 5 | EY39: 5 | EZ39: 5 | FA39: 5 | FB39: 5 | FC39: 5 | FD39: 5 | FE39: 5 | FF39: 5 | FG39: 5 | FH39: 5 | FI39: 5 | FJ39: 5 | FK39: 5 | FL39: 5 | FM39: 5 | FN39: 5 | FO39: 5 | FP39: 5 | FQ39: 5 | FR39: 5 | FS39: 5 | FT39: 5 | FU39: 5 | FV39: 5 | FW39: 5 | FX39: 5 | FY39: 5
C40: 100 | AL40: 17.4 | CH40: 15 | CI40: 2.8 | CJ40: 1.74 | CK40: 1.74 | CL40: 1.74 | CM40: 1.74 | CN40: 1.74 | CO40: 1.74 | CP40: 1.74 | CQ40: 0.8 | CR40: 0.8 | CS40: 0.8 | CT40: 0.8 | CU40: 0.8 | CV40: 1.74 | CW40: 1.74 | CX40: 1.74 | CY40: 1.74 | CZ40: 2.8 | DA40: 2.8 | DB40: 2.8 | DC40: 2.8 | DD40: 2.8 | DE40: 2.8 | DF40: 2.8 | DG40: 2.8 | DH40: 2.8 | DI40: 2.8 | DJ40: 2.8 | DK40: 2.8 | DL40: 0.9 | DM40: 0.9 | DN40: 0.9 | DO40: 0.9 | DP40: 0.9 | DQ40: 0.9 | DR40: 0.9 | DS40: 0.9 | DT40: 0.9 | DU40: 0.9 | DV40: 0.9 | DW40: 0.9 | DX40: 0.9 | DY40: 0.9 | DZ40: 0.9 | EA40: 0.9 | EB40: 0.9 | EC40: 0.9 | ED40: 0.9 | EE40: 0.9 | EF40: 0.9 | EG40: 0.9 | EH40: 0.9 | EI40: 0.9 | EK40: =+EH40-EI40 -> 0 | EM40: 0.8 | EN40: 0.8 | EO40: 0.8 | EP40: 0.8 | EQ40: 0.8 | ER40: 0.8 | ES40: 0.8 | ET40: 0.8 | EU40: 0.8 | EV40: 0.8 | EW40: 0.8 | EX40: 0.8 | EY40: 0.8 | EZ40: 0.8 | FA40: 0.8 | FB40: 0.8 | FC40: 0.8 | FD40: 0.8 | FE40: 0.8 | FF40: 0.8
C41: 50 | AL41: 4 | CH41: 4.5 | CI41: 15 | CJ41: 2.8 | CK41: 2.8 | CL41: 2.8 | CM41: 2.8 | CN41: 2.8 | CO41: 2.8 | CP41: 2.8 | CQ41: 0.4 | CR41: 0.4 | CS41: 0.4 | CT41: 0.4 | CU41: 0.4 | CV41: 2.8 | CW41: 2.8 | CX41: 2.8 | CY41: 2.8 | CZ41: 15 | DA41: 15 | DB41: 15 | DC41: 15 | DD41: 15 | DE41: 15 | DF41: 15 | DG41: 15 | DH41: 15 | DI41: 15 | DJ41: 15 | DK41: 15 | DL41: 10 | DM41: 10 | DN41: 10 | DO41: 10 | DP41: 10 | DQ41: 10 | DR41: 10 | DS41: 10 | DT41: 10 | DU41: 10 | DV41: 10 | DW41: 10 | DX41: 10 | DY41: 10 | DZ41: 10 | EA41: 10 | EB41: 5 | EC41: 5 | ED41: 5 | EE41: 5 | EF41: 5 | EG41: 5 | EH41: 5 | EI41: 5 | EK41: =+EH41-EI41 -> 0 | EM41: 0.4 | EN41: 0.4 | EO41: 0.4 | EP41: 0.4 | EQ41: 0.4 | ER41: 0.4 | ES41: 0.4 | ET41: 0.4 | EU41: 0.4 | EV41: 0.4 | EW41: 0.4 | EX41: 0.4 | EY41: 0.4 | EZ41: 0.4 | FA41: 0.4 | FB41: 0.4 | FC41: 0.4 | FD41: 0.4 | FE41: 0.4 | FF41: 0.4 | FG41: 0.4 | FH41: 0.4 | FI41: 0.4 | FJ41: 0.4 | FK41: 0.4 | FL41: 0.4 | FM41: 0.4 | FN41: 0.4 | FO41: 0.4 | FP41: 0.4 | FQ41: 0.4 | FR41: 0.4 | FS41: 0.4 | FT41: 0.4 | FU41: 0.4 | FV41: 0.4 | FW41: 0.4 | FX41: 0.4 | FY41: 0.4
C42: 10 | AL42: 21.4 | CH42: 4.5 | CI42: 4.5 | CJ42: 15 | CK42: 15 | CL42: 15 | CM42: 15 | CN42: 15 | CO42: 15 | CP42: 15 | CQ42: 1.8 | CR42: 1.8 | CS42: 1.8 | CT42: 1.8 | CU42: 1.8 | CV42: 15 | CW42: 15 | CX42: 15 | CY42: 15 | CZ42: 4.5 | DA42: 4.5 | DB42: 4.5 | DC42: 4.5 | DD42: 4.5 | DE42: 4.5 | DF42: 4.5 | DG42: 4.5 | DH42: 4.5 | DI42: 4.5 | DJ42: 4.5 | DK42: 4.5 | DL42: 2.1 | DM42: 2.1 | DN42: 2.1 | DO42: 2.1 | DP42: 2.1 | DQ42: 2.1 | DR42: 2.1 | DS42: 2.1 | DT42: 2.1 | DU42: 2.1 | DV42: 2.1 | DW42: 2.1 | DX42: 2.1 | DY42: 2.1 | DZ42: 2.1 | EA42: 2.1 | EB42: 1 | EC42: 1 | ED42: 1 | EE42: 1 | EF42: 1 | EG42: 1 | EH42: 1 | EI42: 1 | EK42: =+EH42-EI42 -> 0 | EM42: 1.8 | EN42: 1.8 | EO42: 1.8 | EP42: 1.8 | EQ42: 1.8 | ER42: 1.8 | ES42: 1.8 | ET42: 1.8 | EU42: 1.8 | EV42: 1.8 | EW42: 1.8 | EX42: 1.8 | EY42: 1.8 | EZ42: 1.8 | FA42: 1.8 | FB42: 1.8 | FC42: 1.8 | FD42: 1.8 | FE42: 1.8 | FF42: 1.8 | FG42: 1.8 | FH42: 1.8 | FI42: 1.8 | FJ42: 1.8 | FK42: 1.8 | FL42: 1.8 | FM42: 1.8 | FN42: 1.8 | FO42: 1.8 | FP42: 1.8 | FQ42: 1.8 | FR42: 1.8 | FS42: 1.8 | FT42: 1.8 | FU42: 1.8 | FV42: 1.8 | FW42: 1.8 | FX42: 1.8 | FY42: 1.8
C43: 50 | AL43: =+AL42+0.8 -> 22.2 | CH43: 4 | CI43: 4.5 | CJ43: 4.5 | CK43: 4.5 | CL43: 4.5 | CM43: 4.5 | CN43: 4.5 | CO43: 4.5 | CP43: 4.5 | CQ43: 2 | CR43: 2 | CS43: 2 | CT43: 2 | CU43: 2 | CV43: 4.5 | CW43: 4.5 | CX43: 4.5 | CY43: 4.5 | CZ43: 4.5 | DA43: 4.5 | DB43: 4.5 | DC43: 4.5 | DD43: 4.5 | DE43: 4.5 | DF43: 4.5 | DG43: 4.5 | DH43: 4.5 | DI43: 4.5 | DJ43: 4.5 | DK43: 4.5 | DL43: 4.5 | DM43: 4.5 | DN43: 4.5 | DO43: 4.5 | DP43: 4.5 | DQ43: 4.5 | DR43: 4.5 | DS43: 4.5 | DT43: 4.5 | DU43: 4.5 | DV43: 4.5 | DW43: 4.5 | DX43: 4.5 | DY43: 4.5 | DZ43: 4.5 | EA43: 4.5 | EC43: 2 | ED43: 2 | EE43: 2 | EF43: 2 | EG43: 2 | EH43: 2 | EI43: 2 | EK43: =+EH43-EI43 -> 0 | EM43: 2 | EN43: 2 | EO43: 2 | EP43: 2 | EQ43: 2 | ER43: 2 | ES43: 2 | ET43: 2 | EU43: 2 | EV43: 2 | EW43: 2 | EX43: 2 | EY43: 2 | EZ43: 2 | FA43: 2 | FB43: 2 | FC43: 2 | FD43: 2 | FE43: 2 | FF43: 2 | FG43: 2 | FH43: 2 | FI43: 2 | FJ43: 2 | FK43: 2 | FL43: 2 | FM43: 2 | FN43: 2 | FO43: 2 | FP43: 2 | FQ43: 2 | FR43: 2 | FS43: 2 | FT43: 2 | FU43: 2 | FV43: 2 | FW43: 2 | FX43: 2 | FY43: 2
C44: 90 | CH44: 6.3 | CI44: 4 | CJ44: 4.5 | CK44: 4.5 | CL44: 4.5 | CM44: 4.5 | CN44: 4.5 | CO44: 4.5 | CP44: 4.5 | CQ44: 5 | CR44: 5 | CS44: 5 | CT44: 5 | CU44: 5 | CV44: 4.5 | CW44: 4.5 | CX44: 4.5 | CY44: 4.5 | CZ44: 4 | DA44: 4 | DB44: 4 | DC44: 4 | DD44: 4 | DE44: 4 | DF44: 4 | DG44: 4 | DH44: 4 | DI44: 4 | DJ44: 4 | DK44: 4 | DL44: 4 | DM44: 4 | DN44: 4 | DO44: 4 | DP44: 4 | DQ44: 4 | DR44: 4 | DS44: 4 | DT44: 4 | DU44: 4 | DV44: 4 | DW44: 4 | DX44: 4 | DY44: 4 | DZ44: 4 | EA44: 4 | EB44: 2 | EC44: 2 | ED44: 2 | EE44: 2 | EF44: 2 | EG44: 2 | EH44: 2 | EI44: 2 | EK44: =+EH44-EI44 -> 0 | EM44: 5 | EN44: 5 | EO44: 5 | EP44: 5 | EQ44: 5 | ER44: 5 | ES44: 5 | ET44: 5 | EU44: 5 | EV44: 5 | EW44: 5 | EX44: 5 | EY44: 5 | EZ44: 5 | FA44: 5 | FB44: 5 | FC44: 5 | FD44: 5 | FE44: 5 | FF44: 5 | FG44: 5 | FH44: 5 | FI44: 5 | FJ44: 5 | FK44: 5 | FL44: 5 | FM44: 5 | FN44: 5 | FO44: 5 | FP44: 5 | FQ44: 5 | FR44: 5 | FS44: 5 | FT44: 5 | FU44: 5 | FV44: 5 | FW44: 5 | FX44: 5 | FY44: 5
C45: 79.7 | CH45: 25 | CI45: 6.3 | CJ45: 4 | CK45: 4 | CL45: 4 | CM45: 4 | CN45: 4 | CO45: 4 | CP45: 4 | CQ45: 22 | CR45: 22 | CV45: 4 | CW45: 4 | CX45: 4 | CY45: 4 | CZ45: 2 | DA45: 2 | DB45: 2 | DC45: 2 | DD45: 2 | DE45: 2 | DF45: 2 | DG45: 2 | DH45: 2 | DI45: 2 | DJ45: 2 | DK45: 2 | DL45: 2 | DM45: 2 | DN45: 2 | DO45: 2 | DP45: 2 | DQ45: 2 | DR45: 2 | DS45: 2 | DT45: 2 | DU45: 2 | DV45: 2 | DW45: 2 | DX45: 2 | DY45: 2 | DZ45: 2 | EA45: 2 | EB45: 2 | EC45: 1 | ED45: 1 | EE45: 1 | EF45: 1 | EG45: 1 | EH45: 1 | EI45: 1 | EK45: =+EH45-EI45 -> 0
C46: 379 | CH46: 25 | CI46: 25 | CJ46: 6.3 | CK46: 6.3 | CL46: 6.3 | CM46: 6.3 | CN46: 6.3 | CO46: 2 | CP46: 2 | CQ46: 8 | CR46: 8 | CS46: 8 | CT46: 8 | CU46: 3 | CV46: 2 | CW46: 2 | CX46: 2 | CY46: 2 | CZ46: 7 | DA46: 7 | DB46: 7 | DC46: 7 | DD46: 7 | DE46: 7 | DF46: 7 | DG46: 7 | DH46: 7 | DI46: 7 | DJ46: 7 | DK46: 7 | DL46: 7 | DM46: 7 | DN46: 7 | DO46: 7 | DP46: 7 | DQ46: 7 | DR46: 7 | DS46: 7 | DT46: 7 | DU46: 7 | DV46: 7 | DW46: 7 | DX46: 7 | DY46: 6 | DZ46: 6 | EA46: 6 | EB46: 2 | EC46: 0.3 | ED46: 0.3 | EE46: 0.3 | EF46: 0.3 | EG46: 0.3 | EH46: 0.3 | EI46: 0.3 | EK46: =+EH46-EI46 -> 0 | EM46: 3 | EN46: 3 | EO46: 3 | EP46: 3 | EQ46: 3 | ER46: 3 | ES46: 3 | ET46: 3 | EU46: 3 | EV46: 3
CH47: 20 | CI47: 25 | CJ47: 25 | CK47: 25 | CL47: 25 | CM47: 25 | CN47: 25 | CO47: 7 | CP47: 7 | CQ47: 0.7 | CR47: 0.7 | CS47: 0.7 | CT47: 0.7 | CU47: 0.7 | CV47: 7 | CW47: 7 | CX47: 7 | CY47: 7 | CZ47: 5.1 | DA47: 5.1 | DB47: 5.1 | DC47: 5.1 | DD47: 5.1 | DE47: 5.1 | DF47: 5.1 | DG47: 5.1 | DH47: 5.1 | DI47: 5.1 | DJ47: 5.1 | DK47: 5.1 | DL47: 5.1 | DM47: 5.1 | DN47: 5.1 | DO47: 5.1 | DP47: 5.1 | DQ47: 5.1 | DR47: 5.1 | DS47: 5.1 | DT47: 5.1 | DU47: 5.1 | DV47: 5.1 | DW47: 5.1 | DX47: 5.1 | DY47: 5.1 | DZ47: 5.1 | EA47: 5.1 | EB47: 1 | EK47: =+EH47-EI47 -> 0 | EM47: 0.7 | EN47: 0.7
CH48: 20 | CI48: 20 | CJ48: 25 | CK48: 25 | CL48: 25 | CM48: 25 | CN48: 25 | CO48: 5.1 | CP48: 5.1 | CQ48: 3 | CR48: 3 | CS48: 3 | CT48: 3 | CU48: 3 | CV48: 5.1 | CW48: 5.1 | CX48: 5.1 | CY48: 5.1 | CZ48: 20 | DA48: 20 | DB48: 20 | DC48: 20 | EB48: 0.3 | EK48: =+EH48-EI48 -> 0 | EM48: 3 | EN48: 3 | EO48: 3 | EP48: 3 | EQ48: 3 | ER48: 3 | ES48: 3 | ET48: 3 | EU48: 3 | EV48: 3 | EW48: 3 | EX48: 3 | EY48: 3 | EZ48: 3 | FA48: 3 | FB48: 3 | FC48: 3 | FD48: 3 | FE48: 3 | FF48: 3 | FG48: 3 | FH48: 3 | FI48: 3
CH49: 291.6 | CI49: 20 | CJ49: 20 | CK49: 20 | CL49: 20 | CM49: 20 | CN49: 20 | CO49: 20 | CP49: 20 | CQ49: 3.3 | CR49: 4.1 | CS49: 4.1 | CT49: 4.1 | CU49: 4.1 | CV49: 20 | CW49: 20 | CX49: 20 | CY49: 20 | CZ49: 2 | DA49: 2 | DB49: 2 | DC49: 2 | DD49: 2 | DE49: 2 | DF49: 2 | DG49: 2 | DH49: 2 | DI49: 2 | DJ49: 2 | DK49: 2 | DL49: 2 | DM49: 2 | DN49: 2 | DO49: 2 | DP49: 2 | DQ49: 2 | DR49: 2 | DS49: 2 | DT49: 2 | DU49: 2 | DV49: 2 | DW49: 2 | DX49: 2 | DY49: 2 | DZ49: 2 | EA49: 2 | EK49: =+EH49-EI49 -> 0 | EM49: 4.1 | EN49: 4.1 | EO49: 4.1 | EP49: 4.1 | EQ49: 4.1 | ER49: 4.1 | ES49: 4.1 | ET49: 4.1 | EU49: 4.1 | EV49: 4.1 | EW49: 4.1 | EX49: 4.1 | EY49: 4.1 | EZ49: 4.1 | FA49: 4.1 | FB49: 4.1 | FC49: 4.1 | FD49: 4.1 | FE49: 4.1 | FF49: 4.1 | FG49: 4.1 | FH49: 4.1 | FI49: 4.1 | FJ49: 4.1 | FK49: 4.1 | FL49: 4.1 | FM49: 4.1 | FN49: 4.1 | FO49: 4.1 | FP49: 4.1 | FQ49: 4.1 | FR49: 4.1 | FS49: 4.1 | FT49: 4.1 | FU49: 4.1 | FV49: 4.1 | FW49: 4.1 | FX49: 4.1 | FY49: 4.1
CH50: 2012 | CI50: 301.9 | CJ50: 20 | CK50: 20 | CL50: 20 | CM50: 20 | CN50: 20 | CO50: 20 | CP50: 20 | CQ50: 18.4 | CV50: 20 | CW50: 20 | CX50: 20 | CY50: 2 | CZ50: 12.4 | DA50: 12.4 | DB50: 12.4 | DC50: 12.4 | DD50: 12.4 | DE50: 12.4 | DF50: 12.4 | DG50: 12.4 | DH50: 12.4 | DI50: 12.4 | DJ50: 12.4 | DK50: 12.4 | DL50: 2 | DM50: 2 | DN50: 2 | DO50: 2 | DP50: 2 | DQ50: 2 | DR50: 2 | DS50: 2 | DT50: 2 | DU50: 2 | DV50: 2 | DW50: 2 | DX50: 2 | DY50: 2 | DZ50: 2 | EA50: 2 | EK50: =+EH50-EI50 -> 0
CH51: 17.1 | CI51: 1961.5 | CJ51: 271.3 | CK51: 251.8 | CL51: 245.3 | CM51: 243.2 | CN51: 25 | CO51: 25 | CP51: 25 | CQ51: 3.5 | CV51: 25 | CW51: 25 | CX51: 25 | CY51: 12.4 | CZ51: 4.1 | DA51: 4.1 | DB51: 4.1 | DC51: 4.1 | DD51: 4.1 | DE51: 4.1 | DF51: 4.1 | DG51: 4.1 | DH51: 4.1 | DI51: 4.1 | DJ51: 4.1 | DK51: 4.1 | DL51: 4.1 | DM51: 4.1 | DN51: 4.1 | DO51: 4.1 | DP51: 4.1 | DQ51: 4.1 | DR51: 4.1 | DS51: 4.1 | DT51: 4.1 | DU51: 4.1 | DV51: 4.1 | DW51: 4.1 | DX51: 4.1 | DY51: 4.1 | DZ51: 4.1 | EA51: 4.1 | EK51: =+EH51-EI51 -> 0
CC52: =152445*11450 -> 1745495250 | CH52: 195 | CI52: 17.1 | CJ52: 2025 | CK52: 2090 | CL52: 2197 | CM52: 2226.5 | CN52: 25 | CO52: 25 | CP52: 25 | CQ52: 17.2 | CV52: 25 | CW52: 25 | CX52: 25 | CY52: 4.1 | CZ52: 23.5 | DA52: 23.5 | DB52: 23.5 | DC52: 23.5 | DD52: 14.5 | DE52: 14.5 | DF52: 14.5 | DG52: 14.5 | DH52: 14.5 | DI52: 14.5 | DJ52: 14.5 | DK52: 14.5 | DL52: 14.5 | DM52: 14.5 | DN52: 14.5 | DO52: 14.5 | DP52: 14.5 | DQ52: 14.5 | DR52: 14.5 | DS52: 2.4 | DT52: 2.4 | DU52: 2.4 | DV52: 2.4 | DW52: 2.4 | DX52: 2.4 | DY52: 2.4 | DZ52: 2.4 | EA52: 2.4 | EK52: =+EH52-EI52 -> 0
CC53: 794000000 | CH53: 33 | CI53: 151 | CJ53: 17.1 | CK53: 17.1 | CL53: 17.1 | CM53: 17.1 | CN53: 248.3 | CO53: 273.45 | CP53: 286 | CQ53: 4 | CR53: 4 | CS53: 4 | CT53: 4 | CU53: 4 | CV53: 286 | CW53: 309 | CX53: 277.1 | CY53: 322.6 | CZ53: 290 | DA53: 294.8 | DB53: =326.6-17.5 -> 309.1 | DC53: 312.92 | DD53: 20 | DE53: 20 | DF53: 20 | DG53: 20 | DH53: 20 | DI53: 20 | DJ53: 20 | DK53: 20 | DL53: 20 | DM53: 20 | DN53: 20 | DO53: 20 | DP53: 20 | DQ53: 20 | DR53: 20 | DS53: 12.3 | DT53: 12.3 | DU53: 12.3 | DV53: 12.3 | DW53: 12.3 | DX53: 12.3 | DY53: 12.3 | DZ53: 3 | EA53: 3 | EB53: 3 | EC53: 3 | ED53: 3 | EE53: 3 | EF53: 3 | EG53: 0.35 | EH53: 0.35 | EI53: 0.35 | EK53: =+EH53-EI53 -> 0 | EM53: 4 | EN53: 4 | EO53: 4 | EP53: 4 | EQ53: 4 | ER53: 4 | ES53: 4 | ET53: 4 | EU53: 4 | EV53: 4 | EW53: 4 | EX53: 4 | EY53: 4 | EZ53: 4 | FA53: 4 | FB53: 4 | FC53: 4 | FD53: 4 | FE53: 4 | FF53: 4 | FG53: 4 | FH53: 4 | FI53: 4 | FJ53: 4 | FK53: 4 | FL53: 4 | FM53: 4 | FN53: 4 | FO53: 4 | FP53: 4 | FQ53: 4 | FR53: 4 | FS53: 4 | FT53: 4 | FU53: 4 | FV53: 4 | FW53: 4 | FX53: 4 | FY53: 4
CC54: =+CC52-CC53 -> 951495250 | CH54: 235 | CI54: 33 | CJ54: 151 | CK54: 151 | CL54: 217 | CM54: 217 | CN54: 2494 | CO54: 2367 | CP54: 2318 | CQ54: 6.24 | CR54: 6.24 | CS54: 6.24 | CT54: 6.24 | CU54: 6.24 | CV54: 2643 | CW54: 2514 | CX54: 2492.5 | CY54: 2597.8 | CZ54: 2677.8 | DA54: 2918 | DB54: 3065.3 | DC54: 3239.3 | DD54: 336.8 | DE54: 336.8 | DF54: 341.2 | DG54: 372.75 | DH54: 346.1 | DI54: 338.8 | DJ54: 337.7 | DK54: 357.35 | DL54: 339.2 | DM54: 15 | DN54: 15 | DO54: 15 | DP54: 15 | DQ54: 15 | DR54: 15 | DS54: 15 | DT54: 15 | DU54: 15 | DV54: 15 | DW54: 15 | DX54: 6 | DY54: 6 | DZ54: 6 | EA54: 6 | EB54: 6 | EC54: 6 | ED54: 6 | EE54: 6 | EF54: 0.135 | EG54: 0.135 | EH54: 0.135 | EI54: 0.135 | EK54: =+EH54-EI54 -> 0 | EM54: 6.24 | EN54: 6.24 | EO54: 6.24 | EP54: 6.24 | EQ54: 6.24 | ER54: 6.24 | ES54: 6.24 | ET54: 6.24 | EU54: 6.24 | EV54: 6.24 | EW54: 6.24 | EX54: 6.24 | EY54: 6.24 | EZ54: 6.24 | FA54: 6.24 | FB54: 6.24 | FC54: 6.24 | FD54: 6.24 | FE54: 6.24 | FF54: 6.24 | FG54: 6.24 | FH54: 6.24 | FI54: 6.24 | FJ54: 6.24 | FK54: 6.24 | FL54: 6.24 | FM54: 6.24 | FN54: 6.24 | FO54: 6.24 | FP54: 6.24 | FQ54: 6.24 | FR54: 6.24
CH55: 139 | CI55: 246 | CJ55: 33 | CK55: 33 | CL55: 33 | CM55: 33 | CN55: 17.1 | CO55: 17.1 | CP55: 17.1 | CQ55: 20 | CR55: 20 | CS55: 20 | CT55: 20 | CU55: 20 | CV55: 17.1 | CW55: 17.1 | CX55: 17.1 | CY55: 17.1 | CZ55: 17.1 | DA55: 17.1 | DB55: 17.1 | DC55: 17.1 | DD55: 3328.5 | DE55: 3446.5 | DF55: 3424.5 | DG55: 3434 | DH55: 3515 | DI55: 3608.5 | DJ55: 3719 | DK55: 3831 | DL55: 4202.5 | DM55: 319.65 | DN55: 341.5 | DO55: 311.85 | DP55: 347 | DQ55: 372.9 | DR55: 363.37 | DS55: 304.2 | DT55: 10 | DU55: 10 | DV55: 10 | DW55: 10 | DX55: 10 | DY55: 25 | DZ55: 25 | EA55: 25 | EB55: 25 | EC55: 25 | ED55: 25 | EE55: 25 | EF55: 7 | EG55: 7 | EH55: 7 | EI55: 7 | EK55: =+EH55-EI55 -> 0 | EM55: 20 | EN55: 20 | EO55: 20 | EP55: 20 | EQ55: 20 | ER55: 20 | ES55: 20 | ET55: 20 | EU55: 20 | EV55: 20 | EW55: 20 | EX55: 20 | EY55: 20 | EZ55: 20 | FA55: 20 | FB55: 20 | FC55: 20 | FD55: 20
CH56: 556.7 | CI56: 139 | CJ56: 262.5 | CK56: 262.5 | CL56: 272 | CM56: 277 | CN56: =160+33 -> 193 | CO56: =160+33 -> 193 | CP56: 193 | CQ56: 2.1 | CR56: 2.1 | CS56: 2.1 | CT56: 2.1 | CU56: 2.1 | CV56: 193 | CW56: 193 | CX56: 193 | CY56: 193 | CZ56: =160+66 -> 226 | DA56: 226 | DB56: 226 | DC56: 226 | DD56: 17.1 | DE56: 17.1 | DF56: 17.1 | DG56: 17.1 | DH56: 17.1 | DI56: 17.1 | DJ56: 17.1 | DK56: 17.1 | DL56: 17.1 | DM56: 4233.7 | DN56: 4275.2 | DO56: 4366.2 | DP56: 4380.2 | DQ56: 4512.2 | DR56: 4546 | DS56: 4593.5 | DT56: 337.2 | DU56: 348.71 | DV56: 343 | DW56: 367.82 | DX56: 376 | DY56: 373.1 | DZ56: 395.3 | EA56: 400.52 | EB56: 365.7 | EC56: 321.34 | ED56: 355.24 | EE56: 334.5 | EF56: 335.4 | EG56: 331.4 | EH56: =321.5+6 -> 327.5 | EI56: 327.2 | EK56: =+EH56-EI56 -> 0.3 | EM56: 2.1 | EN56: 2.1 | EO56: 2.1 | EP56: 2.1 | EQ56: 2.1 | ER56: 2.1 | ES56: =2.1+0.9 -> 3 | ET56: 3 | EU56: 3 | EV56: 3 | EW56: 3 | EX56: 3 | EY56: 3 | EZ56: 3 | FA56: 3 | FB56: 3 | FC56: 3 | FD56: 3 | FE56: 3 | FF56: 3 | FG56: 3 | FH56: 3 | FI56: 3 | FJ56: 3 | FK56: 3 | FL56: 3 | FM56: 3 | FN56: 3 | FO56: 3 | FP56: 3 | FQ56: 3 | FR56: 3 | FS56: 3 | FT56: 3 | FU56: 3 | FV56: 3 | FW56: 3 | FX56: 3 | FY56: 3
CH57: 8.7 | CI57: 338 | CJ57: 100.7 | CK57: 118 | CL57: 20.6 | CM57: 3.5 | CN57: 287 | CO57: 287 | CP57: =287+3.4 -> 290.4 | CQ57: 1 | CR57: 1 | CS57: 1 | CT57: 1 | CU57: 1 | CV57: 292 | CW57: 295 | CX57: 295 | CY57: 295 | CZ57: 295 | DA57: 310 | DB57: 310 | DC57: 310 | DD57: 273 | DE57: 273 | DF57: 273 | DG57: 273 | DH57: 273 | DI57: 273 | DJ57: 273 | DK57: 273 | DL57: 273 | DM57: 17.1 | DN57: 17.1 | DO57: 17.1 | DP57: 17.1 | DQ57: 17.1 | DR57: 17.1 | DS57: 17.1 | DT57: 4550 | DU57: 4638.5 | DV57: 4773.5 | DW57: 4954.5 | DX57: 5290.85 | DY57: 5620.85 | DZ57: 5708.85 | EA57: 5824.85 | EB57: 5896.85 | EC57: 6083.35 | ED57: 6134.15 | EE57: 6211.15 | EF57: 6233.65 | EG57: 6229.2 | EH57: 6223.2 | EI57: 6406.15 | EK57: =+EH57-EI57 -> -182.95 | EM57: 1 | EN57: 1 | EO57: 1 | EP57: 1 | EQ57: 1 | ER57: 1 | ES57: 1 | ET57: 1 | EU57: 1 | EV57: 1 | EW57: 1 | EX57: 1 | EY57: 1 | EZ57: 1 | FA57: 1 | FB57: 1 | FC57: 1 | FD57: 1 | FE57: 1 | FF57: 1 | FG57: 1 | FH57: 1 | FI57: 1 | FJ57: 1 | FK57: 1 | FL57: 1 | FM57: 1 | FN57: 1 | FO57: 1 | FP57: 1 | FQ57: 1 | FR57: 1 | FS57: 1 | FT57: 1 | FU57: 1 | FV57: 1 | FW57: 1 | FX57: 1 | FY57: 1
CH58: -208.5 | CI58: 8.7 | CJ58: 21.4 | CK58: 21 | CL58: 1.3 | CM58: 250 | CN58: 36.6 | CO58: 31 | CP58: 58.4 | CQ58: 3 | CR58: 3 | CS58: 3 | CT58: 0.712 | CU58: 0.712 | CV58: 75.5 | CW58: 196 | CX58: 235.8 | CY58: 0 | CZ58: 38.9 | DA58: 320.6 | DB58: 434 | DC58: 298.8 | DD58: 310 | DE58: 310 | DF58: 310 | DG58: 310 | DH58: 312.7 | DI58: 312.7 | DJ58: 312.7 | DK58: 312.7 | DL58: 312.7 | DM58: 273 | DN58: 273 | DO58: 240 | DP58: 240 | DQ58: 240 | DR58: 240 | DS58: 307 | DT58: 17.1 | DU58: 17.1 | DV58: 17.1 | DW58: 17.1 | DX58: 17.1 | DY58: 17.1 | DZ58: 17.1 | EA58: 17.1 | EB58: 17.1 | EC58: 17.1 | ED58: 17.1 | EE58: 17.1 | EF58: 17.1 | EG58: 17.1 | EH58: 17.1 | EI58: 17.1 | EK58: =+EH58-EI58 -> 0 | EM58: 0.712 | EN58: 0.712 | EO58: 0.712 | EP58: 0.712 | EQ58: 0.712 | ER58: 0.712 | ES58: 0.712 | ET58: 0.712 | EU58: 0.712 | EV58: 0.712 | EW58: 0.712 | EX58: 0.712
CH59: 17 | CI59: -208.5 | CJ59: 8.7 | CK59: 8.7 | CL59: 8.7 | CM59: 8.7 | CN59: 201 | CO59: 209 | CP59: 202.5 | CQ59: 0.7 | CR59: 0.7 | CS59: 0.7 | CT59: 0.7 | CU59: 0.7 | CV59: 189.6 | CW59: 405 | CX59: 253 | CY59: 254 | CZ59: 545.5 | DA59: 365.2 | DB59: 244.5 | DC59: 211 | DD59: 0 | DE59: 35.5 | DF59: 55 | DG59: 26.3 | DH59: 69.8 | DJ59: 6 | DK59: 6 | DL59: 6 | DM59: 313 | DN59: 313 | DO59: 313 | DP59: 313 | DQ59: 313 | DR59: 334 | DS59: 334 | DT59: 307 | DU59: 307 | DV59: 307 | DW59: 307 | DX59: 307 | DY59: 307 | DZ59: 307 | EA59: 283 | EB59: 283 | EC59: 283 | ED59: 283 | EE59: 283 | EF59: 283 | EG59: 283 | EH59: 283 | EI59: 283 | EK59: =+EH59-EI59 -> 0 | EM59: 0.7 | EN59: 0.7 | EO59: 0.7 | EP59: 0.7 | EQ59: 0.7 | ER59: 0.7 | ES59: 0.7 | ET59: 0.7
CH60: 56 | CI60: 17 | CJ60: -8.7 | CK60: -8.7 | CL60: -8.7 | CM60: -8.7 | CN60: 8.7 | CO60: 8.7 | CP60: 8.7 | CQ60: 3 | CR60: 3 | CS60: 3 | CT60: 3 | CU60: 3 | CV60: 8.7 | CW60: 8.7 | CX60: 8.7 | CY60: 8.7 | CZ60: 8.7 | DA60: 8.7 | DB60: 8.7 | DC60: 8.7 | DD60: 158.5 | DE60: 134.5 | DF60: 77.4 | DG60: 40 | DH60: 11.5 | DI60: 2.5 | DJ60: 22 | DK60: 74.4 | DL60: 105.3 | DM60: 6 | DN60: 6 | DO60: 6 | DP60: 6 | DQ60: 6 | DR60: 6 | DS60: 6 | DT60: 300 | DU60: 304 | DV60: 304 | DW60: 304 | DX60: 307 | DY60: 307 | DZ60: 312.5 | EA60: 313 | EB60: 313 | EC60: 315 | ED60: 257 | EE60: 258 | EF60: 258 | EG60: 265 | EH60: 301.5 | EI60: 301.5 | EK60: =+EH60-EI60 -> 0 | EM60: 3 | EN60: 3 | EO60: 3 | EP60: 3 | EQ60: 3 | ER60: 3 | ES60: 3 | ET60: 3 | EU60: 3 | EV60: 3 | EW60: 3 | EX60: 3 | EY60: 3 | EZ60: 3 | FA60: 3 | FB60: 3 | FC60: 3 | FD60: 3 | FE60: 3 | FF60: 3 | FG60: 3 | FH60: 3 | FI60: 3 | FJ60: 3 | FK60: 3 | FL60: 3 | FM60: 3 | FN60: 3 | FO60: 3 | FP60: 3 | FQ60: 3 | FR60: 3 | FS60: 3 | FT60: 3 | FU60: 3 | FV60: 3 | FW60: 3 | FX60: 3 | FY60: 3
CH61: 56 | CI61: 56 | CJ61: -721.35 | CK61: -721.35 | CL61: -755.7 | CM61: =-755.7+500+114.5 -> -141.2 | CN61: -8.7 | CO61: 11.5 | CP61: 11.5 | CQ61: 11.4 | CR61: 11.4 | CS61: 11.4 | CT61: 11.4 | CU61: 11.4 | CV61: 11.5 | CW61: -951.5 | CX61: -951 | CY61: -877 | CZ61: -277 | DA61: -1387.4 | DB61: -788.5 | DC61: -788.5 | DD61: 11.6 | DE61: 11.6 | DF61: 11.6 | DG61: 11.6 | DH61: 11.6 | DI61: 11.6 | DJ61: 11.6 | DK61: 275 | DL61: 392 | DM61: 154.5 | DN61: 206.1 | DO61: 18.3 | DP61: 73.8 | DQ61: 125.9 | DR61: 156.8 | DS61: 217.2 | DT61: 6 | DU61: 6 | DV61: 6 | DW61: 6 | DX61: 6 | DY61: 6 | DZ61: 6 | EA61: 6 | EB61: 6 | EC61: 6 | ED61: 6 | EE61: 6 | EF61: 6 | EG61: 6 | EH61: 6 | EI61: 6 | EK61: =+EH61-EI61 -> 0 | EM61: =11.4+11.5-2.28-2.3 -> 18.32 | EN61: 18.32 | EO61: 18.32 | EP61: 18.32 | EQ61: 18.32 | ER61: 18.32 | ES61: 18.32 | ET61: 18.32
CH62: 609.7 | CI62: 56 | CJ62: 17 | CK62: 17 | CL62: 17 | CM62: 17 | CN62: -142.5 | CO62: -944 | CP62: -544 | CQ62: 3 | CR62: 3 | CV62: -544 | CW62: 17 | CX62: 17 | CY62: 17 | CZ62: 17 | DA62: 34.7 | DB62: 34.7 | DC62: 9.7 | DD62: -1057.2 | DE62: -1007.2 | DF62: -1757.4 | DG62: -1316.2 | DH62: -1281.85 | DI62: -998 | DJ62: -948.1 | DK62: 11.6 | DL62: 11.6 | DM62: 346.5 | DN62: 323.2 | DO62: 288.5 | DP62: 231.5 | DQ62: 185 | DR62: 164 | DS62: 173.4 | DT62: 208 | DU62: 199.8 | DV62: 217 | DW62: 0 | DX62: 17.28 | DY62: 32.2 | DZ62: 0 | EA62: 56.3 | EB62: 17.3 | EC62: 53.3 | ED62: -27.8 | EE62: -55.68 | EF62: -83.5 | EG62: -83.5 | EH62: -83.5 | EI62: -83.5 | EK62: =+EH62-EI62 -> 0
CI63: 562.2 | CJ63: 56 | CK63: 56 | CL63: 56 | CM63: 56 | CN63: 17 | CO63: 17 | CP63: 17 | CR63: 1 | CS63: 1.5 | CT63: 0.5 | CV63: 17 | CW63: -33 | CX63: 17.3 | DD63: 1560 | DE63: 62 | DF63: 62 | DG63: 62 | DH63: 62 | DI63: 72.9 | DJ63: 72.9 | DK63: -1438.1 | DL63: -1167.3 | DM63: 11.6 | DN63: 11.6 | DO63: 11.6 | DP63: 11.6 | DQ63: 11.6 | DR63: 11.6 | DS63: 11.6 | DT63: 115.5 | DU63: 172 | DV63: 201 | DW63: 200 | DX63: 83 | DY63: 71.3 | DZ63: 95.5 | EA63: 116.5 | EB63: 262.7 | EC63: 311.6 | ED63: 17.3 | EE63: 35.65 | EF63: 49.88 | EG63: 62.6 | EH63: 18.56 | EI63: 40.6 | EK63: =+EH63-EI63 -> -22.04
CJ64: 56 | CK64: 56 | CN64: 56 | CO64: 56 | CP64: 56 | CR64: 5.2 | CS64: 5.2 | CT64: 1.52 | CU64: 1.52 | CV64: 56 | CW64: 28 | CX64: 51.3 | DE64: 1344.7 | DF64: 2134.1 | DG64: 1936 | DH64: -17.5 | DK64: 92.1 | DL64: 92.1 | DM64: -1063.1 | DN64: -1063.1 | DO64: -1424.6 | DP64: -1124 | DQ64: -1124 | DR64: -1926.1 | DS64: -2429.1 | DT64: 11.6 | DU64: 11.6 | DV64: 11.6 | DW64: 11.6 | DX64: 11.6 | DY64: 11.6 | DZ64: 11.6 | EA64: 11.6 | EB64: 11.6 | EC64: 11.6 | ED64: 325.5 | EE64: 376.5 | EF64: 236 | EG64: 261.2 | EH64: 254 | EI64: 275.6 | EK64: =+EH64-EI64 -> -21.6 | EM64: 1.52 | EN64: 1.52 | EO64: 1.52
CJ65: 1075.1 | CK65: 963 | CL65: 814 | CM65: 732.8 | CN65: 473 | CO65: 1192.4 | CP65: 1032 | CR65: 1.5 | CS65: 1.5 | CV65: 695.5 | CW65: 1272.5 | CX65: 1012.6 | CY65: 1009.2 | CZ65: 869.5 | DA65: 1573.68 | DB65: 1249.6 | DC65: 986.3 | DD65: 180 | DE65: 180 | DH65: 1711.08 | DI65: 1351.5 | DJ65: 1049.8 | DK65: 1607 | DL65: 1094.5 | DM65: 92.1 | DN65: -21.7 | DO65: -21.7 | DP65: -21.7 | DQ65: -21.7 | DR65: -21.7 | DS65: -43.5 | DT65: -2329.3 | DU65: 34.6 | DY65: 17 | DZ65: 0 | ED65: 34.6 | EE65: 11.6 | EF65: 11.6 | EG65: 11.6 | EH65: 74 | EI65: 17.15 | EK65: =+EH65-EI65 -> 56.85
CS66: 2 | CT66: 2 | CU66: 2.2 | CX66: 28 | CY66: 28 | DC66: 176.3 | DD66: 43.7 | DK66: 33.5 | DN66: 92.1 | DO66: 71.1 | DP66: 39.7 | DQ66: 39.7 | DR66: 39.7 | DS66: 90.7 | DT66: -43.5 | DU66: -2329.3 | DV66: -2329.3 | DW66: -2700 | DX66: -2595 | DY66: -2495 | DZ66: -3265 | EA66: -3196.9 | EB66: -3620 | EC66: -3603 | ED66: 11.6 | EE66: -3143 | EF66: -3961 | EG66: 34.2 | EH66: 11.6 | EI66: 74 | EK66: =+EH66-EI66 -> -62.4 | EM66: 2.2 | EN66: 2.2 | EO66: 2.2 | EP66: 2.2 | EQ66: 2.2 | ER66: 2.2 | ES66: 2.2 | ET66: 2.2 | EU66: 2.2 | EV66: 2.2 | EW66: 2.2 | EX66: 2.2 | EY66: 2.2 | EZ66: 2.2 | FA66: 2.2 | FB66: 2.2 | FC66: 2.2 | FD66: 2.2 | FE66: 2.2 | FF66: 2.2 | FG66: 2.2 | FH66: 2.2 | FI66: 2.2 | FJ66: 2.2 | FK66: 2.2 | FL66: 2.2 | FM66: 2.2 | FN66: 2.2 | FO66: 2.2 | FP66: 2.2 | FQ66: 2.2 | FR66: 2.2 | FS66: 2.2 | FT66: 2.2 | FU66: 2.2 | FV66: 2.2 | FW66: 2.2 | FX66: 2.2 | FY66: 2.2
CS67: 3 | CT67: 3 | CU67: 3 | DM67: 883.3 | DN67: 687 | DO67: 1292.7 | DP67: 1080.1 | DQ67: 920.5 | DR67: 1657.9 | DS67: 2225.3 | DT67: 40.7 | DU67: -43.5 | DV67: -43.5 | DW67: -43.5 | DX67: -43.5 | DY67: -43.5 | DZ67: -43.5 | EA67: -43.5 | EB67: -65 | EC67: -65.5 | ED67: -3361 | EE67: -65.5 | EF67: -65.5 | EG67: 55.5 | EI67: 11.6 | EK67: =+EH67-EI67 -> -11.6 | EM67: =3+1 -> 4 | EN67: 4 | EO67: 4 | EP67: 4 | EQ67: 4 | ER67: 4 | ES67: 4 | ET67: 4 | EU67: 4 | EV67: 4 | EW67: 4 | EX67: 4 | EY67: 4 | EZ67: 4 | FA67: 4 | FB67: 4 | FC67: 4 | FD67: 4 | FE67: 4 | FF67: 4 | FG67: 4 | FH67: 4 | FI67: 4 | FJ67: 4 | FK67: 4 | FL67: 4 | FM67: 4 | FN67: 4 | FO67: 4 | FP67: 4
CT68: 2 | CU68: 2 | DT68: 2093.6 | DU68: 91.76 | DV68: 91.76 | DW68: 91.76 | DX68: 91.76 | DY68: 91.76 | DZ68: 41.76 | EA68: 41.76 | EB68: -8.24 | EC68: 3 | ED68: -65.5 | EG68: -3961 | EH68: -3789 | EI68: -3789 | EK68: =+EH68-EI68 -> 0 | EM68: 2 | EN68: 2 | EO68: 2 | EP68: 2 | EQ68: 2 | ER68: 2 | ES68: 2 | ET68: 2 | EU68: 2 | EV68: 2 | EW68: 2 | EX68: 2 | EY68: 2 | EZ68: 2 | FA68: 2 | FB68: 2 | FC68: 2 | FD68: 2 | FE68: 2 | FF68: 2 | FG68: 2 | FH68: 2 | FI68: 2 | FJ68: 2 | FK68: 2 | FL68: 2 | FM68: 2 | FN68: 2 | FO68: 2 | FP68: 4.2 | FQ68: 4.2 | FR68: 4.2 | FS68: 4.7 | FT68: 4.7 | FU68: 4.7 | FV68: 4.7 | FW68: 4.7 | FX68: 4.7 | FY68: 4.7
CU69: 1.2 | DU69: 1869.21 | DV69: 1753.5 | DW69: 2371.8 | DX69: 1993.4 | DY69: 1691 | DZ69: 2351 | EA69: 2029 | EB69: 2760.5 | EC69: 2425 | ED69: 3 | EE69: 2057.3 | EF69: 2798.5 | EG69: -65.5 | EH69: -44 | EI69: -44 | EK69: =+EH69-EI69 -> 0 | EM69: 1.2 | EN69: 1.2 | EO69: 1.2 | EP69: 1.2 | EQ69: 1.2 | ER69: 1.2 | ES69: 1.2 | ET69: 1.2 | EU69: 1.2 | EV69: 1.2 | EW69: 1.2 | EX69: 1.2 | EY69: 1.2 | EZ69: 1.2 | FA69: 1.2 | FB69: 1.2 | FC69: 1.2 | FD69: 1.2 | FE69: 1.2 | FF69: 1.2 | FG69: 1.2 | FH69: 1.2 | FI69: 1.2 | FJ69: 1.2 | FK69: 1.2 | FL69: 1.2 | FM69: 1.2 | FN69: 1.2 | FO69: 1.2 | FP69: 1.2 | FQ69: 1.2 | FR69: 1.2 | FS69: 1.2 | FT69: 1.2 | FU69: 1.2 | FV69: 1.2 | FW69: 1.2 | FX69: 1.2 | FY69: 1.2
CU70: 3.03 | ED70: 2260.9 | EG70: 2585 | EH70: 2568.8 | EI70: 2332.1 | EK70: =+EH70-EI70 -> 236.7 | EM70: 0
EF71: 17.1 | EM71: -10
DL72: 5910.64 | EM72: 0.1 | EN72: 0.1 | EO72: 0.1 | EP72: 0.1 | EQ72: 0.5
DL73: 1989.4 | EM73: 10.05 | EN73: 10.05 | EO73: 10.05
EN74: 15.15 | EO74: 15.15 | EP74: 15.15 | EQ74: 15.15 | ER74: 15.15 | ES74: 15.15 | ET74: 15.15 | EU74: 15.15 | EV74: 15.15 | EW74: 15.15 | EX74: 15.15 | EY74: 15.15 | EZ74: 15.15 | FA74: 15.15 | FB74: 15.15 | FC74: 15.15 | FD74: 15.15 | FE74: 15.15 | FF74: 15.15 | FG74: 15.15 | FH74: 15.15 | FI74: 15.15 | FJ74: 15.15 | FK74: 15.15 | FL74: 15.15 | FM74: 15.15 | FN74: 15.15 | FO74: 15.15 | FP74: 15.15 | FQ74: 15.15 | FR74: 15.15 | FS74: 15.15 | FT74: 15.15 | FU74: 15.15 | FV74: 15.15 | FW74: 15.15 | FX74: 15.15 | FY74: 15.15
EO75: 2.7 | EP75: 2.7 | EQ75: 2.7 | ER75: 0.7 | ES75: 0.7 | ET75: 0.7 | EU75: 0.7 | EV75: 0.7 | EW75: 0.7 | EX75: 0.7 | EY75: 0.7 | EZ75: 0.7 | FA75: 0.7 | FB75: 0.7 | FC75: 0.7 | FD75: 0.7
EO76: 10 | EP76: 10 | EQ76: 10 | ER76: 10 | ES76: 10 | ET76: 10 | EU76: 10 | EV76: 10 | EW76: 10 | EX76: 10 | EY76: 15 | EZ76: 15 | FA76: 15 | FB76: 15 | FC76: 15 | FD76: 15 | FE76: 15 | FF76: 15 | FG76: 15 | FH76: 15 | FI76: 15 | FJ76: 15 | FK76: 15 | FL76: 15 | FM76: 15 | FN76: 15 | FO76: 15 | FP76: 15
EO77: 0.77 | EP77: 0.77 | EQ77: 0.77 | ER77: 0.77 | ES77: 0.77 | ET77: 0.77 | EU77: 0.77 | EV77: 0.77 | EW77: 0.77 | EX77: 0.77 | EY77: 0.77 | EZ77: 0.77 | FA77: 0.77 | FB77: 0.77 | FC77: 0.77 | FD77: 0.8 | FE77: 0.8 | FF77: 0.8 | FG77: 0.8 | FH77: 0.8 | FI77: 0.8 | FJ77: 0.8 | FK77: 0.8 | FL77: 0.8 | FM77: 0.8 | FN77: 0.8 | FO77: 0.8 | FP77: 0.8 | FQ77: 0.8 | FR77: 0.8 | FS77: 0.8 | FT77: 0.8 | FU77: 0.8 | FV77: 0.8 | FW77: 0.8 | FX77: 0.8 | FY77: 0.8
EP78: 5 | EQ78: 5 | ER78: 5 | ES78: 5 | ET78: =5+18.4 -> 23.4 | EU78: 23.4 | EV78: 23.4 | EW78: 23.4 | EX78: 23.4 | EY78: 23.4 | EZ78: 23.4 | FA78: 23.4 | FB78: 23.4 | FC78: 23.4 | FD78: 23.4 | FE78: 23.4
EP79: 6 | EQ79: 6
EP80: 0.315 | EQ80: 0.315
EQ81: 3 | ER81: 3 | ES81: 3 | ET81: 3 | EU81: 3 | EV81: 3 | EW81: 3
EQ82: 2.2 | ER82: 2.2 | ES82: 2.2 | ET82: 2.2 | EU82: 2.2 | EV82: 2.2 | EW82: 2.2 | EX82: 2.2 | EY82: 2.2 | EZ82: 2.2 | FA82: 2.2 | FB82: 2.2 | FC82: 2.2 | FD82: 2.2
ER83: 1.9
ES84: 5 | ET84: 5 | EU84: 5 | EV84: 5 | EW84: 5 | EX84: 5 | EY84: 5 | EZ84: 5 | FA84: 5 | FB84: 5 | FC84: 5 | FD84: 5 | FE84: 5 | FF84: 5 | FG84: 5 | FH84: 5 | FI84: 5 | FJ84: 5 | FK84: 5 | FL84: 5 | FM84: 5 | FN84: 5 | FO84: 5 | FP84: -23
ES85: 0.213
ES86: 5.5 | ET86: 5.5 | EU86: 5.5 | EV86: 5.5 | EW86: 5.5 | EX86: 5.5 | EY86: 5.5 | EZ86: 5.5 | FA86: 5.5 | FB86: 5.5 | FC86: 5.5 | FD86: 5.5 | FE86: 5.5 | FF86: 5.5 | FG86: 5.5 | FH86: 5.5 | FI86: 5.5 | FJ86: 5.5 | FK86: 5.5 | FL86: 5.5 | FM86: 5.5 | FN86: 5.5 | FO86: 5.5 | FP86: 5.5 | FQ86: 5.5 | FR86: 5.5 | FS86: 5.5 | FT86: 5.5 | FU86: 5.5 | FV86: 5.5 | FW86: 5.5 | FX86: 5.5 | FY86: 5.5
ES87: 4.66
ES88: 10 | ET88: 10 | EU88: 10 | EV88: 10 | EW88: 10 | EX88: 10 | EY88: 10 | EZ88: 10 | FA88: 10 | FB88: 10 | FC88: 10 | FD88: 10
ES89: -20 | ET89: -20 | EU89: -20 | EV89: -15 | EW89: -15 | EX89: -15 | EY89: -8 | EZ89: -8 | FA89: -8 | FB89: -8 | FC89: -8 | FD89: -8 | FE89: -8 | FF89: 0
ES90: 18 | ET90: 18 | EU90: 18 | EV90: 18
ES91: 34.2
ES92: 16.1
ES93: -28 | ET93: -28 | EU93: -28 | EV93: -28 | EW93: -28
ET94: 1.5 | EU94: 1.5 | EV94: 1.5 | EW94: 1.5 | EX94: 1.5 | EY94: 1.5 | EZ94: 1.5 | FA94: 1.5 | FB94: 1.5 | FC94: 1.5 | FD94: 1.5 | FE94: 1.5 | FF94: 1.5 | FG94: 1.5 | FH94: 1.5 | FI94: 1.5 | FJ94: 1.5 | FK94: 1.5
ET95: 3.5 | EU95: 3.5 | EV95: 3.5 | EW95: 3.5 | EX95: 3.5 | EY95: 3.5 | EZ95: 3.5 | FA95: 3.5 | FB95: 3.5 | FC95: 3.5 | FD95: 3.5 | FE95: 3.5
EU96: 2.5 | EV96: 2.5 | EW96: 1.5 | EX96: 1.5 | EY96: 1.5 | EZ96: 1.5 | FA96: 1.5 | FB96: 1.5 | FC96: 1.5 | FD96: 1.5 | FE96: 1 | FF96: 1 | FG96: 1 | FH96: 1 | FI96: 1 | FJ96: 1 | FK96: 1 | FL96: 1 | FM96: 1 | FN96: 1 | FO96: 1 | FP96: 1 | FQ96: 1 | FR96: 1 | FS96: 1 | FT96: 1 | FU96: 1 | FV96: 1 | FW96: 1 | FX96: 1 | FY96: 1
EU97: 18 | EV97: 18 | EW97: 18
EV98: 1 | EW98: 1 | EX98: 1 | EY98: 1 | EZ98: 1 | FA98: 1 | FB98: 1 | FC98: 1 | FD98: 1 | FE98: 1 | FF98: 1 | FG98: 1 | FH98: 1 | FI98: 1 | FJ98: 1 | FK98: 1 | FL98: 1 | FM98: 1 | FN98: 1 | FO98: 1 | FP98: 1
EV99: 6.8 | EW99: 6.8 | EX99: 6.8 | EY99: 6.8 | EZ99: 0.6
EV100: 20
EW101: -2 | EX101: -2 | EY101: -2 | EZ101: -2 | FA101: -2 | FB101: -2 | FC101: -2 | FD101: -2 | FE101: -2 | FF101: -2 | FG101: -2 | FH101: -2 | FI101: -2 | FJ101: -2 | FK101: -2 | FL101: -2 | FM101: -2 | FN101: -2 | FO101: -2 | FP101: -2 | FQ101: -2 | FR101: -2 | FS101: -2 | FT101: -2 | FU101: -2 | FV101: -2 | FW101: -2 | FX101: -2 | FY101: -2
EW102: 5.7
EW103: 1 | EX103: 1 | EY103: 1 | EZ103: 1 | FA103: 1 | FB103: 1 | FC103: 1 | FD103: 1 | FE103: 1 | FF103: 1 | FG103: 1 | FH103: 1 | FI103: 1 | FJ103: 1 | FK103: 1 | FL103: 1 | FM103: 1 | FN103: 1 | FO103: 1 | FP103: 1 | FQ103: 1 | FR103: 1 | FS103: 1 | FT103: 1 | FU103: 1 | FV103: 1 | FW103: 1 | FX103: 1 | FY103: 1
...

Sheet Qarzdorlar 
H32: 56000000

Sheet панел
A1: № | B1: Куёш панел | E1: кв сумма
A2: 1 | B2: 5 | C2: кв | D2: 18000000 | E2: =D2/B2 -> 3600000
A3: 2 | B3: 10 | C3: кв | D3: 36000000 | E3: =D3/B3 -> 3600000
A4: 3 | B4: 15 | C4: кв | D4: 52000000 | E4: =D4/B4 -> 3466666.7
A5: 4 | B5: 20 | C5: кв | D5: 68000000 | E5: =D5/B5 -> 3400000 | F5: 3500000 | G5: =B5*F5 -> 70000000
A6: 5 | B6: 30 | C6: кв | D6: 100000000 | E6: =D6/B6 -> 3333333.3
A7: 6 | B7: 50 | C7: кв | D7: =B7*E7 -> 160000000 | E7: 3200000
A8: 7 | B8: 60 | C8: кв | D8: =B8*E8 -> 192000000 | E8: 3200000
A9: 8 | B9: 80 | C9: кв | D9: =B9*E9 -> 256000000 | E9: 3200000
A10: 9 | B10: 100 | C10: кв | D10: =B10*E10 -> 320000000 | E10: 3200000

Sheet Остатка
A2: № | B2: сана | C2: шартнома болган корхона | D2: Кредит олувчи | E2: махалла | F2: сумма
A3: 1 | B3: 45859 | C3: TECH NEST 777 MCHJ | D3: XO'JABAYEVA ZAMIRA SULTANBAYEVNA | E3: Илғор маҳалласи | F3: 23000000
A4: 2 | B4: 45859 | C4: YANGIARIQ ECO CHORVA FARMIX MCHJ | D4: ALLABERGANOVA ZOHIDA ADAMBOY QIZI | E4: Саҳоват МФЙ | F4: 21000000
A5: 3
A6: 4
A7: 5 | E7: .
B12: 22,07,2025
E13: кирим | G13: Расход | I13: Доллир
E14: 20000000 | G14: 625000 | I14: 3000 | J14: ушатдим
G15: 87000 | I15: 200 | J15: картадан накд
G16: 600000 | I16: 300 | J16: картадан накд
G17: 150000 | I17: 1000
E18: =SUM(E14:E17) -> 20000000 | G18: =SUM(G14:G17) -> 1462000 | I18: =I14-I15-I16-I17+200 -> 1700
F20: =E18-G18 -> 18538000
F21: 4000000
F22: 5500000
C23: накд | D23: 11000000 | F23: 14333000
C24: доллир | D24: =1700*12700 -> 21590000 | F24: =F20+F21-F22-F23 -> 2705000
D25: =SUM(D23:D24) -> 32590000
B28: 23,07,2025
E31: Кирим | F31: Кредит Чиким | G31: Кунлик Чиким | H31: Доллир
E32: 11000000 | F32: 1500 | G32: 250000 | H32: 1700
G33: 300000
G34: 2250000
G35: 1900000
U36: 339000
U37: 7280
U38: 17100
E41: =SUM(E32:E40) -> 11000000 | F41: =SUM(F32:F40) -> 1500 | G41: =SUM(G32:G40) -> 4700000 | H41: =SUM(H32:H38) -> 1700 | X41: 441240000
C44: 45861 | G44: 45862 | J44: 45863 | N44: 45864 | R44: 45866 | V44: 45867 | Y44: =+Y47-16710000 -> 379580000 | Z44: 45868 | AC44: 45869 | AF44: 45870
C45: Колдик | D45: Кирим | E45: Чиким | F45: Колдик | G45: Кирим | H45: Чиким | I45: Колдик | J45: Колдик | K45: Кирим | L45: Чиким | M45: Колдик | N45: Колдик | O45: Кирим | P45: Чиким | Q45: Колдик | R45: Колдик | S45: Кирим | T45: Чиким | U45: Колдик | V45: Колдик | W45: Кирим | X45: Чиким | Y45: Колдик | Z45: Кирим | AA45: Чиким | AB45: Колдик | AC45: Кирим | AD45: Чиким | AE45: Колдик | AF45: Кирим | AG45: Чиким | AH45: Колдик
B46: Пластик | C46: 2700000 | D46: 10000000 | E46: =11000000+300000 -> 11300000 | F46: =+C46+D46-E46 -> 1400000 | H46: 500000 | I46: =+F46+G46-H46 -> 900000 | J46: 900000 | K46: 3360000 | L46: =3360000+338000+200000 -> 3898000 | M46: =+J46+K46-L46 -> 362000 | N46: =+M46 -> 362000 | P46: =300000+37500 -> 337500 | Q46: =+N46+O46-P46 -> 24500 | R46: 24500 | S46: =8575000+1000000 -> 9575000 | T46: =4760000+500000 -> 5260000 | U46: =+Q46+S46-T46 -> 4339500 | V46: =U46 -> 4339500 | X46: =600000+300000 -> 900000 | Y46: =+V46+W46-X46 -> 3439500 | Z46: =5000000+5000000 -> 10000000 | AA46: =2280000+40000+9500000+337500 -> 12157500 | AB46: =+Y46+Z46-AA46 -> 1282000 | AC46: 125000 | AD46: =500000+144000 -> 644000 | AE46: =+AB46+AC46-AD46 -> 763000 | AF46: 3000000 | AG46: =500000+50000+30000 -> 580000 | AH46: =+AE46+AF46-AG46 -> 3183000
B47: Накд | C47: 11000000 | D47: =64000000+30000000 -> 94000000 | E47: =250000+2250000+1900000+19320000+10390000+29700000+35000+217000+29700000+10000000+100000 -> 103862000 | F47: =+C47+D47-E47 -> 1138000 | G47: =140000000+8000000+6000000+60000000 -> 214000000 | H47: =5000000+24000000+30690000+30690000+30360000+30360000+1400000+300000+20000000+1000000+8550000+25400000+5365000 -> 213115000 | I47: =+F47+G47-H47-138000 -> 1885000 | J47: 1885000 | K47: =198000000+1550000+1000000+1260000+77000000 -> 278810000 | L47: =19320000+30690000+27900000+24700000+600000+24300000+27000000+2200000+23410000+30950000+34950000+860000+540000+100000+32200000 -> 279720000 | M47: =+J47+K47-L47 -> 975000 | N47: =M47 -> 975000 | O47: =17000000+1500000+1270000+70000000 -> 89770000 | P47: =100000+100000+600000+100000+5000000+2300000+9500000+100000+100000+150000+1600000+70000000 -> 89650000 | Q47: =+N47+O47-P47 -> 1095000 | R47: 1095000 | S47: =60000000+100000000+8580000+250000 -> 168830000 | T47: =270000+80000+660000+5400000+60000000+45000000+1085000+22750000+100000+85000+8500000+4000000+22000000 -> 169930000 | U47: =+Q47+S47-T47 -> -5000 | V47: 0 | W47: =40000000+792990000+600000 -> 833590000 | X47: =30360000+174600000+30360000+22500000+91000000+39560000+5000000+9200000+13800000+20920000 -> 437300000 | Y47: =+V47+W47-X47 -> 396290000 | Z47: =50000000+521730000+2280000+40000 -> 574050000 | AA47: =500000+2000000+50000+3100000+5000000+2000000+5135000+5000000+5730000+1000000+2000000+7280000+17100000+92500000+22860000+7500000+9500000+46500000+30690000 -> 265445000 | AB47: =+Y47+Z47-AA47-605000000 -> 99895000 | AC47: =4450000+6500000+36000000 -> 46950000 | AD47: =5700000+144000+200000+2200000+2800000+200000+200000+47000000+15960000+13800000+9000000+21160000+17540000 -> 135904000 | AE47: =+AB47+AC47-AD47 -> 10941000 | AF47: =96000000+3300000+800000+369270000 -> 469370000 | AG47: =23140000+11500000+780000+22760000+17600000+2000000+100000+770000+270000+272600000 -> 351520000 | AH47: =AE47+AF47-AG47 -> 128791000
B48: Доллар | C48: 1700 | D48: 0 | E48: 1500 | F48: =+C48+D48-E48 -> 200 | I48: =+F48+G48-H48 -> 200 | J48: =I48 -> 200 | M48: =+J48+K48-L48 -> 200 | N48: =+M48 -> 200 | O48: 3000 | P48: =2200+100 -> 2300 | Q48: =+N48+O48-P48 -> 900 | R48: 900 | T48: 900 | U48: =+Q48+S48-T48 -> 0 | V48: 0 | W48: 300 | Y48: =+V48+W48-X48 -> 300 | AA48: 100 | AB48: =+Y48+Z48-AA48 -> 200 | AC48: 800 | AE48: =+AB48+AC48-AD48 -> 1000 | AH48: 1000
C49: =+C48*1262 -> 2145400 | E49: =+E48*12750 -> 19125000 | O49: =12660*O48 -> 37980000 | P49: =+P48*12680 -> 29164000 | T49: =+T48*12600 -> 11340000 | AA49: =255695000-AA47 -> -9750000 | AG49: =+AH47-AE47 -> 117850000
T50: 16740000 | AB50: =+AB47-710705 -> 99184295
E51: 250000 | T51: =+T50-T49 -> 5400000 | AD51: =26000000*88% -> 22880000 | AG51: =99000000+18850000 -> 117850000 | AH51: =+AH47-AE47 -> 117850000
E52: 2250000 | AG52: =+AG51-AH51 -> 0 | AH52: =+AH47-AH51 -> 10941000
E53: 1900000 | R53: Шит | S53: 270000 | AA53: =29040+2200 -> 31240
E54: 19320000 | R54: газ | S54: 80000 | AA54: =500*12550+8565000 -> 14840000 | AB54: =2700000+AA54 -> 17540000
E55: 10390000 | R55: Пахтаобод хё | S55: 660000 | AA55: =21160000 -> 21160000 | AB55: 29040000
E56: 29700000 | R56: Шохрух | S56: 100000 | AA56: =+AA54+AA55 -> 36000000 | AB56: =+AB55-AB54 -> 11500000
E57: 35000 | R57: Элдор | S57: 85000
E58: 217000 | R58: Фура | S58: 8500000
E59: 29700000 | S59: 5400000
E60: 10000000 | S60: 45000000
E61: 100000 | S61: 60000000
E62: =SUM(E51:E61) -> 103862000 | S62: 22750000
S63: 4000000 | AA63: 1200000
S64: 22000000 | AA64: =-AA63400000 -> #NAME?
S65: 1085000
L67: 41455000 | N67: 300000000 | S67: =SUM(S53:S65) -> 169930000
L68: 70000000 | N68: =N67*98.5% -> 295500000 | S68: =+S67-T47 -> 0
L69: 60000000
L70: 40000000
L71: =SUM(L67:L70) -> 211455000 | N71: =N68-L71 -> 84045000

Sheet Лист7
A3: AMINOV MUXAMMAD QURAMBOY O‘G‘LI
E6: 45868 | H6: 45869 | K6: 45870 | N6: 45871 | Q6: 45873 | T6: 45874 | W6: 45875 | Z6: 45876 | AC6: 45877 | AF6: 45878
A7: Колдик | B7: Кирим | C7: Чиким | D7: Колдик | E7: Кирим | F7: Чиким | G7: Колдик | H7: Кирим | I7: Чиким | J7: Колдик | K7: Кирим | L7: Чиким | M7: Колдик | N7: Кирим | O7: Чиким | P7: Колдик | Q7: Кирим | R7: Чиким | S7: Колдик | T7: Кирим | U7: Чиким | V7: Колдик | W7: Кирим | X7: Чиким | Y7: Колдик | Z7: Кирим | AA7: Чиким | AB7: Колдик | AC7: Кирим | AD7: Чиким | AE7: Колдик | AF7: Кирим | AG7: Чиким | AH7: Колдик
A8: 4339500 | C8: =600000+300000 -> 900000 | D8: =+A8+B8-C8 -> 3439500 | E8: =5000000+5000000 -> 10000000 | F8: =2280000+40000+9500000+337500 -> 12157500 | G8: =+D8+E8-F8 -> 1282000 | H8: 125000 | I8: =500000+144000 -> 644000 | J8: =+G8+H8-I8 -> 763000 | K8: 3000000 | L8: =500000+50000+30000 -> 580000 | M8: =+J8+K8-L8 -> 3183000 | O8: 125000 | P8: =+M8+N8-O8 -> 3058000 | Q8: 1000000 | S8: =+P8+Q8-R8 -> 4058000 | T8: 0 | U8: 750000 | V8: =+S8+T8-U8 -> 3308000 | X8: =41200+370000 -> 411200 | Y8: =+V8+W8-X8 -> 2896800 | Z8: 1000000 | AA8: =300000+500000 -> 800000 | AB8: =+Y8+Z8-AA8 -> 3096800 | AC8: 1500000 | AD8: 0 | AE8: =AB8+AC8-AD8 -> 4596800 | AF8: 0 | AG8: 0 | AH8: =AE8+AF8-AG8 -> 4596800
A9: 0 | B9: =40000000+792990000+600000 -> 833590000 | C9: =30360000+174600000+30360000+23000000+10000000+91000000+10000000+23000000+5000000+9200000+13800000+20920000 -> 441240000 | D9: =+A9+B9-C9 -> 392350000 | E9: =50000000+2280000+40000+521730000 -> 574050000 | F9: =7280000+17100000+92500000+22860000+7500000+46500000+30690000+31515000 -> 255945000 | G9: =+D9+E9-F9-605000000 -> 105455000 | H9: =4450000+6500000+36000000 -> 46950000 | I9: =47000000+15960000+13800000+17540000+21160000+11444000+9000000 -> 135904000 | J9: =+G9+H9-I9 -> 16501000 | K9: =3300000+800000+96000000+369270000 -> 469370000 | L9: =17600000+22760000+23140000+780000+11500000+770000+272600000+2370000 -> 351520000 | M9: =J9+K9-L9 -> 134351000 | N9: 8970000 | O9: =300000+100000+300000+25320000+500000 -> 26520000 | P9: =M9+N9-O9 -> 116801000 | R9: =3000000+100000+2000000+600000+6500000+15000000+1000000+21160000+28500000+1250000+1000000+200000 -> 80310000 | S9: =P9+Q9-R9 -> 36491000 | T9: 154440000 | U9: =240000+350000+18600000+13300000+30690000+30690000+30360000+200000+1000000 -> 125430000 | V9: =S9+T9-U9 -> 65501000 | W9: =1000000+736362000 -> 737362000 | X9: =100000+536000+180000+800000+13500000+30360000+2850000 -> 48326000 | Y9: =V9+W9-X9 -> 754537000 | AA9: =9200000+22080000+13950000+4750000+50000+340000+500000000+1000000+5660000+200000 -> 557230000 | AB9: =Y9+Z9-AA9 -> 197307000 | AC9: =6500000+2500000 -> 9000000 | AD9: =250000+30360000+27000000+29700000+29700000+1920000+250000+100000 -> 119280000 | AE9: =AB9+AC9-AD9 -> 87027000 | AF9: 0 | AG9: =33690000+2520000+300000 -> 36510000 | AH9: =AE9+AF9-AG9 -> 50517000
A10: 0 | B10: 300 | D10: =+A10+B10-C10 -> 300 | F10: 100 | G10: =+D10+E10-F10 -> 200 | H10: 800 | J10: =+G10+H10-I10 -> 1000 | M10: 1000 | P10: 1000 | Q10: =1000+100 -> 1100 | S10: =P10+Q10-R10 -> 2100 | T10: 0 | U10: 800 | V10: =S10+T10-U10 -> 1300 | W10: 100 | X10: 100 | Y10: =V10+W10-X10 -> 1300 | AB10: =Y10+Z10-AA10 -> 1300 | AE10: =AB10+AC10-AD10 -> 1300 | AF10: 200 | AH10: =AE10+AF10-AG10 -> 1500
S11: =+S9-7001000 -> 29490000 | AB11: =+AB9-7001000 -> 190306000
B12: =+Остатка!W47 -> 833590000 | C12: =+Остатка!X47 -> 437300000 | D12: =+Остатка!Y47 -> 396290000 | E12: =+Остатка!Z47 -> 574050000 | F12: =+Остатка!AA47 -> 265445000 | G12: =+Остатка!AB47 -> 99895000 | H12: =+Остатка!AC47 -> 46950000 | I12: =+Остатка!AD47 -> 135904000 | ... M12: =+Остатка!AH47 -> 128791000 | P12: =+P9-74000000-8250000 -> 34551000 | S12: =+S9-7001000 -> 29490000 | V12: 7001000 | Y12: =+Y9-7001000 -> 747536000 | AE12: =+AE9 -> 87027000 | AH12: 7001000
C13: =+C12-C9 -> -3940000 | D13: 375640000 | F13: =+F12-F9 -> 9500000 | G13: =+G12-G9 -> -5560000 | I13: =+I9-I12 -> 0 | P13: 18050000 | S13: =19500000+690000 -> 20190000 | Y13: =+Y15-Y12 -> -745804000 | AB13: =+AB11-AB14 -> 9524000 | AE13: =+AE12-65800000+250000+100000 -> 21577000 | AH13: =+AH9-AH12 -> 43516000
D14: =+D12-D13 -> 20650000 | F14: =500000+2000000+50000+3100000+5000000+2000000+5135000+5000000+5730000+1000000+2000000 -> 31515000 | I14: =5700000+144000+200000+2200000+2800000+200000+200000 -> 11444000 | L14: =2000000+100000+270000 -> 2370000 | P14: =+P12-P13 -> 16501000 | S14: =+S12-S13 -> 9300000 | V14: =V9 -> 65501000 | AB14: =145000000+25000000+10500000+282000 -> 180782000 | AE14: =+AE13-7001000 -> 14576000
D15: =+D14-7000000 -> 13650000 | N15: =6900000+1250000+100000 -> 8250000 | P15: =+P9-P14 -> 100300000 | V15: =V14-V12 -> 58500000 | Y15: 1732000 | AB15: =+AB9-AB14 -> 16525000 | AE15: =+AE12-7001000 -> 80026000 | AH15: =34260000-34316000 -> -56000
N16: =+N15-8970000 -> -720000 | P16: =74000000+8250000+18550000 -> 100800000 | AB16: =+AB15-7001000 -> 9524000 | AE16: =4260000+30000000 -> 34260000
AA17: =9200+22080+13950+4750+390+500000 -> 550370 | AE17: =+AE16+33690000 -> 67950000
AE18: =+AE9-AE17 -> 19077000
AE19: =+AE18-1255000-1255000 -> 16567000
T22: 3300000
T23: =V8-T22 -> 8000
X24: =SUM(X25:X28) -> 1682000 | Y24: =Y9-7001000 -> 747536000
X25: 160000
X26: 450000
X27: 1000000
X28: 72000

Sheet Лист2
G2: Накд | I2: ПК | K2: Доллар
E3: Тушган сана | F3: Берилган сана | G3: Кирим | H3: Чиким | I3: Кирим | J3: Чиким | K3: Кирим | L3: Чиким
A4: 1 | B4: Богот Агро касаба уюшма | C4: 10000000 | D4: 9400000 | E4: 45860 | F4: 45860 | H4: 9400000 | I4: 20000000 | K4: 3000
A5: =+A4+1 -> 2 | B5: ЯТТ Отабоева Зилола | C5: 25000000 | D5: =2520000+19145000+1085000 -> 22750000 | E5: 45860 | L5: 200
A6: =+A5+1 -> 3 | B6: Оллаберганова Зохида | C6: 21000000 | D6: 19320000 | E6: 45860
A7: =+A6+1 -> 4 | B7: Хажиева Замира | C7: 23000000 | D7: 21390000 | E7: 45860
A8: =+A7+1 -> 5 | H8: 500000
A9: =+A8+1 -> 6 | H9: 87000
A10: =+A9+1 -> 7 | H10: 900000 | L10: 1000
A11: =+A10+1 -> 8 | J11: 300000
A12: =+A11+1 -> 9 | J12: 300000
A13: =+A12+1 -> 10 | H13: =SUM(H4:H12) -> 10887000 | I13: =SUM(I4:I12) -> 20000000 | J13: =SUM(J4:J12) -> 600000 | K13: =SUM(K4:K12) -> 3000 | L13: =SUM(L4:L12) -> 1200
A14: =+A13+1 -> 11 | I14: =+I13-H13 -> 9113000
A15: =+A14+1 -> 12
A16: =+A15+1 -> 13
A17: =+A16+1 -> 14
A18: =+A17+1 -> 15
A19: =+A18+1 -> 16
A20: =+A19+1 -> 17 | G20: 11000000 | I20: 2700000 | K20: 1700
A21: =+A20+1 -> 18 | E21: Тушган сана | F21: Берилган сана | G21: Кирим | H21: Чиким | I21: Кирим | J21: Чиким | K21: Кирим | L21: Чиким
A22: 1 | B22: Юсупов Маркс | C22: 33000000 | D22: 29700000 | E22: 45861 | G22: 30000000 | H22: 29700000 | I22: 10000000 | J22: 11000000
A23: =+A22+1 -> 2 | B23: Норбоев Комилжон | C23: 33000000 | D23: 30690000 | E23: 45861 | G23: 64025000 | L23: 19145000
A24: =+A23+1 -> 3 | B24: Камолов Мансур | C24: 33000000 | D24: 30690000 | E24: 45861 | G24: 11000000 | H24: 19320000
A25: =+A24+1 -> 4 | B25: Авезова Гулмира | C25: 21000000 | D25: 19320000 | E25: 45861 | H25: 21390000
A26: =+A25+1 -> 5 | B26: Машарипова Маргуба | C26: 6310000 | D26: 5665000 | E26: 45861 | H26: 29700000
A27: =+A26+1 -> 6 | B27: Худайберганов Алишер | C27: 33000000 | D27: 30360000 | E27: 45861
A28: =+A27+1 -> 7 | B28: Каландарова машхура | C28: 33000000 | D28: 30360000 | E28: 45861
A29: =+A28+1 -> 8 | B29: Хужаков Ахмед | C29: 18000000 | E29: 45861
A30: =+A29+1 -> 9 | B30: Курязов Бахтиёр | C30: 33000000 | D30: 29700000 | E30: 45861
A31: =+A30+1 -> 10 | B31: Янгиарик Огахий Сервис | C31: 9000000 | D31: 8550000 | E31: 45861
A32: =+A31+1 -> 11 | H32: 350000 | J32: 300000
A33: =+A32+1 -> 12 | H33: 2250000
H34: 1900000
H35: 35000
H36: 10000000
G37: =SUM(G22:G36) -> 105025000 | H37: =SUM(H22:H36) -> 114645000 | I37: =+G20+G37-H37 -> 1380000 | J37: =+I20+I22-J22-J32 -> 1400000
B38: 45862 | E38: Тушган сана | F38: Берилган сана | G38: Кирим | H38: Чиким | I38: Кирим | J38: Чиким | K38: Кирим | L38: Чиким
A39: 1 | B39: Авезов Шерзод | C39: 33000000 | D39: 30690000 | F39: Илхом | G39: 140000000 | H39: 30690000
A40: =+A39+1 -> 2 | B40: Гулмирзаева марифат | C40: 30000000 | D40: 27900000 | F40: фарогат | G40: 14000000 | H40: 30690000
A41: =+A40+1 -> 3 | B41: омонова Хуршида | C41: 33000000 | D41: =5000000+24700000 -> 29700000 | F41: сув | G41: 60000000 | H41: 5665000
A42: =+A41+1 -> 4 | B42: машарипова Райхона | C42: 27000000 | D42: 24300000 | H42: 30360000
A43: =+A42+1 -> 5 | B43: машарипова Фарида | C43: 30000000 | D43: =24000000+600000-6000000+9000000 -> 27600000 | H43: 30360000
A44: =+A43+1 -> 6 | B44: Матякубова Рано | C44: 33000000 | D44: =27000000+3360000 -> 30360000 | H44: 8550000
A45: =+A44+1 -> 7 | B45: Сотимова Замира | C45: 30000000 | D45: =25400000+2200000 -> 27600000 | H45: 5000000
A46: =+A45+1 -> 8 | B46: Убиниязова Венера | C46: 33000000 | D46: =23410000+7280000 -> 30690000 | H46: 24000000
A47: =+A46+1 -> 9 | B47: Давлетова Замира | C47: 50000000 | D47: 45000000 | H47: 25400000
A48: =+A47+1 -> 10 | B48: Раис бобо чорваси | C48: 35000000 | D48: 32200000
J50: 500000
H51: 1400000
H52: 100000
H53: 100000
H54: 100000
H55: 1000000
H56: 20000000
G57: =SUM(G39:G56) -> 214000000 | H57: =SUM(H39:H56) -> 213415000 | I57: =+I37+G57-H57 -> 1965000 | J57: =+J37-J50 -> 900000
B58: 45863 | E58: Тушган сана | F58: Берилган сана | G58: Кирим | H58: Чиким | I58: Кирим | J58: Чиким | K58: Кирим | L58: Чиким
A59: 1 | B59: Курязов Рустам | C59: 33000000 | D59: 30360000 | F59: Жавлон кассоб | G59: 1550000 | H59: 19320000 | I59: 3360000
A60: =+A59+1 -> 2 | B60: Бест обод томорка мчж | C60: 38000000 | D60: 34960000 | F60: Худайназаров Машарип | G60: 1000000 | H60: 30690000
A61: =+A60+1 -> 3 | B61: Артикова Юлдуз | C61: 33000000 | D61: 30360000 | F61: Рузметов Донёр | G61: 1260000 | H61: 27900000
A62: =+A61+1 -> 4 | B62: Холбекова Муборак | C62: 33000000 | D62: 30360000 | F62: Илхом | G62: 198000000 | H62: 24700000
A63: =+A62+1 -> 5 | B63: Нобоева Максуда | C63: 33000000 | D63: 30360000 | F63: Сувчи | G63: 77000000 | H63: 24300000
H64: 600000
H65: 27000000
H66: 2200000
H67: 23410000
H68: 32200000
H69: 30360000
H70: 34960000
H73: 200000
H74: 100000
H75: 510000
H76: 50000
H77: 860000 | I77: 3360000
H78: 540000 | I78: 338000
I79: 200000
G80: =SUM(G59:G79) -> 278810000 | H80: =SUM(H59:H79) -> 279900000 | I80: =+I57+G80-H80 -> 875000 | J80: =+J57+I59-I77-I78-I79 -> 362000
I81: =+I80-975000 -> -100000
C82: 45864 | E82: Тушган сана | F82: Берилган сана | G82: Кирим | H82: Чиким | I82: Кирим | J82: Чиким | K82: Кирим | L82: Чиким
A83: 1 | B83: Жетоур логистик | C83: 10000000 | D83: 9500000 | F83: Абдуллаева Фарогат | G83: 17000000 | H83: 9500000 | J83: 300000
A84: 2 | B84: Маликабону Зулайхо | C84: 100000000 | D84: =70000000+22000000 -> 92000000 | F84: Лутфилла | H84: 70000000 | J84: 37500 | K84: 3000 | L84: 2200
F85: Гулзода Балик | G85: 1500000 | H85: 2300000
F86: Шакар | G86: 70000000 | L86: 100
F87: доллар | G87: 1270000
H93: 100000
H94: 100000
H95: 600000
H96: 100000
H97: 5000000
H98: 100000
H99: 100000
H100: 1600000
G102: =SUM(G83:G101) -> 89770000 | H102: =SUM(H83:H101) -> 89500000 | I102: =+I80+G102-H102 -> 1145000 | J102: =+J80-J83-J84 -> 24500 | K102: 900
C104: 45866 | E104: Тушган сана | F104: Берилган сана | G104: Кирим | H104: Чиким | I104: Кирим | J104: Чиким | K104: Кирим | L104: Чиким
A105: 1 | B105: Узб черноблчи | C105: 18000000 | D105: 16740000 | F105: Илхом | G105: 100000000 | H105: 5400000 | I105: 4000000 | L105: 900
A106: =+A105+1 -> 2 | B106: Ширин конгрот | C106: 255000000 | D106: =60000000+174600000 -> 234600000 | F106: Сув | G106: 60000000 | H106: 60000000
A107: =+A106+1 -> 3 | B107: Жумабоев Вали | C107: 25000000 | D107: 22500000 | F107: Озод | G107: 9580000 | H107: 22750000
A108: =+A107+1 -> 4 | F108: Хумоюн | G108: 250000 | H108: 22000000
A109: =+A108+1 -> 5 | H109: 45000000
A110: =+A109+1 -> 6 | H110: 1085000
A111: =+A110+1 -> 7
...

Sheet Касса
E3: Беко прихот | F3: 440000000 | G3: 45892
J4: Кредит расход | L4: Кунлик чиким | N4: Кирим
J5: 17745000 | L5: 55000 | N5: 3800000
J6: 94000000 | L6: 2900000 | N6: 39700000
J7: 13800000 | L7: 100000
J8: 19000000 | L8: 5000000
J9: 83500000
J10: 11400000
J11: 93400000
J12: =SUM(J5:J11) -> 332845000 | L12: =SUM(L5:L8) -> 8055000 | N12: =SUM(N5:N6) -> 43500000
I13: Касса | J13: =F3-J12-L12+N12 -> 142600000
G14: 45891
J15: Кредит расход | L15: Кунлик чиким | N15: Кирим | P15: доллр
K16: Каха бро | L16: 200000 | M16: Олим Доктир панел | N16: 18000000 | P16: 1700
K17: Шох запчаст | L17: 3600000
K18: Фура | L18: 8700000
K19: Каттий фирма | L19: 2500000
K20: Офис свет | L20: 1000000
K21: Элдор газ | L21: 100000
L23: =SUM(L16:L22) -> 16100000 | N23: =SUM(N16:N22) -> 18000000
I24: Касса | J24: =J13-L23+N23 -> 144500000
G25: 45892
J26: Кредит расход | L26: Кунлик чиким | N26: Кирим | P26: доллр $
G27: Ят Мадримов Хамза | J27: 31850000 | K27: Лабо гас | L27: 100000 | M27: Шокир ога сув | N27: 100000000 | O27: Шахзод | P27: 100
G28: Алламова Шахло Бехзод гурлан | J28: 30690000 | K28: Шокир огам | L28: 1500000
K29: Жумми ана кредит | L29: 800000
K30: Сардор Ипотека | L30: 1020000
K31: Кахрамон ога | L31: 700000
K32: Шокир огам | L32: 220000
K33: Элдор | L33: 1000000
J34: =SUM(J27:J34) -> 62540000 | L34: =SUM(L27:L33) -> 5340000 | N34: =SUM(N27:N33) -> 100000000 | P34: =SUM(P27:P32) -> 100
G36: Жами расход | J36: =62540000+5340000 -> 67880000
I37: Касса | J37: =J24+N27-J36 -> 176620000
I38: $ | J38: 1600
G39: 45893
J40: Кредит расход | L40: Кунлик чиким | N40: Кирим | P40: доллр $
K41: Шокир ога | L41: 600000 | M41: Беко | N41: $4000 | P41: =1787+4000 -> 5787
K42: Хоким Бува | L42: 300000 | M42: Хумоюн | N42: 13150000
L47: =SUM(L41:L46) -> 900000 | N47: =SUM(N42:N46) -> 13150000 | P47: =SUM(P41:P46) -> 5787
G52: Жами расход | J52: =L47 -> 900000
I53: Касса | J53: =J37-J52+N47 -> 188870000
I54: $ | J54: 5787
N56: 5700
N57: 87
G60: 45894
J62: Кредит расход | L62: Кунлик чиким | N62: Кирим | P62: доллр $
J63: 9200000 | L63: 250000 | M63: Кутлимуратов фарход | N63: 11000000 | P63: 5787
J64: 3800000 | L64: 300000 | M64: Шокир ога сув | N64: =53450000-4940000 -> 48510000 | P64: 400 | S64: 2.3120001e+19
J65: 29700000 | L65: 100000 | M65: Xumoyun | N65: 5000000 | P65: 1100
L66: 100000
L67: 250000
L68: 250000
J70: =SUM(J63:J69) -> 42700000 | L70: =SUM(L63:L69) -> 1250000 | N70: =SUM(N63:N69) -> 64510000 | P70: =+P63+P64+P65 -> 7287
D74: 4000000
D75: =D74*0.95 -> 3800000 | G75: Жами расход | J75: =J70+L70 -> 43950000
I76: Касса | J76: =J53+N70-J75 -> 209430000 | N76: =+J53+N70-J70-L70 -> 209430000
I77: $ | J77: =+P70 -> 7287
F78: 209370000
F80: =F78-J76 -> -60000
G83: 45895
J85: Кредит расход | L85: Кунлик чиким | N85: Кирим накд | P85: доллр $
G86: Абдуллаева Гулноза | J86: 18400000 | K86: Музаффар ога Зайниддинов | L86: 6600000 | M86: Шох Сув | N86: 40000000 | P86: =J77 -> 7287
G87: Ислаиов Анварбек | J87: 29700000 | K87: Кахрамон ога | L87: 150000 | M87: Панел | N87: 36000000 | O87: Шох сув | P87: 1650
G88: Бахт капитал | J88: 9200000 | K88: Азиз Х.Й | L88: 1020000 | M88: Сув | N88: =80000000-720*12350 -> 71108000 | O88: сув | P88: 720
G89: Олимбоев Полвон | J89: 30300000 | K89: Шокир ога | L89: 150000
G90: Ибодуллаев Одилбек | J90: 21390000
G91: Каха бро барган | J91: 139500000
J93: =SUM(J86:J92) -> 248490000 | L93: =SUM(L86:L92) -> 7920000 | N93: =SUM(N86:N92) -> 147108000 | P93: =SUM(P86:P92) -> 9657
G98: Жами расход | J98: =J93+L93 -> 256410000
G99: Касса | J99: =J76+N93-J98 -> 100128000
E100: 99747000 | G100: $ | J100: =P93 -> 9657
E101: =J99-E100 -> 381000
G107: 45896
E108: 484000000 | J108: Кредит расход | L108: Кунлик чиким | N108: Кирим накд | P108: доллр $
I109: Фозил агро | J109: 91000000 | K109: Лутфулла уста | L109: 2200000 | N109: 4500000
I110: Фозил агро | J110: 91000000 | K110: Шркир ога | L110: 12000000 | N110: 43000000
I111: хуршида | J111: 19000000 | K111: Элдор | L111: 200000 | M111: сув 29,08,25 | N111: 36000000
J112: 46500000 | K112: чиким | L112: 900000
J113: 64000000
J114: 29700000
J115: =SUM(J109:J114) -> 341200000 | L115: =SUM(L109:L113) -> 15300000 | N115: =SUM(N109:N113) -> 83500000
G120: Жами расход | J120: =J115+L115 -> 356500000
G121: Касса | J121: =E108+N115-J120 -> 211000000
G122: $ | J122: 1500
E134: 150000000 | G134: 45909
J135: Кредит расход | L135: Кунлик чиким | N135: Кирим накд | P135: доллр $
I136: Анвар налог | J136: =33000000*0.93 -> 30690000 | K136: Шохрух газа | L136: 100000 | N136: 8000000
I137: Гулсара Умирбек МЧЖ | J137: =100000000*0.91 -> 91000000 | K137: Свнвт ога | L137: 16000000
I138: Матязова Ирода калажиккала | J138: 12050000 | K138: Шокир ога | L138: 1300000
J142: =SUM(J136:J141) -> 133740000 | L142: =SUM(L136:L140) -> 17400000 | N142: =SUM(N136:N140) -> 8000000
G145: Жами расход | J145: =J142+L142 -> 151140000
G146: Касса | J146: =E134-J145+N142 -> 6860000
G147: $
O152: Карта ПК
G153: 45911 | O153: чиким | Q153: кирим
J154: Кредит расход | L154: Кунлик чиким | N154: Кирим накд
G155: Бехзод гурлан П.К барилди | I155: NISHONOV NURBEK XOLBOY Гурлан | J155: 4650000 | K155: Хасанбой Хива | L155: 22500000 | M155: Бехзод налог | N155: 3500000 | O155: Нахтланди | P155: 4200000 | Q155: Мот карз | R155: 17980000
K156: Лутфулла уста | L156: 2000000 | M156: Халк Банк | N156: 4200000 | O156: кредит расход | P156: 4650000 | Q156: Бехзод налог | R156: 5000000
K157: Газа | L157: 100000 | M157: Шокир ога шакар | N157: 45200000 | Q157: Ойбек йол | R157: 1700000
K158: Гаи | L158: 1000000 | M158: картадан накдланди | N158: 4200000 | Q158: Остатка 10.09.25 | R158: 605000
...

Sheet Лист8
A6: 46151 | C6: Кредит расход | E6: Кунлик чиким | G6: Кирим накд | I6: кирим П.К | K6: чиким П.К | M6: Доллир кирим | O6: Доллир чиким
C7: Ramazvon Avezov | D7: 8000000 | E7: Ramzon Mayda | F7: 300000 | G7: 16,04,2026 Lutfulla olib ketdi | H7: 4000000 | N7: 1400
C8: Ollamov Anvar | D8: 59840000 | E8: 10 kw 39 niki | F8: 1600000 | G8: 10 Berz subsidiya | H8: 0 | I8: 10 Berz subsidiya | J8: 39000000 | M8: Olma opa | N8: 500
C9: Raxmonov Xamro | D9: 39920000 | E9: Shafyor | F9: 1570000 | G9: Panel 3 dona | H9: =3*1200000 -> 3600000 | M9: Bunyod | N9: 1500
C10: Ilyos doyim | D10: 125000000 | E10: Shamiyev Orif | F10: 1300000 | G10: Panel 18 dona | H10: 20000000 | O10: Inventor | P10: 1900
C11: dollar 8600 | D11: =8600*12100 -> 104060000 | E11: Furaga | F11: 2000000 | G11: Shamiyev Orif | H11: 141000000
E12: SHOMIRZAYEV SHERALI | F12: 1600000 | G12: SHOMIRZAYEV SHERALI QODIROVICH | H12: 77000000 | I12: SHOMIRZAYEV SHERALI QODIROVICH | J12: 50000000
E13: Ergashov Toxir | F13: 400000 | G13: Ergashov Toxir | H13: 24400000 | I13: Ergashov Toxir | J13: 3600000
E14: HOLIQOVA MUXABBAT XAMROYEVNA | F14: 200000 | G14: HOLIQOVA MUXABBAT XAMROYEVNA | H14: 34000000
E15: Yakkabog` Doyim topgan odam | F15: 7600000 | G15: Yakkabog` Doyim topgan odam | H15: 100000000
E16: Yakkabog` Doyim topgan odam | F16: 2000000
C17: Ilyos doyim 1000 dollar | D17: 121000000 | E17: MAMATKOSIMOV UMIDJON XASANJONOVICH | F17: 7000000 | G17: MAMATKOSIMOV UMIDJON XASANJONOVICH | H17: =10300*12100 -> 124630000
C18: Buxoro Romiton 50 kw | D18: =10000*12000 -> 120000000 | E18: SATTAROV RAVSHAN ABDAZIMOVICH | F18: =4400000+1000000 -> 5400000 | G18: SATTAROV RAVSHAN ABDAZIMOVICH | H18: =87000000-8080000-9320000-2400000 -> 67200000
C19: Panel arendada | D19: 12000000 | E19: furaga | F19: 1000000 | G19: OCHILOV SHERZOD SHERALIYEVICH | H19: 0
C20: Behzodga berildi | D20: =3000*12000 -> 36000000 | E20: OCHILOV SHERZOD SHERALIYEVICH | F20: 4400000 | G20: Buxoro Romiton 50 kw | H20: =10000*12000 -> 120000000
E21: KAMALOV MUHAMMADBEK ILHOM-O‘G‘LI | F21: 2300000 | G21: Panel arendada | H21: 12000000
E22: 47 14 mayda | F22: 1000000
E23: Buxoro Romiton 50 kw | F23: 11000000
D26: =SUM(D7:D25) -> 625820000 | F26: =SUM(F7:F25) -> 50670000 | H26: =SUM(H7:H25) -> 727830000 | J26: =SUM(J7:J14) -> 92600000 | L26: =SUM(L7:L25) -> 0 | N26: =SUM(N7:N25) -> 3400 | P26: =SUM(P7:P25) -> 1900
G32: Утди | I32: Пк | J32: =J26-L26 -> 92600000 | M32: Дол | N32: =N26-P26 -> 1500
A33: Жами расход | D33: =D26+F26 -> 676490000 | G33: галди | I33: Оманат
A34: Касса | D34: =H26-D33 -> 51340000
A35: $ | D35: =+N32 -> 1500
A36: Plastik | D36: =+J32 -> 92600000
E41: lutfulla usta | F41: 15500000
E42: ustalarga | F42: 6000000
F43: =1700000+1200000 -> 2900000
F44: 2200000
F45: 2700000

Sheet Смарт
A1: № | B1: Клиент | C1: Махалла | D1: Жшшр | E1: Парол | F1: Кредит Ш | G1: сумма | H1: Максади | I1: Холати
A2: 1 | B2: ABDIRIMOV BAXROM RAJABOVICH | D2: 31008793110012 | E2: LUxhe7G527 | F2: 1 | G2: 33 | H2: Чорва | I2: тайор
A3: 2 | B3: BEKNAZAROV UMIDJON ANVARBEK O‘G‘LI | C3: Тупчи | D3: 53009047100018 | E3: yk10Z5zCW3 | G3: 22 | H3: Мот | I3: Банк отказ
A4: 3 | E4: B92zB5Hec5
A5: 4 | B5: ODAMOVA MUXABBAT EGAMOVNA | D5: 42708683180010 | E5: 72XTr3Ls5o
A6: 5
A7: 6
A8: 7
A9: 8
A10: 9
A11: 10
A12: 11
A13: 12
A14: 13
A15: 14
A16: 15
A17: 16
... A24: 23

Sheet Лист4
A1: № | B1: Клиент | C1: Махалла | D1: Жшшр | E1: Парол | F1: Кредит Ш | G1: сумма | H1: Максади | I1: Холати
A2: 1 | B2: SOBIROV ELDOR ERKINBOYEVICH | C2: Абу райхон беруний | D2: 30901863070025 | E2: yKT257hbG4 | H2: Контейнер | I2: Ариза юборилмаган | J2: 971136688
A3: 2
A4: 3
A5: 4
A6: 5
A7: 6
A8: 7
A9: 8
A10: 9
A11: 10
A12: 11
A13: 12
A14: 13
... A24: 23

Sheet Лист5
A1: №
B2: 30509843330071 | C2: XODJAMURATOV BAXROM TURAMURATOVICH
B3: 42707883330023 | C3: KUCHKAROVA NAZAKAT ISMAILOVNA | D3: AD4596557ad
B4: 31010827230014 | D4: AE1711599ae
B5: 31708853330102 | C5: XUDAYAROV RASHID YERIMBATOVICH | E5: отказ солик сервис
B6: 60704037230044
B7: 31001823330033
B8: 31001823330033
B9: 31708853330102
B10: 50601027230019
B11: 32607953330025
B12: 50601027230019
B13: 41111883330047
B14: 52012017230012
B15: 42401997230021

Sheet Rasulbek Xisob kitob 
B3: O`tkazilgan Summa | C3: Qo`lga Tegadigani | D3: Olindi | E3: Qoldiq
C4: 10000000
C5: =25000000*0.98 -> 24500000
B6: 54600000 | C6: =+B6*0.99 -> 54054000
B7: 387000000 | C7: =+B7*0.99 -> 383130000
B8: 67900000 | C8: =+B8*0.99 -> 67221000
B9: 89090000 | C9: =+B9*0.99 -> 88199100
B10: 600700000 | C10: =+B10*0.99 -> 594693000
B11: 867200000 | C11: =+B11*0.99 -> 858528000
B12: 94800000 | C12: =+B12*0.99 -> 93852000
B13: 144700000 | C13: =+B13*0.99 -> 143253000
B14: 667800000 | C14: =+B14*0.99 -> 661122000
B15: 148500000 | C15: =+B15*0.99 -> 147015000
A16: 18,03,2026 | D16: 865000000
A17: 21,03,2026 | D17: 700000000
A18: 24,03,2026 | B18: 301000000 | C18: =+B18*0.99 -> 297990000
B19: 1750000000 | C19: =+B19*0.99 -> 1732500000
B20: 257400000 | C20: =+B20*0.99 -> 254826000
B21: 297400000 | C21: =+B21*0.99 -> 294426000
B22: 63300000 | C22: =+B22*0.99 -> 62667000
B23: 51700000 | C23: =+B23*0.99 -> 51183000
A24: 25,03,2026 | D24: 500000000
B25: 49900000 | C25: =+B25*0.99 -> 49401000
B26: 45700000 | C26: =+B26*0.99 -> 45243000
B27: 257400000 | C27: =+B27*0.99 -> 254826000
B28: 282300000 | C28: =+B28*0.99 -> 279477000
B29: 50000000 | C29: =+B29*0.99 -> 49500000
A30: 26,03,2026 | C30: =+B30*0.99 -> 0 | D30: 400000000
B31: 50000000 | C31: =+B31*0.99 -> 49500000
B32: 150000000 | C32: =+B32*0.99 -> 148500000
B33: 100000000 | C33: =+B33*0.99 -> 99000000
A34: 27,03,2026 | C34: =+B34*0.99 -> 0 | D34: 300000000
B35: 91250000 | C35: =+B35*0.99 -> 90337500
B36: 46000000 | C36: =+B36*0.99 -> 45540000
B37: 68900000 | C37: =+B37*0.99 -> 68211000
B38: 494500000 | C38: =+B38*0.99 -> 489555000
B39: 238500000 | C39: =+B39*0.99 -> 236115000
B40: 378800000 | C40: =+B40*0.99 -> 375012000
A41: 29,03,2026 | C41: =+B41*0.99 -> 0 | D41: 230000000
C42: =+B42*0.99 -> 0 | D42: 900000000
C43: =+B43*0.99 -> 0 | D43: 1220000000
A45: 31,03,2026 | C45: =+B45*0.99 -> 0 | D45: 500000000
B46: 39900000 | C46: =+B46*0.99 -> 39501000
B47: 65900000 | C47: =+B47*0.99 -> 65241000
B48: 82800000 | C48: =+B48*0.99 -> 81972000
B49: 159600000 | C49: =+B49*0.99 -> 158004000
B50: 346000000 | C50: =+B50*0.99 -> 342540000
B51: 150000000 | C51: =+B51*0.99 -> 148500000
A52: 01,04,2026 | C52: =+B52*0.99 -> 0
B53: 30000000 | C53: =+B53*0.99 -> 29700000
B54: 400000000 | C54: =+B54*0.99 -> 396000000
A55: 02,04,2026 | C55: =+B55*0.99 -> 0 | D55: 200000000
B56: 99700000 | C56: =+B56*0.99 -> 98703000
B57: 199500000 | C57: =+B57*0.99 -> 197505000
B58: 109400000 | C58: =+B58*0.99 -> 108306000
B59: 154500000 | C59: =+B59*0.99 -> 152955000
B60: 107800000 | C60: =+B60*0.99 -> 106722000
A61: 03,04,2026 | C61: =+B61*0.99 -> 0
B62: 46900000 | C62: =+B62*0.99 -> 46431000
B63: 82300000 | C63: =+B63*0.99 -> 81477000
B64: 101800000 | C64: =+B64*0.99 -> 100782000
B65: 59800000 | C65: =+B65*0.99 -> 59202000
B66: 112600000 | C66: =+B66*0.99 -> 111474000
B67: 150000000 | C67: =+B67*0.99 -> 148500000
A68: 05,04,2026 | C68: =+B68*0.99 -> 0 | D68: 902000000
B69: 62900000 | C69: =+B69*0.99 -> 62271000
B70: 99900000 | C70: =+B70*0.99 -> 98901000
B71: 35200000 | C71: =+B71*0.99 -> 34848000
B72: 32000000 | C72: =+B72*0.99 -> 31680000
B73: 53000000 | C73: =+B73*0.99 -> 52470000
B74: 100000000 | C74: =+B74*0.99 -> 99000000
B75: 150000000 | C75: =+B75*0.99 -> 148500000
B76: 170000000 | C76: =+B76*0.99 -> 168300000
A77: 08,04,2026 | C77: =+B77*0.99 -> 0 | D77: 700000000
B78: 200000000 | C78: =+B78*0.99 -> 198000000
A79: 09,04,2026 | C79: =+B79*0.99 -> 0 | D79: 600000000
B80: 150000000 | C80: =+B80*0.99 -> 148500000
C81: =+B81*0.99 -> 0
A82: 10,04,2026 | C82: =+B82*0.99 -> 0 | D82: 400000000
B83: 174000000 | C83: =+B83*0.99 -> 172260000
B84: 267945000 | C84: =+B84*0.99 -> 265265550
A85: 11,04,2026 | C85: =+B85*0.99 -> 0 | D85: 300000000
C86: =+B86*0.99 -> 0
A87: 12,04,2026 | B87: 300000000 | C87: =+B87*0.99 -> 297000000 | D87: 800000000
B88: 121000000 | C88: =+B88*0.99 -> 119790000
B89: 322000000 | C89: =+B89*0.99 -> 318780000
A90: 14,04,2026 | C90: =+B90*0.99 -> 0
B91: 300000000 | C91: =+B91*0.99 -> 297000000
B92: 472400000 | C92: =+B92*0.99 -> 467676000
A93: 15,04,2026 | C93: =+B93*0.99 -> 0 | D93: 700000000
B94: 100000000 | C94: =+B94*0.99 -> 99000000
B95: 72800000 | C95: =+B95*0.99 -> 72072000
B96: 204500000 | C96: =+B96*0.99 -> 202455000
B97: 199500000 | C97: =+B97*0.99 -> 197505000
B98: 40000000 | C98: =+B98*0.99 -> 39600000
B99: 55800000 | C99: =+B99*0.99 -> 55242000
B100: 124500000 | C100: =+B100*0.99 -> 123255000
B101: 197500000 | C101: =+B101*0.99 -> 195525000
B102: 40000000 | C102: =+B102*0.99 -> 39600000
A103: 16,04,2026 | C103: =+B103*0.99 -> 0 | D103: 900000000
...
